Workbook
Name CPWD_Carriage_Item_Codes: '01_Carriage_of_Materials'!$A$180:$A$216
Name CPWD_Carriage_Materials: '01_Carriage_of_Materials'!$B$180:$B$216
Name CPWD_Carriage_Net_Payable: '01_Carriage_of_Materials'!$D$180:$D$216
Name CPWD_Carriage_Scope: '01_Carriage_of_Materials'!$A$260:$A$265
Name CPWD_Carriage12_Materials: '01_Carriage_of_Materials'!$B$221:$B$255
Name CPWD_Carriage14_Items: '01_Carriage_of_Materials'!$A$269:$A$272
Name CPWD_Carriage14_Table: '01_Carriage_of_Materials'!$A$269:$M$272
Name CPWD_DataSheet1: '01_Carriage_of_Materials'!$A$146:$H$175
Name CPWD_Earth_Items: '02_Earth_Work'!$P$100:$P$148
Name Factor_Cess: Global_Factors!$F$15
Name Factor_CPOH: Global_Factors!$F$14
Name Factor_GST: Global_Factors!$F$13
Name Factor_Sundries: Global_Factors!$F$16
Name Factor_Water: Global_Factors!$F$12
Name Master_Codes: Rates_Master!$A$2:$A$2142
Name Master_Rates_Table: Rates_Master!$A$2:$E$2142
Name Productivity_Summary: Labour_Machinery_Productivity!$A$6:$L$179
Name Productivity_Work_Types: Labour_Machinery_Productivity!$A$6:$A$179
Name Resolved_Cess_Factor: IF(Global_Factors!$E$15<>"",Global_Factors!$E$15,Global_Factors!$C$15)
Name Resolved_CPOH_Factor: IF(Global_Factors!$E$14<>"",Global_Factors!$E$14,Global_Factors!$C$14)
Name Resolved_GST_Factor: IF(Global_Factors!$E$13<>"",Global_Factors!$E$13,Global_Factors!$C$13)
Name Resolved_Water_Factor: IF(Global_Factors!$E$12<>"",Global_Factors!$E$12,Global_Factors!$C$12)
Name Table_5E_Master: '02_Earth_Work'!$P$100:$V$148
Name Table_5E_Resources: '02_Earth_Work'!$A$100:$O$277
Name Total_Active_Rates: COUNTA(Rates_Master!$A:$A)-1
Name Total_Labour_Norms: COUNTA(Labour_Machinery_Productivity!$C$183:$C$3206)
Name Total_Sundries_Norms: COUNTA(Sundries_Reference!$A:$A)-1
Name Total_Work_Type_Crews: ROWS(Labour_Machinery_Productivity!$A$6:$A$179)
Name XV_13_50_1: Resolved_Cross_Volume_Items!$G$66
Name XV_13_50_3: Resolved_Cross_Volume_Items!$G$86
Name XV_13_57_1: Resolved_Cross_Volume_Items!$G$107
Name XV_18_78: Resolved_Cross_Volume_Items!$G$126
Name XV_4_2_5: Resolved_Cross_Volume_Items!$G$44

Sheet Vol_1_Cover
A1: CPWD DAR 2019 | CUSTOM RATE ANALYSIS WORKBOOK — VOLUME 1 (Sub-Heads 01–12) Template File | Open → Work → Save As <Project Name>.xlsx | Do NOT rename this file
A3: ★ TEMPLATE — THIS FILE OPENS FRESH EACH TIME ★ Nothing you type here is saved to the template. To keep your work: File → Save As → give it a project/item name (e.g. "ItemAnalysis_CC_Flooring.xlsx").
A7: HOW TO USE THIS WORKBOOK 1. SHEET LAYOUT (each trade sheet 01–12 has the same structure): Panel 1 — Scope & Item Identification (yellow INPUT cells) Section 2 — Material Block (enter code → rate auto-fills from Rates_Master) Section 3 — Labour Block (same lookup pattern) Section 4 — Sundries, Markup Chain, Say Rate 2. YELLOW CELLS are user inputs. All other cells are calculated — do not overtype them. 3. RATES_MASTER: 2,200 CPWD DAR 2019 codes with basic rates. Type the code in Column B of the material/labour block; description, unit and rate fill automatically. To override a rate, type it directly in Column F of that row. 4. GLOBAL FACTORS (Water Tax, GST, CPOH, Cess, Sundries%) are in the Global_Factors sheet. Change them there once; all trade sheets update automatically. 5. IF YOU USE VOL. 2 (Sub-Heads 13–26): Before opening Vol. 2, save THIS file as: CPWD_DAR_2019_Custom_Rate_Analysis_Workbook_Vol_1.xlsx in the SAME FOLDER as Vol. 2. Vol. 2 external links depend on that exact filename. 6. REFERENCE SHEETS (read-only): Rates_Master, Global_Factors, Labour_Machinery_Productivity, Sundries_Reference, Resolved_Cross_Volume_Items — do not edit these; regenerate from source if needed.

Sheet Rates_Master
A1: Code | B1: Category | C1: Description / Specification | D1: Unit | E1: Basic Rate (Rs)
A2: 0001 | B2: Hire Charges of Plants & Machinery | C2: Hire charges of Coaltar Boiler 900 to 1400 litres | D2: day | E2: 800
A3: 0002 | B3: Hire Charges of Plants & Machinery | C3: Hire charges of Concrete Mixer 0.25 to 0.40 cum with Hopper | D3: day | E3: 800
A4: 0003 | B4: Hire Charges of Plants & Machinery | C4: Hire charges of Diesel Road Roller - 8 to 10 tonne | D4: day | E4: 3000
A5: 0004 | B5: Hire Charges of Plants & Machinery | C5: Production cost of concrete by batch mix plant | D5: cum | E5: 350
A6: 0005 | B6: Hire Charges of Plants & Machinery | C6: Hire charges of Diesel Truck - 9 tonne | D6: day | E6: 2000
A7: 0006 | B7: Hire Charges of Plants & Machinery | C7: Hire charges of Spraying machine including electric charges | D7: day | E7: 250
A8: 0007 | B8: Hire Charges of Plants & Machinery | C8: Hire charges of Coaltar Sprayer | D8: day | E8: 300
A9: 0008 | B9: Hire Charges of Plants & Machinery | C9: Hire charges of Barber green, drying, mixing and Asphalt Plant, | D9: day | E9: 7700
A10: 0009 | B10: Hire Charges of Plants & Machinery | C10: Pumping charges of concrete including Hire charges of pump, | D10: cum | E10: 210
A11: 0010 | B11: Hire Charges of Plants & Machinery | C11: Hire charges of Derrick monkey rope | D11: day | E11: 750
A12: 0011 | B12: Hire Charges of Plants & Machinery | C12: Hire charges of Pump set of capacity 4000 litres/hour | D12: day | E12: 700
A13: 0012 | B13: Hire Charges of Plants & Machinery | C13: Vibrator (Needle type 40 mm) | D13: day | E13: 370
... A2142: 9999 | B2142: Building Materials | C2142: Sundries | D2142: L.S. | E2142: 2

Sheet Global_Factors
A1: CPWD DELHI ANALYSIS OF RATES (DAR 2019) — GLOBAL STATUTORY FACTORS & PROJECT SETTINGS
A2: LEGEND: | B2: Standard Default Value (CPWD DAR 2019) | C2: Project Specific Override (User Input) | D2: Effective Value Used Across Workbook
A4: 1. PROJECT & CONTRACT PARAMETERS
A5: Project Name / Scope of Work: | B5: General Construction & Maintenance Estimates (Non-DSR Items) | D5: CPWD PLANT & MACHINERY HIRE CONVENTION (Item Codes 0001 to 0083): 1. Hire charges include services of operating staff, lubricating oil, diesel/petrol/kerosene, and all consumables for running the machinery, and exclude GST. 2. Hire charges are on per-day basis for a single shift of eight working hours. 3. Do not add duplicate fuel or operator lines unless using un-fueled codes (e.g. 0084 onwards).
A6: Project Location / Zone: | B6: Delhi & National Capital Region (CPWD Circle)
A7: Base Rates Schedule: | B7: CPWD Delhi Analysis of Rates (DAR 2019, Vol. 1)
A8: Location Cost Index: | B8: 118
A10: 2. STATUTORY MARKUPS & OVERHEAD COEFFICIENTS
A11: S.No | B11: Statutory Markup Component | C11: CPWD Default Rate | D11: Basis of Application | E11: Project Override Rate | F11: Effective Rate Applied | G11: CPWD DAR 2019 Rule & Statutory Basis
A12: 1 | B12: Water Charges | C12: 0.01 | D12: Applied on Direct Cost (W) | F12: =IF(E12<>"", E12, C12) -> 0.01 | G12: CPWD Standard: 1.0% on Direct Cost (W) for water consumed in construction/curing. Toggleable on trade sheets.
A13: 2 | B13: Goods and Services Tax (GST) | C13: 0.1405 | D13: Applied on Compounded Base (X = W + Water) | F13: =IF(E13<>"", E13, C13) -> 0.1405 | G13: CPWD DAR 2019 multiplying factor 0.1405 (14.05% effective works contract rate). Override here for 18% (0.18) or 12% (0.12).
A14: 3 | B14: Contractor's Profit & Overheads (CPOH) | C14: 0.15 | D14: Applied on Compounded Base (Y = X + GST) | F14: =IF(E14<>"", E14, C14) -> 0.15 | G14: CPWD DAR Standard: 15.0% for site management, head office overheads, tools, and contractor margin.
A15: 4 | B15: Building & Other Construction Workers Cess (BOCW) | C15: 0.01 | D15: Applied on Compounded Base (Z = Y + CPOH) | F15: =IF(E15<>"", E15, C15) -> 0.01 | G15: Statutory Labour Welfare Cess @ 1.0% per BOCW Welfare Cess Act, 1996.
A16: 5 | B16: Sundries Cost Index Multiplier | C16: 2 | D16: Applied on Base L.S. Allowance (PAR-2012 Base) | F16: =IF(E16<>"", E16, C16) -> 2 | G16: CPWD DAR 2019 Preface: Multiplier of 2.00 on base sundries allowance reflecting Delhi Cost Index (118 vs PAR-2012 base 100).
A18: 3. CPWD SUB-HEAD STATUTORY PRESETS & TRADE CONVENTIONS
A19: Sub-Head Code | B19: Trade Name | C19: Water (1%) | D19: GST (14.05%) | E19: CPOH (15%) | F19: Cess (1%) | G19: CPWD Trade Statutory Convention & Rationale
A20: 01 | B20: Carriage of Materials | C20: NO | D20: NO | E20: YES | F20: NO | G20: Mechanical transport applies 15% CPOH only. Water & Cess omitted (no water used). GST handled separately in freight.
A21: 02 | B21: Earth Work | C21: YES | D21: YES | E21: YES | F21: YES | G21: Standard 5-step compounding chain applied across labour & earthmoving equipment.
A22: 03 | B22: Mortars | C22: NO | D22: NO | E22: NO | F22: NO | G22: Intermediate building block. Stops at direct cost (W). Markup chain is OFF to prevent double taxation when imported into Masonry/Flooring.
A23: 04 | B23: Concrete Work | C23: YES | D23: YES | E23: YES | F23: YES | G23: Standard 5-step compounding chain applied over materials, labour, mixer & vibrator hire.
A24: 05 | B24: RCC Work | C24: YES | D24: YES | E24: YES | F24: YES | G24: Standard 5-step compounding chain. Shuttering and reinforcement are measured & priced separately in CPWD.
A25: 06 | B25: Masonry Work | C25: YES | D25: YES | E25: YES | F25: YES | G25: Imports un-marked Mortar rates as a Material line, then applies full markup chain once over the combined total.
A26: 07 | B26: Stone Work | C26: YES | D26: YES | E26: YES | F26: YES | G26: Imports Mortar rates as Material line; applies full markup chain over stone, mortar, dressing and laying labour.
A27: 08 | B27: Cladding Work | C27: YES | D27: YES | E27: YES | F27: YES | G27: Imports both bedding mortar and pointing mortar rates; applies full markup chain over stone veneer, mortar, scaffolding.
A28: 09 | B28: Wood & PVC Work | C28: YES | D28: YES | E28: YES | F28: YES | G28: Applies full markup chain over timber in scantling (with 5% wastage allowance) and carpentry labour.
A29: 10 | B29: Steel Work | C29: YES | D29: YES | E29: YES | F29: YES | G29: Applies the CPWD (W-A) rule: the priming coat (resolved item 13.50.3) already carries Water, GST, CPOH and Cess, so it is tagged A and every markup is computed on (W-A), (X-A), (Y-A), (Z-A). Verified against DAR item 10.1.
A30: 11 | B30: Flooring | C30: YES | D30: YES | E30: YES | F30: YES | G30: Imports Mortar/Concrete bed rate; applies full markup chain over tiles, stone, laying labour and polishing.
A31: 12 | B31: Roofing | C31: YES | D31: YES | E31: YES | F31: YES | G31: Applies full markup chain over roofing sheets, fixing J-hooks/bolts, limpet washers, and carpenter/fixing labour.

Sheet Labour_Machinery_Productivity
A1: CPWD DAR 2019 - LABOUR & MACHINERY PRODUCTIVITY, ORGANISED BY WORK TYPE (Section 1 = crew summary per work type / Section 2 = full source detail)
A2: Advisory reference only - nothing here is a compute dependency. "Typical Coeff" is the median day-coefficient observed across every DAR item of that work type, at the output basis shown; Low/High give the range actually printed in the book, and Observations says how many item lines back it. Carry a crew into a builder sheet as a starting point, then edit the coefficients to suit the item being priced.
A4: 1. CREW SUMMARY BY WORK TYPE (median day-coefficient per output basis)
A5: Work Type | B5: Trade Group | C5: Resource Type | D5: Code | E5: Resource Description | F5: Unit | G5: Typical Coeff | H5: Low | I5: High | J5: Observations | K5: Output Basis | L5: Basic Rate (Rs)
A6: Carriage - Mechanical Transport | B6: Carriage & Handling | C6: Labour | D6: 0114 | E6: Beldar | F6: day | G6: 4.625 | H6: 2 | I6: 10.66 | J6: 4 | K6: 1 unit | L6: 558
A7: Carriage - Mechanical Transport | B7: Carriage & Handling | C7: Machinery | D7: 0084 | E7: HIre charges of Diesel Truck - 9 tonne excluding diesel & mobile oil | F7: day | G7: 1 | H7: 1 | I7: 1 | J7: 1 | K7: 3 | L7: 1500
A8: Loading / Unloading at Siding | B8: Carriage & Handling | C8: Labour | D8: 0114 | E8: Beldar | F8: day | G8: 3.75 | H8: 3.75 | I8: 3.75 | J8: 1 | K8: 1 unit | L8: 558
A9: Earthwork - Excavation | B9: Earthwork | C9: Labour | D9: 0114 | E9: Beldar | F9: day | G9: 1.1 | H9: 0.06 | I9: 16.5 | J9: 47 | K9: 1 unit | L9: 558
A10: Earthwork - Excavation | B10: Earthwork | C10: Labour | D10: 0112 | E10: Carpenter 2nd class | F10: day | G10: 0.25 | H10: 0.03 | I10: 1.5 | J10: 19 | K10: a manhole 1 | L10: 679
A11: Earthwork - Excavation | B11: Earthwork | C11: Labour | D11: 0115 | E11: Coolie | F11: day | G11: 1.67 | H11: 0.17 | I11: 7 | J11: 12 | K11: 10 cum | L11: 558
A12: Earthwork - Excavation | B12: Earthwork | C12: Labour | D12: 0101 | E12: Bhisti | F12: day | G12: 0.4 | H12: 0.35 | I12: 0.5 | J12: 4 | K12: 10 cum | L12: 617
A13: Earthwork - Excavation | B13: Earthwork | C13: Labour | D13: 0128 | E13: Mate | F13: day | G13: 0.32 | H13: 0.1 | I13: 0.4 | J13: 3 | K13: 10 cum | L13: 617
A14: Earthwork - Excavation | B14: Earthwork | C14: Labour | D14: 0113 | E14: Chowkidar | F14: day | G14: 0.008 | H14: 0.008 | I14: 0.008 | J14: 2 | K14: 10 cum | L14: 558
A15: Earthwork - Excavation | B15: Earthwork | C15: Labour | D15: 0124 | E15: Mason (brick layer) 2nd class | F15: day | G15: 0.275 | H15: 0.05 | I15: 0.5 | J15: 2 | K15: 9 sqm | L15: 679
A16: Earthwork - Excavation | B16: Earthwork | C16: Machinery | D16: 0003 | E16: Hire charges of Diesel Road Roller - 8 to 10 tonne | F16: day | G16: 0.008 | H16: 0.008 | I16: 0.008 | J16: 2 | K16: 10 cum | L16: 3000
A17: Earthwork - Excavation | B17: Earthwork | C17: Machinery | D17: 0018 | E17: Hire and running charges of loader. | F17: day | G17: 0.041 | H17: 0.041 | I17: 0.041 | J17: 2 | K17: 10 cum | L17: 5000
... A179: Painting & Priming | B179: Finishing | C179: Labour | D179: 0131 | E179: Painter | F179: day | G179: 1.13 | H179: 0.15 | I179: 10.37 | J179: 20 | K179: a roof with each sloping side 18 | L179: 679
A181: 2. FULL SOURCE DETAIL (every LABOUR / MACHINERY line mined from the base volumes)
A182: Work Type | B182: Trade Group | C182: Sub-Head | D182: DAR Item No | E182: Item Nomenclature | F182: Output Basis | G182: Resource Type | H182: Code | I182: Resource Description | J182: Unit | K182: Day Coeff / Qty | L182: Basic Rate (Rs)
A183: Carriage - Mechanical Transport | B183: Carriage & Handling | C183: 01_Carriage_of_Materials | F183: 3 | G183: Machinery | H183: 0084 | I183: HIre charges of Diesel Truck - 9 tonne excluding diesel & mobile oil | J183: day | K183: 1 | L183: 1500
A184: Carriage - Mechanical Transport | B184: Carriage & Handling | C184: 01_Carriage_of_Materials | F184: 3 | G184: Labour | H184: 0114 | I184: Beldar | J184: day | K184: 6 | L184: 558
A185: Carriage - Mechanical Transport | B185: Carriage & Handling | C185: 01_Carriage_of_Materials | F185: 3 | G185: Labour | H185: 0114 | I185: Beldar | J185: day | K185: 0 | L185: 558
A186: Carriage - Mechanical Transport | B186: Carriage & Handling | C186: 01_Carriage_of_Materials | F186: 3 | G186: Labour | H186: 0115 | I186: Coolie | J186: day | K186: 0 | L186: 558
A187: Carriage - Mechanical Transport | B187: Carriage & Handling | C187: 01_Carriage_of_Materials | D187: 1.2.10 | E187: Steam Coal | F187: 1 unit | G187: Labour | H187: 0114 | I187: Beldar | J187: Day | K187: 0 | L187: 558
A188: Carriage - Mechanical Transport | B188: Carriage & Handling | C188: 01_Carriage_of_Materials | D188: 1.2.10 | E188: Steam Coal | F188: 1 unit | G188: Labour | H188: 0115 | I188: Coolie | J188: Day | K188: 0 | L188: 558
A189: Carriage - Mechanical Transport | B189: Carriage & Handling | C189: 01_Carriage_of_Materials | D189: 1.4.1 | E189: Steel Details of 44 tonnes of steel LABOUR | F189: 1 unit | G189: Labour | H189: 0114 | I189: Beldar | J189: day | K189: 10.66 | L189: 558
A190: Carriage - Mechanical Transport | B190: Carriage & Handling | C190: 01_Carriage_of_Materials | D190: 1.4.2 | E190: G.I., C.I., R.C.C. or C.C. pipes upto 500 mm dia and similar heavy materials Details of cost of unlo | F190: 1 unit | G190: Labour | H190: 0114 | I190: Beldar | J190: day | K190: 2 | L190: 558
A191: Carriage - Mechanical Transport | B191: Carriage & Handling | C191: 01_Carriage_of_Materials | D191: 1.4.2 | E191: G.I., C.I., R.C.C. or C.C. pipes upto 500 mm dia and similar heavy materials Details of cost of unlo | F191: 1 unit | G191: Labour | H191: 0114 | I191: Beldar | J191: day | K191: 3.25 | L191: 558
A192: Loading / Unloading at Siding | B192: Carriage & Handling | C192: 01_Carriage_of_Materials | D192: 1.3 | E192: Loading in or unloading cement from the railway wagons at siding and carrying the same from or into | F192: 1 unit | G192: Labour | H192: 0114 | I192: Beldar | J192: day | K192: 3.75 | L192: 558
A193: Earthwork - Excavation | B193: Earthwork | C193: 02_Earth_Work | D193: 1.2.2 | E193: Rate as per item no 1.2.2 of | F193: 1 unit | G193: Labour | H193: 0114 | I193: Beldar (1/2x0.89=0.45 day) | J193: day | K193: 0.45 | L193: 558
A194: Earthwork - Excavation | B194: Earthwork | C194: 02_Earth_Work | D194: 1.2.2 | E194: Rate as per item no 1.2.2 of | F194: 1 unit | G194: Labour | H194: 0101 | I194: Bhisti | J194: day | K194: 0.35 | L194: 617
A195: Earthwork - Excavation | B195: Earthwork | C195: 02_Earth_Work | D195: 2.1.1 | E195: All kinds of soil Details of cost for 100 Sqm LABOUR | F195: 100 Sqm | G195: Labour | H195: 0114 | I195: Beldar | J195: day | K195: 6.8 | L195: 558
A196: Earthwork - Excavation | B196: Earthwork | C196: 02_Earth_Work | D196: 2.1.1 | E196: All kinds of soil Details of cost for 100 Sqm LABOUR | F196: 100 Sqm | G196: Labour | H196: 0115 | I196: Coolie | J196: day | K196: 5.6 | L196: 558
A197: Earthwork - Excavation | B197: Earthwork | C197: 02_Earth_Work | D197: 2.16.1 | E197: Depth not exceeding 1.5 m Details of cost for a trench 30m long and 1.5m deep area 2x30x1.50=90 sqm | F197: a trench 30m long and 1 | G197: Labour | H197: 0112 | I197: Carpenter 2nd class | J197: day | K197: 0.5 | L197: 679
A198: Earthwork - Excavation | B198: Earthwork | C198: 02_Earth_Work | D198: 2.16.1 | E198: Depth not exceeding 1.5 m Details of cost for a trench 30m long and 1.5m deep area 2x30x1.50=90 sqm | F198: a trench 30m long and 1 | G198: Labour | H198: 0114 | I198: Beldar | J198: day | K198: 1 | L198: 558
... A3206: Painting & Priming | B3206: Finishing | C3206: 12_Roofing | D3206: 12.63 | E3206: Providing and applying two coats of High Albedo paint having minimum Solar Reflective Index (SRI) 10 | F3206: 10 Sqm | G3206: Labour | H3206: 0131 | I3206: Painter | J3206: day | K3206: 0.54 | L3206: 679

Sheet Sundries_Reference
A1: Sub-Head | B1: DAR Item No | C1: Item Nomenclature | D1: Output Basis | E1: Sundries Description | F1: Base L.S. Quantity | G1: Index Multiplier | H1: Total Amount (Rs)
A2: 01_Carriage_of_Materials | B2: 1.3 | C2: Loading in or unloading cement from the railway wagons at siding and carrying the same from or into | D2: 1 unit | E2: Sundries Add for sweeping the wagon, screening the swept cement and filling the same in bags | F2: 2.62 | G2: 2 | H2: 5.24
A3: 01_Carriage_of_Materials | B3: 1.4.2 | C3: G.I., C.I., R.C.C. or C.C. pipes upto 500 mm dia and similar heavy materials Details of cost of unlo | D3: 1 unit | E3: Sundries | F3: 3.1 | G3: 2 | H3: 6.2
A4: 01_Carriage_of_Materials | B4: 1.4.2 | C4: G.I., C.I., R.C.C. or C.C. pipes upto 500 mm dia and similar heavy materials Details of cost of unlo | D4: 1 unit | E4: Extra for fixing crane including labour involved | F4: 91.15 | G4: 2 | H4: 182.3
A5: 01_Carriage_of_Materials | B5: 1.4.2 | C5: G.I., C.I., R.C.C. or C.C. pipes upto 500 mm dia and similar heavy materials Details of cost of unlo | D5: 1 unit | E5: Sundries | F5: 7.4 | G5: 2 | H5: 14.8
A6: 02_Earth_Work | B6: 2.2.1 | C6: All kinds of soil Details of cost for 10 cum. LABOUR | D6: 10 cum | E6: Sundries | F6: 2.73 | G6: 2 | H6: 5.46
A7: 02_Earth_Work | B7: 2.3.1 | C7: All kinds of soil Details of cost for 10 cum. LABOUR | D7: 10 cum | E7: Sundries | F7: 2.73 | G7: 2 | H7: 5.46
A8: 02_Earth_Work | B8: 2.4 | C8: Deduct for not rolling with power roller of minimum 8 tonnes for banking excavated earth in layers n | D8: 10 cum | E8: Sundries | F8: 1.82 | G8: 2 | H8: 3.64
A9: 02_Earth_Work | B9: 2.7.1 | C9: Ordinary rock Details of cost for 10 cum. MACHINERY | D9: 10 cum | E9: Sundries | F9: 10.79 | G9: 2 | H9: 21.58
A10: 02_Earth_Work | B10: 2.7.2 | C10: Hard rock (requiring blasting) Details of cost for 10 cum. MACHINERY | D10: 10 cum | E10: Sundries | F10: 16.12 | G10: 2 | H10: 32.24
A11: 02_Earth_Work | B11: 2.7.3 | C11: Hard rock (blasting prohibited) Details of cost for 10 cum. MACHINERY | D11: 10 cum | E11: Sundries | F11: 16.12 | G11: 2 | H11: 32.24
A12: 02_Earth_Work | B12: 2.9.1 | C12: Ordinary rock Details of cost for 10 cum. MACHINERY | D12: 10 cum | E12: Sundries | F12: 13.52 | G12: 2 | H12: 27.04
A13: 02_Earth_Work | B13: 2.9.2 | C13: Hard rock (requiring blasting) Details of cost for 10 cum. MACHINERY | D13: 10 cum | E13: Sundries | F13: 18.85 | G13: 2 | H13: 37.7
... A1218: 12_Roofing | B1218: 12.63 | C1218: Providing and applying two coats of High Albedo paint having minimum Solar Reflective Index (SRI) 10 | D1218: 10 Sqm | E1218: Sundries (Brushes & T&P etc. | F1218: 13.52 | G1218: 2 | H1218: 27.04

Sheet Resolved_Cross_Volume_Items
A1: CPWD DAR 2019 - RESOLVED CROSS-VOLUME ITEMS (Vol.2 items re-derived from WB1 data only)
A2: LEGEND: | B2: User Input (Editable) | C2: Auto Lookup from Rates_Master | D2: Calculated | E2: Resolved Rate | F2: CPWD Rule / Note
A3: Vol.1 builder sheets 08, 09 and 10 need four items printed in Vol.2. Each is re-derived here line-by-line from this workbook's own Rates_Master catalogue and computed to a final rate, so WB1 never needs Vol.2 open. Consuming sheets reference the RESULT (see summary below), and tag that line "A" so it is excluded from their own markup chain per the CPWD (W-A) convention.
A5: 1. RESOLVED RATE SUMMARY (referenced by the consuming builder sheets)
A6: Item No | B6: Source Sub-Head | C6: Nomenclature | D6: Unit | E6: Basis | F6: DAR 2019 Printed Rate | G6: Resolved Rate (live) | H6: Defined Name | I6: Consumed By
A7: 4.2.5 | B7: 04 Concrete Work (Vol.1) | C7: Providing and laying in position cement concrete of specified grade excluding the cost of centering and shuttering - 1:3:6 (1 cement : 3 coarse sand (zone-III) : 6 graded stone aggregate 20 mm nominal size) | D7: cum | E7: 1 | F7: 8025 | G7: =G44 -> 8025 | H7: XV_4_2_5 | I7: Feeds resolved item 18.78 below (not a Vol.2 item - re-derived here so 18.78 is self-contained)
A8: 13.50.1 | B8: 13 Finishing (Vol.2) | C8: Applying priming coat with ready mixed pink or Grey primer of approved brand and manufacture on wood work (hard and soft wood) | D8: sqm | E8: 10 | F8: 57.05 | G8: =G66 -> 57.05 | H8: XV_13_50_1 | I8: 09_Wood_and_PVC_Work (primer on wood work)
A9: 13.50.3 | B9: 13 Finishing (Vol.2) | C9: Applying priming coat with ready mixed red oxide zinc chromate primer of approved brand and manufacture on steel / iron work | D9: sqm | E9: 10 | F9: 50.7 | G9: =G86 -> 50.7 | H9: XV_13_50_3 | I9: 10_Steel_Work (priming coat), 09_Wood_and_PVC_Work (steel fittings)
A10: 13.57.1 | B10: 13 Finishing (Vol.2) | C10: Painting with oil type wood preservative of approved brand and manufacture - new work (two or more coats) | D10: sqm | E10: 10 | F10: 44.5 | G10: =G107 -> 44.5 | H10: XV_13_57_1 | I10: 09_Wood_and_PVC_Work (preservative treatment on timber)
A11: 18.78 | B11: 18 Water Supply (Vol.2) | C11: Making chases up to 7.5 x 7.5 cm in walls including making good and finishing the same with cement concrete 1:3:6 | D11: metre | E11: 10 | F11: 154.15 | G11: =G126 -> 154.15 | H11: XV_18_78 | I11: 08_Cladding_Work (chase cutting for concealed fixings / services)
A13: 2. FULL LINE-BY-LINE BREAKDOWNS (every rate traced to Rates_Master)
A14: ITEM 4.2.5 - 04 Concrete Work (Vol.1) - Providing and laying in position cement concrete of specified grade excluding the cost of centering and shuttering - 1:3:6 (1 cement : 3 coarse sand (zone-III) : 6 graded stone aggregate 20 mm nominal size)
A15: Basis: | B15: 1 | C15: cum | D15: Consumed by: | E15: Feeds resolved item 18.78 below (not a Vol.2 item - re-derived here so 18.78 is self-contained)
A16: Line | B16: Code / Source | C16: Description / Specification | D16: Unit | E16: Quantity / Coeff | F16: Basic Rate (Rs) | G16: Amount (Rs) | H16: Source Reference / Remarks | I16: Markup Tag
A17: 1 | B17: 0295 | C17: =IFERROR(INDEX(Rates_Master!$C:$C, MATCH(B17, Rates_Master!$A:$A, 0)), "Code not found in Rates_Master") -> Stone Aggregate (Single size) : 20 mm nominal size | D17: =IFERROR(INDEX(Rates_Master!$D:$D, MATCH(B17, Rates_Master!$A:$A, 0)), "") -> cum | E17: 0.7 | F17: =IFERROR(INDEX(Rates_Master!$E:$E, MATCH(B17, Rates_Master!$A:$A, 0)), 0) -> 1350 | G17: =ROUND(E17 * F17, 2) -> 945 | H17: Stone Aggregate (single size) 20 mm nominal size
A18: 2 | B18: 0297 | C18: =IFERROR(INDEX(Rates_Master!$C:$C, MATCH(B18, Rates_Master!$A:$A, 0)), "Code not found in Rates_Master") -> Stone Aggregate (Single size) : 10 mm nominal size | D18: =IFERROR(INDEX(Rates_Master!$D:$D, MATCH(B18, Rates_Master!$A:$A, 0)), "") -> cum | E18: 0.24 | F18: =IFERROR(INDEX(Rates_Master!$E:$E, MATCH(B18, Rates_Master!$A:$A, 0)), 0) -> 1350 | G18: =ROUND(E18 * F18, 2) -> 324 | H18: Stone Aggregate (single size) 10 mm nominal size
A19: 3 | B19: 2202 | C19: =IFERROR(INDEX(Rates_Master!$C:$C, MATCH(B19, Rates_Master!$A:$A, 0)), "Code not found in Rates_Master") -> Carriage of Stone aggregate below 40 mm nominal size | D19: =IFERROR(INDEX(Rates_Master!$D:$D, MATCH(B19, Rates_Master!$A:$A, 0)), "") -> cum | E19: 0.94 | F19: =IFERROR(INDEX(Rates_Master!$E:$E, MATCH(B19, Rates_Master!$A:$A, 0)), 0) -> 103.77 | G19: =ROUND(E19 * F19, 2) -> 97.54 | H19: Carriage of Stone aggregate below 40 mm nominal size
A20: 4 | B20: 0982 | C20: =IFERROR(INDEX(Rates_Master!$C:$C, MATCH(B20, Rates_Master!$A:$A, 0)), "Code not found in Rates_Master") -> Coarse sand (zone III) | D20: =IFERROR(INDEX(Rates_Master!$D:$D, MATCH(B20, Rates_Master!$A:$A, 0)), "") -> cum | E20: 0.47 | F20: =IFERROR(INDEX(Rates_Master!$E:$E, MATCH(B20, Rates_Master!$A:$A, 0)), 0) -> 1350 | G20: =ROUND(E20 * F20, 2) -> 634.5 | H20: Coarse sand (zone III)
A21: 5 | B21: 2203 | C21: =IFERROR(INDEX(Rates_Master!$C:$C, MATCH(B21, Rates_Master!$A:$A, 0)), "Code not found in Rates_Master") -> Carriage of Coarse sand | D21: =IFERROR(INDEX(Rates_Master!$D:$D, MATCH(B21, Rates_Master!$A:$A, 0)), "") -> cum | E21: 0.47 | F21: =IFERROR(INDEX(Rates_Master!$E:$E, MATCH(B21, Rates_Master!$A:$A, 0)), 0) -> 103.77 | G21: =ROUND(E21 * F21, 2) -> 48.77 | H21: Carriage of Coarse sand
A22: 6 | B22: 0367 | C22: =IFERROR(INDEX(Rates_Master!$C:$C, MATCH(B22, Rates_Master!$A:$A, 0)), "Code not found in Rates_Master") -> Portland Cement (OPC-43 Grade) | D22: =IFERROR(INDEX(Rates_Master!$D:$D, MATCH(B22, Rates_Master!$A:$A, 0)), "") -> tonne | E22: 0.22 | F22: =IFERROR(INDEX(Rates_Master!$E:$E, MATCH(B22, Rates_Master!$A:$A, 0)), 0) -> 4940 | G22: =ROUND(E22 * F22, 2) -> 1086.8 | H22: Portland Cement (0.15674 cum = 0.22 tonne)
A23: 7 | B23: 2209 | C23: =IFERROR(INDEX(Rates_Master!$C:$C, MATCH(B23, Rates_Master!$A:$A, 0)), "Code not found in Rates_Master") -> Carriage of Cement | D23: =IFERROR(INDEX(Rates_Master!$D:$D, MATCH(B23, Rates_Master!$A:$A, 0)), "") -> tonne | E23: 0.22 | F23: =IFERROR(INDEX(Rates_Master!$E:$E, MATCH(B23, Rates_Master!$A:$A, 0)), 0) -> 92.24 | G23: =ROUND(E23 * F23, 2) -> 20.29 | H23: Carriage of Cement
A24: 8 | B24: 0114 | C24: =IFERROR(INDEX(Rates_Master!$C:$C, MATCH(B24, Rates_Master!$A:$A, 0)), "Code not found in Rates_Master") -> Beldar | D24: =IFERROR(INDEX(Rates_Master!$D:$D, MATCH(B24, Rates_Master!$A:$A, 0)), "") -> day | E24: 0.9 | F24: =IFERROR(INDEX(Rates_Master!$E:$E, MATCH(B24, Rates_Master!$A:$A, 0)), 0) -> 558 | G24: =ROUND(E24 * F24, 2) -> 502.2 | H24: Beldar
A25: 9 | B25: 0115 | C25: =IFERROR(INDEX(Rates_Master!$C:$C, MATCH(B25, Rates_Master!$A:$A, 0)), "Code not found in Rates_Master") -> Coolie | D25: =IFERROR(INDEX(Rates_Master!$D:$D, MATCH(B25, Rates_Master!$A:$A, 0)), "") -> day | E25: 0.78 | F25: =IFERROR(INDEX(Rates_Master!$E:$E, MATCH(B25, Rates_Master!$A:$A, 0)), 0) -> 558 | G25: =ROUND(E25 * F25, 2) -> 435.24 | H25: Coolie
A26: 10 | B26: 0101 | C26: =IFERROR(INDEX(Rates_Master!$C:$C, MATCH(B26, Rates_Master!$A:$A, 0)), "Code not found in Rates_Master") -> Bhisti | D26: =IFERROR(INDEX(Rates_Master!$D:$D, MATCH(B26, Rates_Master!$A:$A, 0)), "") -> day | E26: 0.7 | F26: =IFERROR(INDEX(Rates_Master!$E:$E, MATCH(B26, Rates_Master!$A:$A, 0)), 0) -> 617 | G26: =ROUND(E26 * F26, 2) -> 431.9 | H26: Bhisti
A27: 11 | B27: 0123 | C27: =IFERROR(INDEX(Rates_Master!$C:$C, MATCH(B27, Rates_Master!$A:$A, 0)), "Code not found in Rates_Master") -> Mason (brick layer) 1st class | D27: =IFERROR(INDEX(Rates_Master!$D:$D, MATCH(B27, Rates_Master!$A:$A, 0)), "") -> day | E27: 0.06 | F27: =IFERROR(INDEX(Rates_Master!$E:$E, MATCH(B27, Rates_Master!$A:$A, 0)), 0) -> 738 | G27: =ROUND(E27 * F27, 2) -> 44.28 | H27: Mason (brick layer) 1st class
A28: 12 | B28: 0124 | C28: =IFERROR(INDEX(Rates_Master!$C:$C, MATCH(B28, Rates_Master!$A:$A, 0)), "Code not found in Rates_Master") -> Mason (brick layer) 2nd class | D28: =IFERROR(INDEX(Rates_Master!$D:$D, MATCH(B28, Rates_Master!$A:$A, 0)), "") -> day | E28: 0.06 | F28: =IFERROR(INDEX(Rates_Master!$E:$E, MATCH(B28, Rates_Master!$A:$A, 0)), 0) -> 679 | G28: =ROUND(E28 * F28, 2) -> 40.74 | H28: Mason (brick layer) 2nd class
... A31: 15 | B31: 0115 | C31: =IFERROR(INDEX(Rates_Master!$C:$C, MATCH(B31, Rates_Master!$A:$A, 0)), "Code not found in Rates_Master") -> Coolie | D31: =IFERROR(INDEX(Rates_Master!$D:$D, MATCH(B31, Rates_Master!$A:$A, 0)), "") -> day | E31: 1.88 | F31: =IFERROR(INDEX(Rates_Master!$E:$E, MATCH(B31, Rates_Master!$A:$A, 0)), 0) -> 558 | G31: =ROUND(E31 * F31, 2) -> 1049.04 | H31: Coolie - extra labour lifting material upto floor V level (0.75 x 2.5 = 1.88)
A32: 16 | B32: 9999 | C32: Scaffolding (17.60 x 2.5 avg.) | D32: L.S. | E32: 114.4 | F32: =Factor_Sundries -> 2 | G32: =ROUND(E32 * F32, 2) -> 228.8 | H32: Base L.S. allowance x Cost Index Multiplier (Global_Factors)
A33: 17 | B33: 9999 | C33: Sundries | D33: L.S. | E33: 13.52 | F33: =Factor_Sundries -> 2 | G33: =ROUND(E33 * F33, 2) -> 27.04 | H33: Base L.S. allowance x Cost Index Multiplier (Global_Factors)
A34: TOTAL DIRECT COST "W" (all lines above): | G34: =ROUND(SUM(G17:G33), 2) -> 5998.04 | H34: Book value of W for item 4.2.5 = Rs 5,998.05
A35: Less "A" - imported lines already carrying statutory markups: | G35: =ROUND(SUMIF($I$17:$I$33, "A", $G$17:$G$33), 2) -> 0 | H35: CPWD convention: markups are computed on (W-A), (X-A), (Y-A), (Z-A). A line tagged "A" is an imported rate that already includes Water, GST, CPOH and Cess.
A36: X1 | B36: YES | C36: Add Water Charges on (W - A) | E36: =G34 - G35 -> 5998.04 | F36: =Factor_Water -> 0.01 | G36: =IF(B36="YES", ROUND(E36 * F36, 2), 0) -> 59.98 | H36: CPWD: 1% water charges, computed on the direct cost net of A-tagged imports.
A37: X | B37: - | C37: Subtotal "X" (W + Water Charges) | G37: =G34 + G36 -> 6058.02 | H37: Running compounded subtotal
A38: Y1 | B38: YES | C38: Add GST on (X - A) | E38: =G37 - G35 -> 6058.02 | F38: =Factor_GST -> 0.1405 | G38: =IF(B38="YES", ROUND(E38 * F38, 2), 0) -> 851.15 | H38: CPWD DAR 2019 works contract multiplying factor 0.1405, net of A.
A39: Y | B39: - | C39: Subtotal "Y" (X + GST) | G39: =G37 + G38 -> 6909.17 | H39: Running compounded subtotal
A40: Z1 | B40: YES | C40: Add Contractor Profit & Overheads on (Y - A) | E40: =G39 - G35 -> 6909.17 | F40: =Factor_CPOH -> 0.15 | G40: =IF(B40="YES", ROUND(E40 * F40, 2), 0) -> 1036.38 | H40: Standard 15% CPOH, net of A.
A41: Z | B41: - | C41: Subtotal "Z" (Y + CPOH) | G41: =G39 + G40 -> 7945.55 | H41: Running compounded subtotal
A42: Z2 | B42: YES | C42: Add BOCW Welfare Cess on (Z - A) | E42: =G41 - G35 -> 7945.55 | F42: =Factor_Cess -> 0.01 | G42: =IF(B42="YES", ROUND(E42 * F42, 2), 0) -> 79.46 | H42: Statutory 1% BOCW Welfare Cess, net of A.
A43: Cost of 1.00 cum: | G43: =ROUND(G41 + G42, 2) -> 8025.01
A44: RESOLVED RATE per 1.00 cum (SAY): | G44: =MROUND(G43 / 1, 0.05) -> 8025 | H44: CPWD DAR 2019 printed Say rate for this item = Rs 8,025.00 per cum. Rounded with MROUND(x, 0.05) because CPWD quotes every Say rate to the nearest 5 paise. Any difference means a Rates_Master rate has been edited away from the 2019 base.
A46: ITEM 13.50.1 - 13 Finishing (Vol.2) - Applying priming coat with ready mixed pink or Grey primer of approved brand and manufacture on wood work (hard and soft wood)
A47: Basis: | B47: 10 | C47: sqm | D47: Consumed by: | E47: 09_Wood_and_PVC_Work (primer on wood work)
A48: Line | B48: Code / Source | C48: Description / Specification | D48: Unit | E48: Quantity / Coeff | F48: Basic Rate (Rs) | G48: Amount (Rs) | H48: Source Reference / Remarks | I48: Markup Tag
A49: 1 | B49: 0823 | C49: =IFERROR(INDEX(Rates_Master!$C:$C, MATCH(B49, Rates_Master!$A:$A, 0)), "Code not found in Rates_Master") -> Pink primer (for wood) | D49: =IFERROR(INDEX(Rates_Master!$D:$D, MATCH(B49, Rates_Master!$A:$A, 0)), "") -> litre | E49: 0.75 | F49: =IFERROR(INDEX(Rates_Master!$E:$E, MATCH(B49, Rates_Master!$A:$A, 0)), 0) -> 105 | G49: =ROUND(E49 * F49, 2) -> 78.75 | H49: Pink primer (for wood)
A50: 2 | B50: 0131 | C50: =IFERROR(INDEX(Rates_Master!$C:$C, MATCH(B50, Rates_Master!$A:$A, 0)), "Code not found in Rates_Master") -> Painter | D50: =IFERROR(INDEX(Rates_Master!$D:$D, MATCH(B50, Rates_Master!$A:$A, 0)), "") -> day | E50: 0.25 | F50: =IFERROR(INDEX(Rates_Master!$E:$E, MATCH(B50, Rates_Master!$A:$A, 0)), 0) -> 679 | G50: =ROUND(E50 * F50, 2) -> 169.75 | H50: Painter
A51: 3 | B51: 0115 | C51: =IFERROR(INDEX(Rates_Master!$C:$C, MATCH(B51, Rates_Master!$A:$A, 0)), "Code not found in Rates_Master") -> Coolie | D51: =IFERROR(INDEX(Rates_Master!$D:$D, MATCH(B51, Rates_Master!$A:$A, 0)), "") -> day | E51: 0.25 | F51: =IFERROR(INDEX(Rates_Master!$E:$E, MATCH(B51, Rates_Master!$A:$A, 0)), 0) -> 558 | G51: =ROUND(E51 * F51, 2) -> 139.5 | H51: Coolie
A52: 4 | B52: 9999 | C52: Putty | D52: L.S. | E52: 2.73 | F52: =Factor_Sundries -> 2 | G52: =ROUND(E52 * F52, 2) -> 5.46 | H52: Base L.S. allowance x Cost Index Multiplier (Global_Factors)
A53: 5 | B53: 9999 | C53: Carriage of material | D53: L.S. | E53: 0.39 | F53: =Factor_Sundries -> 2 | G53: =ROUND(E53 * F53, 2) -> 0.78 | H53: Base L.S. allowance x Cost Index Multiplier (Global_Factors)
A54: 6 | B54: 9999 | C54: Brushes, sand paper etc. | D54: L.S. | E54: 5.33 | F54: =Factor_Sundries -> 2 | G54: =ROUND(E54 * F54, 2) -> 10.66 | H54: Base L.S. allowance x Cost Index Multiplier (Global_Factors)
A55: 7 | B55: 9999 | C55: Sundries | D55: L.S. | E55: 10.79 | F55: =Factor_Sundries -> 2 | G55: =ROUND(E55 * F55, 2) -> 21.58 | H55: Base L.S. allowance x Cost Index Multiplier (Global_Factors)
A56: TOTAL DIRECT COST "W" (all lines above): | G56: =ROUND(SUM(G49:G55), 2) -> 426.48 | H56: Book value of W for item 13.50.1 = Rs 426.48
A57: Less "A" - imported lines already carrying statutory markups: | G57: =ROUND(SUMIF($I$49:$I$55, "A", $G$49:$G$55), 2) -> 0 | H57: CPWD convention: markups are computed on (W-A), (X-A), (Y-A), (Z-A). A line tagged "A" is an imported rate that already includes Water, GST, CPOH and Cess.
A58: X1 | B58: YES | C58: Add Water Charges on (W - A) | E58: =G56 - G57 -> 426.48 | F58: =Factor_Water -> 0.01 | G58: =IF(B58="YES", ROUND(E58 * F58, 2), 0) -> 4.26 | H58: CPWD: 1% water charges, computed on the direct cost net of A-tagged imports.
A59: X | B59: - | C59: Subtotal "X" (W + Water Charges) | G59: =G56 + G58 -> 430.74 | H59: Running compounded subtotal
A60: Y1 | B60: YES | C60: Add GST on (X - A) | E60: =G59 - G57 -> 430.74 | F60: =Factor_GST -> 0.1405 | G60: =IF(B60="YES", ROUND(E60 * F60, 2), 0) -> 60.52 | H60: CPWD DAR 2019 works contract multiplying factor 0.1405, net of A.
A61: Y | B61: - | C61: Subtotal "Y" (X + GST) | G61: =G59 + G60 -> 491.26 | H61: Running compounded subtotal
A62: Z1 | B62: YES | C62: Add Contractor Profit & Overheads on (Y - A) | E62: =G61 - G57 -> 491.26 | F62: =Factor_CPOH -> 0.15 | G62: =IF(B62="YES", ROUND(E62 * F62, 2), 0) -> 73.69 | H62: Standard 15% CPOH, net of A.
A63: Z | B63: - | C63: Subtotal "Z" (Y + CPOH) | G63: =G61 + G62 -> 564.95 | H63: Running compounded subtotal
A64: Z2 | B64: YES | C64: Add BOCW Welfare Cess on (Z - A) | E64: =G63 - G57 -> 564.95 | F64: =Factor_Cess -> 0.01 | G64: =IF(B64="YES", ROUND(E64 * F64, 2), 0) -> 5.65 | H64: Statutory 1% BOCW Welfare Cess, net of A.
A65: Cost of 10.00 sqm: | G65: =ROUND(G63 + G64, 2) -> 570.6
A66: RESOLVED RATE per 1.00 sqm (SAY): | G66: =MROUND(G65 / 10, 0.05) -> 57.05 | H66: CPWD DAR 2019 printed Say rate for this item = Rs 57.05 per sqm. Rounded with MROUND(x, 0.05) because CPWD quotes every Say rate to the nearest 5 paise. Any difference means a Rates_Master rate has been edited away from the 2019 base.
A68: ITEM 13.50.3 - 13 Finishing (Vol.2) - Applying priming coat with ready mixed red oxide zinc chromate primer of approved brand and manufacture on steel / iron work
A69: Basis: | B69: 10 | C69: sqm | D69: Consumed by: | E69: 10_Steel_Work (priming coat), 09_Wood_and_PVC_Work (steel fittings)
A70: Line | B70: Code / Source | C70: Description / Specification | D70: Unit | E70: Quantity / Coeff | F70: Basic Rate (Rs) | G70: Amount (Rs) | H70: Source Reference / Remarks | I70: Markup Tag
A71: 1 | B71: 4202 | C71: =IFERROR(INDEX(Rates_Master!$C:$C, MATCH(B71, Rates_Master!$A:$A, 0)), "Code not found in Rates_Master") -> Red oxide Zinc chromate primer | D71: =IFERROR(INDEX(Rates_Master!$D:$D, MATCH(B71, Rates_Master!$A:$A, 0)), "") -> litre | E71: 0.54 | F71: =IFERROR(INDEX(Rates_Master!$E:$E, MATCH(B71, Rates_Master!$A:$A, 0)), 0) -> 110 | G71: =ROUND(E71 * F71, 2) -> 59.4 | H71: Red oxide zinc chromate primer
A72: 2 | B72: 0131 | C72: =IFERROR(INDEX(Rates_Master!$C:$C, MATCH(B72, Rates_Master!$A:$A, 0)), "Code not found in Rates_Master") -> Painter | D72: =IFERROR(INDEX(Rates_Master!$D:$D, MATCH(B72, Rates_Master!$A:$A, 0)), "") -> day | E72: 0.24 | F72: =IFERROR(INDEX(Rates_Master!$E:$E, MATCH(B72, Rates_Master!$A:$A, 0)), 0) -> 679 | G72: =ROUND(E72 * F72, 2) -> 162.96 | H72: Painter
A73: 3 | B73: 0115 | C73: =IFERROR(INDEX(Rates_Master!$C:$C, MATCH(B73, Rates_Master!$A:$A, 0)), "Code not found in Rates_Master") -> Coolie | D73: =IFERROR(INDEX(Rates_Master!$D:$D, MATCH(B73, Rates_Master!$A:$A, 0)), "") -> day | E73: 0.24 | F73: =IFERROR(INDEX(Rates_Master!$E:$E, MATCH(B73, Rates_Master!$A:$A, 0)), 0) -> 558 | G73: =ROUND(E73 * F73, 2) -> 133.92 | H73: Coolie
A74: 4 | B74: 9999 | C74: Carriage of material | D74: L.S. | E74: 0.52 | F74: =Factor_Sundries -> 2 | G74: =ROUND(E74 * F74, 2) -> 1.04 | H74: Base L.S. allowance x Cost Index Multiplier (Global_Factors)
A75: 5 | B75: 9999 | C75: Brushes, sand paper including sundries | D75: L.S. | E75: 10.79 | F75: =Factor_Sundries -> 2 | G75: =ROUND(E75 * F75, 2) -> 21.58 | H75: Base L.S. allowance x Cost Index Multiplier (Global_Factors)
A76: TOTAL DIRECT COST "W" (all lines above): | G76: =ROUND(SUM(G71:G75), 2) -> 378.9 | H76: Book value of W for item 13.50.3 = Rs 378.90
A77: Less "A" - imported lines already carrying statutory markups: | G77: =ROUND(SUMIF($I$71:$I$75, "A", $G$71:$G$75), 2) -> 0 | H77: CPWD convention: markups are computed on (W-A), (X-A), (Y-A), (Z-A). A line tagged "A" is an imported rate that already includes Water, GST, CPOH and Cess.
A78: X1 | B78: YES | C78: Add Water Charges on (W - A) | E78: =G76 - G77 -> 378.9 | F78: =Factor_Water -> 0.01 | G78: =IF(B78="YES", ROUND(E78 * F78, 2), 0) -> 3.79 | H78: CPWD: 1% water charges, computed on the direct cost net of A-tagged imports.
A79: X | B79: - | C79: Subtotal "X" (W + Water Charges) | G79: =G76 + G78 -> 382.69 | H79: Running compounded subtotal
A80: Y1 | B80: YES | C80: Add GST on (X - A) | E80: =G79 - G77 -> 382.69 | F80: =Factor_GST -> 0.1405 | G80: =IF(B80="YES", ROUND(E80 * F80, 2), 0) -> 53.77 | H80: CPWD DAR 2019 works contract multiplying factor 0.1405, net of A.
A81: Y | B81: - | C81: Subtotal "Y" (X + GST) | G81: =G79 + G80 -> 436.46 | H81: Running compounded subtotal
A82: Z1 | B82: YES | C82: Add Contractor Profit & Overheads on (Y - A) | E82: =G81 - G77 -> 436.46 | F82: =Factor_CPOH -> 0.15 | G82: =IF(B82="YES", ROUND(E82 * F82, 2), 0) -> 65.47 | H82: Standard 15% CPOH, net of A.
A83: Z | B83: - | C83: Subtotal "Z" (Y + CPOH) | G83: =G81 + G82 -> 501.93 | H83: Running compounded subtotal
A84: Z2 | B84: YES | C84: Add BOCW Welfare Cess on (Z - A) | E84: =G83 - G77 -> 501.93 | F84: =Factor_Cess -> 0.01 | G84: =IF(B84="YES", ROUND(E84 * F84, 2), 0) -> 5.02 | H84: Statutory 1% BOCW Welfare Cess, net of A.
A85: Cost of 10.00 sqm: | G85: =ROUND(G83 + G84, 2) -> 506.95
A86: RESOLVED RATE per 1.00 sqm (SAY): | G86: =MROUND(G85 / 10, 0.05) -> 50.7 | H86: CPWD DAR 2019 printed Say rate for this item = Rs 50.70 per sqm. Rounded with MROUND(x, 0.05) because CPWD quotes every Say rate to the nearest 5 paise. Any difference means a Rates_Master rate has been edited away from the 2019 base.
A88: ITEM 13.57.1 - 13 Finishing (Vol.2) - Painting with oil type wood preservative of approved brand and manufacture - new work (two or more coats)
A89: Basis: | B89: 10 | C89: sqm | D89: Consumed by: | E89: 09_Wood_and_PVC_Work (preservative treatment on timber)
A90: Line | B90: Code / Source | C90: Description / Specification | D90: Unit | E90: Quantity / Coeff | F90: Basic Rate (Rs) | G90: Amount (Rs) | H90: Source Reference / Remarks | I90: Markup Tag
A91: 1 | B91: 0859 | C91: =IFERROR(INDEX(Rates_Master!$C:$C, MATCH(B91, Rates_Master!$A:$A, 0)), "Code not found in Rates_Master") -> Oil type wood preservative | D91: =IFERROR(INDEX(Rates_Master!$D:$D, MATCH(B91, Rates_Master!$A:$A, 0)), "") -> litre | E91: 1 | F91: =IFERROR(INDEX(Rates_Master!$E:$E, MATCH(B91, Rates_Master!$A:$A, 0)), 0) -> 130 | G91: =ROUND(E91 * F91, 2) -> 130 | H91: Oil type wood preservative
A92: 2 | B92: 0131 | C92: =IFERROR(INDEX(Rates_Master!$C:$C, MATCH(B92, Rates_Master!$A:$A, 0)), "Code not found in Rates_Master") -> Painter | D92: =IFERROR(INDEX(Rates_Master!$D:$D, MATCH(B92, Rates_Master!$A:$A, 0)), "") -> day | E92: 0.15 | F92: =IFERROR(INDEX(Rates_Master!$E:$E, MATCH(B92, Rates_Master!$A:$A, 0)), 0) -> 679 | G92: =ROUND(E92 * F92, 2) -> 101.85 | H92: Painter
A93: 3 | B93: 0115 | C93: =IFERROR(INDEX(Rates_Master!$C:$C, MATCH(B93, Rates_Master!$A:$A, 0)), "Code not found in Rates_Master") -> Coolie | D93: =IFERROR(INDEX(Rates_Master!$D:$D, MATCH(B93, Rates_Master!$A:$A, 0)), "") -> day | E93: 0.15 | F93: =IFERROR(INDEX(Rates_Master!$E:$E, MATCH(B93, Rates_Master!$A:$A, 0)), 0) -> 558 | G93: =ROUND(E93 * F93, 2) -> 83.7 | H93: Coolie
A94: 4 | B94: 9999 | C94: Carriage of material | D94: L.S. | E94: 0.52 | F94: =Factor_Sundries -> 2 | G94: =ROUND(E94 * F94, 2) -> 1.04 | H94: Base L.S. allowance x Cost Index Multiplier (Global_Factors)
A95: 5 | B95: 9999 | C95: Brushes etc. | D95: L.S. | E95: 4.16 | F95: =Factor_Sundries -> 2 | G95: =ROUND(E95 * F95, 2) -> 8.32 | H95: Base L.S. allowance x Cost Index Multiplier (Global_Factors)
A96: 6 | B96: 9999 | C96: Sundries | D96: L.S. | E96: 3.9 | F96: =Factor_Sundries -> 2 | G96: =ROUND(E96 * F96, 2) -> 7.8 | H96: Base L.S. allowance x Cost Index Multiplier (Global_Factors)
A97: TOTAL DIRECT COST "W" (all lines above): | G97: =ROUND(SUM(G91:G96), 2) -> 332.71 | H97: Book value of W for item 13.57.1 = Rs 332.71
A98: Less "A" - imported lines already carrying statutory markups: | G98: =ROUND(SUMIF($I$91:$I$96, "A", $G$91:$G$96), 2) -> 0 | H98: CPWD convention: markups are computed on (W-A), (X-A), (Y-A), (Z-A). A line tagged "A" is an imported rate that already includes Water, GST, CPOH and Cess.
A99: X1 | B99: YES | C99: Add Water Charges on (W - A) | E99: =G97 - G98 -> 332.71 | F99: =Factor_Water -> 0.01 | G99: =IF(B99="YES", ROUND(E99 * F99, 2), 0) -> 3.33 | H99: CPWD: 1% water charges, computed on the direct cost net of A-tagged imports.
A100: X | B100: - | C100: Subtotal "X" (W + Water Charges) | G100: =G97 + G99 -> 336.04 | H100: Running compounded subtotal
A101: Y1 | B101: YES | C101: Add GST on (X - A) | E101: =G100 - G98 -> 336.04 | F101: =Factor_GST -> 0.1405 | G101: =IF(B101="YES", ROUND(E101 * F101, 2), 0) -> 47.21 | H101: CPWD DAR 2019 works contract multiplying factor 0.1405, net of A.
A102: Y | B102: - | C102: Subtotal "Y" (X + GST) | G102: =G100 + G101 -> 383.25 | H102: Running compounded subtotal
A103: Z1 | B103: YES | C103: Add Contractor Profit & Overheads on (Y - A) | E103: =G102 - G98 -> 383.25 | F103: =Factor_CPOH -> 0.15 | G103: =IF(B103="YES", ROUND(E103 * F103, 2), 0) -> 57.49 | H103: Standard 15% CPOH, net of A.
A104: Z | B104: - | C104: Subtotal "Z" (Y + CPOH) | G104: =G102 + G103 -> 440.74 | H104: Running compounded subtotal
A105: Z2 | B105: YES | C105: Add BOCW Welfare Cess on (Z - A) | E105: =G104 - G98 -> 440.74 | F105: =Factor_Cess -> 0.01 | G105: =IF(B105="YES", ROUND(E105 * F105, 2), 0) -> 4.41 | H105: Statutory 1% BOCW Welfare Cess, net of A.
A106: Cost of 10.00 sqm: | G106: =ROUND(G104 + G105, 2) -> 445.15
A107: RESOLVED RATE per 1.00 sqm (SAY): | G107: =MROUND(G106 / 10, 0.05) -> 44.5 | H107: CPWD DAR 2019 printed Say rate for this item = Rs 44.50 per sqm. Rounded with MROUND(x, 0.05) because CPWD quotes every Say rate to the nearest 5 paise. Any difference means a Rates_Master rate has been edited away from the 2019 base.
...

Sheet 01_Carriage_of_Materials
A1: CPWD DAR 2019 — SUB-HEAD 01: CARRIAGE OF MATERIALS (ANALYTICAL SIMULATOR & BENCHMARKS)
A2: LEGEND: | B2: INPUT - you type it | C2: OVERRIDE - optional | D2: LOOKUP - fetched | E2: DERIVED - calculated | F2: RESULT - subtotal | G2: SAY - final rate | H2: CPWD rule / note | I2: Not editable
A3: CPWD DAR Sub-head 01: Dynamic Mechanical Carriage Simulator based on Data Sheet No. 1 (Notes 1 to 5). Supports custom lead (L), truck speed (S), turnaround time (T), and payload capacities (C). Evaluates trips N, km done, dynamic fuel consumption, and net unit rates with 15% CPOH.
A4: HOW TO USE THIS SHEET (read this before typing anything)
A5: HOW TO USE THIS SHEET - STEP 1: fill in PANEL 1 to say WHAT is being built; each row tells you whether that choice actually changes the cost. STEP 2: set the quantities in PANEL 2. STEP 3: enter the MATERIAL and LABOUR lines - type a code in the yellow "Code / Source" cell and the description, unit and rate fill themselves in. STEP 4: read the gold SAY rate at the bottom. Everything between Step 3 and the SAY rate is calculated for you - if a cell is not yellow or orange, do not type in it.
A6: WHAT THE COLOURS MEAN - YELLOW = INPUT, you type it. ORANGE = OVERRIDE, optional; leave it blank to use the looked-up value, or type here to force your own. BLUE = LOOKUP, fetched from Rates_Master or another reference sheet. WHITE = DERIVED, calculated from the cells above it. GREEN = a subtotal to read. GOLD = the final SAY rate. The sheet is protected, so only the yellow and orange cells will let you type at all.
A8: QUICK RATE LOOKUP - READ A READY-MADE CPWD RATE OFF TABLE 1.1. Pick a material and type a lead: the rate below is the one the DAR 2019 already publishes. For anything the book covers you can stop here - the rest of this sheet is only needed when you are pricing something the book does NOT cover.
A9: Parameter | B9: Value | C9: Unit | D9: Cell Role | E9: Where this value comes from, and the CPWD DAR 2019 basis for it
A10: Material to be carried | B10: R.C.C. / C.I. / steel pipes 1000, 1100 & 1200 mm dia | C10: - | D10: INPUT | E10: Pick any of the 37 materials the DAR tabulates in Table 1.1 (section 5B below).
A11: Lead distance | B11: 10 | C11: km | D11: INPUT | E11: One-way haul distance. Any value from 1 km upwards - the book covers up to 30 km directly and beyond that by its per-km band rate.
A12: Table 1.1 row matched | B12: =IFERROR(MATCH(B10, $B$180:$B$216, 0), "") -> 37 | C12: row | D12: DERIVED | E12: Which row of Table 1.1 your material is on.
A13: Rate is per | B13: =IFERROR(INDEX($E$180:$E$216, B12), "") -> 100 m | C13: - | D13: LOOKUP | E13: The DAR schedule unit for this material - the rate below is per ONE of these.
A14: Which part of the table applies | B14: =IF(B12="", "", IF(B11<=5, "Printed column for " & TEXT(MAX(1,CEILING(B11,1)),"0") & " km", IF(B11<=10, "5 km rate + column L per km", IF(B11<=20, "10 km rate + column M per km", "20 km rate + column N per km")))) -> 5 km rate + column L per km | C14: - | D14: DERIVED | E14: The DAR prints exact rates for 1, 2, 3, 4 and 5 km (Table 1.1 columns G to K). Past 5 km it stops printing whole rates and instead gives a PER-KILOMETRE adder for three bands: column L for >5-10 km, column M for >10-20 km, column N for >20 km. This row says which of those four cases your lead falls into.
A15: Base rate taken from the table | B15: =IF(B12="", "", IF(B11<=5, CHOOSE(MAX(1,MIN(5,CEILING(B11,1))), INDEX($G$180:$G$216,B12), INDEX($H$180:$H$216,B12), INDEX($I$180:$I$216,B12), INDEX($J$180:$J$216,B12), INDEX($K$180:$K$216,B12)), IF(B11<=10, INDEX($K$180:$K$216,B12), IF(B11<=20, INDEX($K$180:$K$216,B12) + 5*INDEX($L$180:$L$216,B12), INDEX($K$180:$K$216,B12) + 5*INDEX($L$180:$L$216,B12) + 10*INDEX($M$180:$M$216,B12))))) -> 11764.25 | C15: Rs | D15: LOOKUP | E15: The printed rate the calculation starts from: the 1-5 km column itself, or the 5 km / 10 km / 20 km rate that the relevant band builds on.
A16: Kilometres beyond the base | B16: =IF(B12="", "", IF(B11<=5, 0, IF(B11<=10, B11-5, IF(B11<=20, B11-10, B11-20)))) -> 5 | C16: km | D16: DERIVED | E16: How far past the base rate's lead you are travelling. Zero for leads up to 5 km, because those rates are printed outright.
A17: Per-km rate for that band | B17: =IF(B12="", "", IF(B11<=5, 0, IF(B11<=10, INDEX($L$180:$L$216,B12), IF(B11<=20, INDEX($M$180:$M$216,B12), INDEX($N$180:$N$216,B12))))) -> 886.17 | C17: Rs per km | D17: LOOKUP | E17: Straight out of Table 1.1 column L, M or N depending on the band. This is exactly what those three columns are FOR - they are adders, not rates in their own right.
A18: Add for the extra distance | B18: =IF(B12="", "", ROUND(B16 * B17, 2)) -> 4430.85 | C18: Rs | D18: DERIVED | E18: Kilometres beyond the base x the per-km rate for the band.
A19: CPWD PUBLISHED CARRIAGE RATE | B19: =IF(B12="", "", ROUND(B15 + B18, 2)) -> 16195.1 | C19: Rs | D19: SAY | E19: Base rate + the extra for distance. This is the DAR 2019 rate for this material at this lead, including 15% CP&OH, per the unit shown three rows up. You can put this straight into an estimate.
A20: How that number was reached | B20: =IF(B12="", "Pick a material from the dropdown above to see the book rate.", "Carriage of " & B10 & " for a lead of " & TEXT(B11,"0.00") & " km = " & IF(B11<=5, "Rs " & TEXT(B15,"#,##0.00") & " read directly from the " & TEXT(MAX(1,CEILING(B11,1)),"0") & " km column of Table 1.1", "Rs " & TEXT(B15,"#,##0.00") & " (the " & IF(B11<=10,"5",IF(B11<=20,"10","20")) & " km rate) plus " & TEXT(B16,"0.00") & " km x Rs " & TEXT(B17,"#,##0.00") & " per km = Rs " & TEXT(B18,"#,##0.00")) & ", giving Rs " & TEXT(B19,"#,##0.00") & " per " & B13 & ".") -> Carriage of R.C.C. / C.I. / steel pipes 1000, 1100 & 1200 mm dia for a lead of 10.00 km = Rs 11,764.25 (the 5 km rate) plus 5.00 km x Rs 886.17 per km = Rs 4,430.85, giving Rs 16,195.10 per 100 m.
A22: PANEL 1 - SCOPE & SPECIFICATION (what is being moved, and under what contract scope)
A23: Parameter | B23: Value | C23: Unit | D23: Cell Role | E23: Where this value comes from, and the CPWD DAR 2019 basis for it
A24: Custom item code | B24: 1.1.CUSTOM | C24: - | D24: INPUT | E24: Your reference for this analysis. Pick a DAR item number from the dropdown to base it on a printed item, or type your own code for a genuinely non-DSR item.
A25: Material commodity | B25: R.C.C. / C.I. / steel pipes 1000, 1100 & 1200 mm dia | C25: - | D25: INPUT | E25: DRIVES COST. Sets the truck payload, the net payable quantity and the billing unit, all looked up from Table 1.1 below. Choose from the dropdown so the lookups resolve.
A26: Handling scope | B26: including loading, transporting, unloading and stacking | C26: - | D26: INPUT | E26: DRIVES COST. Sets the Beldar gang on the resource schedule below: 6 for full turnkey handling, 5 without stacking, 3 when machine-loaded, 3.75 at a railway siding, 0 for pure haulage. See the scope table at the bottom of this sheet.
A27: Lift condition | B27: for all lifts | C27: - | D27: INPUT | E27: NOMENCLATURE ONLY. The DAR quotes one carriage rate whatever the lift, so this changes the wording of the item and nothing in the cost.
A28: Municipal gate / tipping fee | B28: 0 | C28: Rs per billing unit | D28: INPUT | E28: USER-SUPPLIED COST. The DAR carries no tipping or gate fee anywhere in Sub-Head 01, so there is no figure to look up. It is added AFTER the markup chain and is therefore NOT subject to the 15% CPOH - it is a reimbursable disbursement, not contractor cost.
A29: Nomenclature override | C29: - | D29: OVERRIDE | E29: Leave blank and the item description below writes itself from your Panel 1 choices. Type here only when you want to word the item yourself.
A30: Assembled item nomenclature | B30: =IF(B29<>"", B29, "Carriage of " & B25 & " by mechanical transport " & B26 & " for lead upto " & TEXT(B34, "0.00") & " km " & B27 & IF(B28>0, ", including municipal tipping / gate fee of Rs " & TEXT(B28, "0.00") & " per " & B55, "") & ", complete as per directions of Engineer-in-charge.") -> Carriage of R.C.C. / C.I. / steel pipes 1000, 1100 & 1200 mm dia by mechanical transport including loading, transporting, unloading and stacking for lead upto 26.00 km for all lifts, complete as per directions of Engineer-in-charge.
A32: PANEL 2 - ROUTE & TRIP DYNAMICS (how far, how fast, how many trips a shift)
A33: Parameter | B33: Value | C33: Unit | D33: Cell Role | E33: Where this value comes from, and the CPWD DAR 2019 basis for it
A34: Lead distance (L) | B34: 26 | C34: km | D34: INPUT | E34: DRIVES COST. One-way haul distance. Everything below - speed, trips, fuel - follows from it.
A35: Benchmark average speed at this lead | B35: =IFERROR(INDEX($B$146:$B$175, MATCH(B34, $A$146:$A$175, 1)), 16) -> 29 | C35: km/h | D35: LOOKUP | E35: Read off CPWD Data Sheet No. 1 (section 5A below) for the lead above: 16 km/h at 1 km rising to 31 km/h at 30 km. Beyond 30 km the last tabulated row is used.
A36: Speed override | C36: km/h | D36: OVERRIDE | E36: Leave blank to use the Data Sheet 1 benchmark above. Fill it in only when site conditions genuinely differ, and record why - departing from the benchmark is what makes a rate non-DSR.
A37: Effective average speed (S) | B37: =IF(B36<>"", B36, B35) -> 29 | C37: km/h | D37: DERIVED | E37: The override if you gave one, otherwise the benchmark. This is the S used in the trips formula.
A38: Turnaround time (T) | B38: 1 | C38: hours per trip | D38: INPUT | E38: Loading plus unloading plus waiting per round trip. CPWD Data Sheet 1 uses 1.00 hour.
A39: Operational mode | B39: STANDARD (DAYTIME) | C39: - | D39: INPUT | E39: Urban restricted hours means heavy vehicles may only run off-peak, which caps the trips achievable in a shift. Selecting it does not change the cost by itself - enter the capped trip count in the override on the next row. DAR item 1.1.18 is the worked example: 3.00 trips instead of the 4.10 the formula gives at 10 km.
A40: Trip count basis | B40: CPWD FRACTIONAL (Data Sheet 1 basis) | C40: - | D40: INPUT | E40: CPWD FRACTIONAL is the book's own basis and the default. Data Sheet No. 1 quotes trips as decimals throughout - 7.11 at 1 km, 4.10 at 10 km, 2.73 at 30 km - because N is a productivity RATE per 8-hour shift, not a count of trips on one particular day; the truck is hired by the day and the cost is spread over the average output. WHOLE TRIPS rounds down to an integer, which is defensible when a real site or regulatory constraint caps the trips, but it does NOT reproduce the printed DAR rates - flooring 7.11 to 7 at 1 km raises the lime/moorum rate from Rs 104.94 to Rs 106.52. Where the DAR itself fixes a whole trip count (item 1.1.18 uses exactly 3.00 under urban restricted hours) it does so as an explicit cap, not as a rounding rule - use the Trips override below for that.
A41: Trips override | C41: trips per shift | D41: OVERRIDE | E41: Leave blank to use the calculated trips below. Fill it in to force a trip count - this is how a restricted-hours item is priced. It is honoured in any mode.
A42: Daily trips achieved (N) | B42: =IF(B41<>"", B41, IF(B40="WHOLE TRIPS (round down to integer)", IFERROR(INT(8 / ((2 * B34 / B37) + B38)), 0), IFERROR(ROUND(8 / ((2 * B34 / B37) + B38), 2), 0))) -> 2.86 | C42: trips per shift | D42: DERIVED | E42: N = 8 / ((2L / S) + T) - an 8-hour shift divided by one round trip. The Trips override wins if it is filled; otherwise the Trip count basis decides whether the result keeps its decimals (CPWD) or is rounded down to a whole trip.
A43: Distance / fuel basis | B43: DIRECT ROUTE (2NL + 6) | C43: - | D43: INPUT | E43: DIRECT ROUTE computes km/day = 2NL + 6, the 6 km being the depot run - this reproduces every row of Data Sheet 1. CPWD PRO-RATA instead takes the Data Sheet 1 km/day for your lead and scales it by (your trips / the benchmark trips at that lead); that is how DAR item 1.1.18 derives 64.40 km from the 10 km row.
A44: Distance travelled per shift | B44: =IF(B43="CPWD PRO-RATA (Data Sheet 1)", IFERROR(ROUND(INDEX($D$146:$D$175, MATCH(B34, $A$146:$A$175, 1)) * (B42 / INDEX($C$146:$C$175, MATCH(B34, $A$146:$A$175, 1))), 2), 0), IFERROR(ROUND((2 * B42 * B34) + 6, 2), 0)) -> 154.72 | C44: km | D44: DERIVED | E44: Follows the basis selected above.
A45: Diesel consumed per shift | B45: =ROUND(B44 / 5, 2) -> 30.94 | C45: litres | D45: DERIVED | E45: CPWD Note 3: distance travelled / 5.0 km per litre.
A46: Mobil oil consumed per shift | B46: =ROUND(B44 / 140, 3) -> 1.105 | C46: litres | D46: DERIVED | E46: CPWD Note 4: distance travelled / 140.0 km per litre.
A48: PANEL 3 - PAYLOAD & BILLING BASIS (how much is actually paid for per trip)
A49: Parameter | B49: Value | C49: Unit | D49: Cell Role | E49: Where this value comes from, and the CPWD DAR 2019 basis for it
A50: Table 1.1 row for this material | B50: =IFERROR(MATCH(B25, $B$180:$B$216, 0), "") -> 37 | C50: row index | D50: DERIVED | E50: Which row of Table 1.1 (section 5B) the material commodity matches. Everything below, and the published DAR rate in Section 2, reads that row. Shows #N/A if the material is not one of the book's - use the overrides in that case.
A51: Gross truck payload per trip | B51: =IFERROR(INDEX($C$180:$C$216, B50), "") -> 10.98 | C51: per Table 1.1 | D51: LOOKUP | E51: What physically goes on the truck, from Table 1.1 below. Shown for information only - it is NOT what the rate is divided by.
A52: Net payable quantity per trip | B52: =IFERROR(INDEX($D$180:$D$216, B50), "") -> 10.98 | C52: per Table 1.1 | D52: LOOKUP | E52: THIS is the divisor CPWD uses. Loose materials are paid on a reduced quantity: earth less 20%, excavated rock less 50%, soling stone less 15%, 40 mm aggregate and manure less 8%. Using the gross payload instead understates the rate by that percentage.
A53: Payable quantity override | C53: per Table 1.1 | D53: OVERRIDE | E53: Leave blank to use the net payable quantity above. Fill it in for a material that is not in Table 1.1, or when a site measurement justifies a different figure.
A54: Effective payable quantity per trip | B54: =IF(B53<>"", B53, IF(B52="", 0, B52)) -> 10.98 | C54: per Table 1.1 | D54: DERIVED | E54: The override if given, otherwise the net payable quantity.
A55: Schedule billing unit | B55: =IFERROR(INDEX($E$180:$E$216, B50), "cum") -> 100 m | C55: - | D55: LOOKUP | E55: The unit the DAR bills this material in, from Table 1.1. Bulk materials in cum, cement and steel in tonne, bricks per 1000 Nos, pipes per 100 m.
A56: Schedule unit scale factor | B56: =IF(B55="1000 Nos", 1000, IF(B55="100 m", 100, 1)) -> 100 | C56: multiplier | D56: DERIVED | E56: The rate is first derived per single unit (per cum, per metre, per brick) and then multiplied by this factor to reach the schedule unit: 1000 for "1000 Nos", 100 for "100 m", otherwise 1.
A57: Total payable output per shift | B57: =ROUND(B42 * B54, 4) -> 31.4028 | C57: per Table 1.1 | D57: RESULT | E57: Trips x effective payable quantity. This is what the shift cost is divided by.
A59: AUDIT STATUS: | B59: =IF(AND(D59="OK", F59="OK", H59="OK"), "[PASS] ALL CHECKS OK", "[ALERT] CHECKS FAILED") -> [PASS] ALL CHECKS OK | C59: Trips: | D59: =IF(B42>0, "OK", "ERR: N<=0") -> OK | E59: Payable output: | F59: =IF(B57>0, "OK", "ERR: no payable qty - pick a Table 1.1 material or set the override") -> OK | G59: Direct cost: | H59: =IF(G71>0, "OK", "ERR: W<=0") -> OK | I59: =IF(NOT(AND(ISNUMBER(G90), G90>0)), "ERR: rate not resolved", IF(G89="", "n/a - custom material", IF(ABS(G89)<0.05, "matches book exactly", IF(ABS(G89)/G88<=0.02, "within book band tolerance", "CHECK: over 2% from book")))) -> within book band tolerance
A61: SECTION 1 - MECHANICAL TRANSPORT RESOURCE SCHEDULE FOR ONE 8-HOUR SHIFT (truck hire + labour gang + fuel)
A62: Line | B62: Code / Source | C62: Resource / Fuel Description | D62: Unit | E62: Quantity / Coeff | F62: Basic Rate (Rs) | G62: Amount (Rs) | H62: Source Reference / CPWD Note | I62: Cell Role
A63: 1 | B63: 0084 | C63: =IF(B63="","", IFERROR(INDEX(Rates_Master!$C:$C, MATCH(B63, Rates_Master!$A:$A, 0)), "Code not in Rates_Master")) -> Hire charges of diesel truck - 9 tonne (without POL) | D63: =IF(B63="","", IFERROR(INDEX(Rates_Master!$D:$D, MATCH(B63, Rates_Master!$A:$A, 0)), "")) -> day | E63: 1 | F63: =IF(B63="","", IFERROR(INDEX(Rates_Master!$E:$E, MATCH(B63, Rates_Master!$A:$A, 0)), 0)) -> 1500 | G63: =IF(OR(B63="", E63=""), 0, ROUND(E63 * F63, 2)) -> 1500 | H63: CPWD Note 5: hire of a 9-tonne diesel truck for one 8-hour shift, excluding diesel and mobil oil (those are the two rows below). | I63: INPUT
A64: 2 | B64: 0114 | C64: =IF(B64="","", IFERROR(INDEX(Rates_Master!$C:$C, MATCH(B64, Rates_Master!$A:$A, 0)), "Code not in Rates_Master")) -> Beldar | D64: =IF(B64="","", IFERROR(INDEX(Rates_Master!$D:$D, MATCH(B64, Rates_Master!$A:$A, 0)), "")) -> day | E64: =IF(ISNUMBER(SEARCH("transporting only", B26)), 0, IF(ISNUMBER(SEARCH("machine loaded", B26)), 3, IF(ISNUMBER(SEARCH("excluding loading", B26)), 3, IF(ISNUMBER(SEARCH("railway siding", B26)), 3.75, IF(ISNUMBER(SEARCH("excluding stacking", B26)), 5, 6))))) -> 6 | F64: =IF(B64="","", IFERROR(INDEX(Rates_Master!$E:$E, MATCH(B64, Rates_Master!$A:$A, 0)), 0)) -> 558 | G64: =IF(OR(B64="", E64=""), 0, ROUND(E64 * F64, 2)) -> 3348 | H64: Gang size follows the Handling Scope you chose in Panel 1: 6 turnkey / 5 no stacking / 3 machine-loaded / 3.75 railway siding / 0 haulage only. See section 5D below. | I64: DERIVED
A65: 3 | B65: 1235 | C65: =IF(B65="","", IFERROR(INDEX(Rates_Master!$C:$C, MATCH(B65, Rates_Master!$A:$A, 0)), "Code not in Rates_Master")) -> Diesel | D65: =IF(B65="","", IFERROR(INDEX(Rates_Master!$D:$D, MATCH(B65, Rates_Master!$A:$A, 0)), "")) -> litre | E65: =B45 -> 30.94 | F65: =IF(B65="","", IFERROR(INDEX(Rates_Master!$E:$E, MATCH(B65, Rates_Master!$A:$A, 0)), 0)) -> 73.5 | G65: =IF(OR(B65="", E65=""), 0, ROUND(E65 * F65, 2)) -> 2274.09 | H65: CPWD Note 3: litres from Panel 2 (distance / 5.0 km per litre). | I65: DERIVED
A66: 4 | B66: 5001 | C66: =IF(B66="","", IFERROR(INDEX(Rates_Master!$C:$C, MATCH(B66, Rates_Master!$A:$A, 0)), "Code not in Rates_Master")) -> Mobil oil | D66: =IF(B66="","", IFERROR(INDEX(Rates_Master!$D:$D, MATCH(B66, Rates_Master!$A:$A, 0)), "")) -> litre | E66: =B46 -> 1.105 | F66: =IF(B66="","", IFERROR(INDEX(Rates_Master!$E:$E, MATCH(B66, Rates_Master!$A:$A, 0)), 0)) -> 315 | G66: =IF(OR(B66="", E66=""), 0, ROUND(E66 * F66, 2)) -> 348.08 | H66: CPWD Note 4: litres from Panel 2 (distance / 140.0 km per litre). | I66: DERIVED
A67: 5 | C67: =IF(B67="","", IFERROR(INDEX(Rates_Master!$C:$C, MATCH(B67, Rates_Master!$A:$A, 0)), "Code not in Rates_Master")) | D67: =IF(B67="","", IFERROR(INDEX(Rates_Master!$D:$D, MATCH(B67, Rates_Master!$A:$A, 0)), "")) | F67: =IF(B67="","", IFERROR(INDEX(Rates_Master!$E:$E, MATCH(B67, Rates_Master!$A:$A, 0)), 0)) | G67: =IF(OR(B67="", E67=""), 0, ROUND(E67 * F67, 2)) -> 0 | I67: INPUT
A68: 6 | C68: =IF(B68="","", IFERROR(INDEX(Rates_Master!$C:$C, MATCH(B68, Rates_Master!$A:$A, 0)), "Code not in Rates_Master")) | D68: =IF(B68="","", IFERROR(INDEX(Rates_Master!$D:$D, MATCH(B68, Rates_Master!$A:$A, 0)), "")) | F68: =IF(B68="","", IFERROR(INDEX(Rates_Master!$E:$E, MATCH(B68, Rates_Master!$A:$A, 0)), 0)) | G68: =IF(OR(B68="", E68=""), 0, ROUND(E68 * F68, 2)) -> 0 | I68: INPUT
A69: 7 | C69: =IF(B69="","", IFERROR(INDEX(Rates_Master!$C:$C, MATCH(B69, Rates_Master!$A:$A, 0)), "Code not in Rates_Master")) | D69: =IF(B69="","", IFERROR(INDEX(Rates_Master!$D:$D, MATCH(B69, Rates_Master!$A:$A, 0)), "")) | F69: =IF(B69="","", IFERROR(INDEX(Rates_Master!$E:$E, MATCH(B69, Rates_Master!$A:$A, 0)), 0)) | G69: =IF(OR(B69="", E69=""), 0, ROUND(E69 * F69, 2)) -> 0 | I69: INPUT
A70: 8 | C70: =IF(B70="","", IFERROR(INDEX(Rates_Master!$C:$C, MATCH(B70, Rates_Master!$A:$A, 0)), "Code not in Rates_Master")) | D70: =IF(B70="","", IFERROR(INDEX(Rates_Master!$D:$D, MATCH(B70, Rates_Master!$A:$A, 0)), "")) | F70: =IF(B70="","", IFERROR(INDEX(Rates_Master!$E:$E, MATCH(B70, Rates_Master!$A:$A, 0)), 0)) | G70: =IF(OR(B70="", E70=""), 0, ROUND(E70 * F70, 2)) -> 0 | I70: INPUT
A71: Direct operating cost of one 8-hour shift, W (Rs): | G71: =SUM(G63:G70) -> 7470.17 | H71: Compare against the "Total Shift Cost" column of Data Sheet 1 below for the same lead - they should agree.
A72: Direct operating cost per round trip (Rs): | G72: =IFERROR(ROUND(G71 / B42, 2), 0) -> 2611.95 | H72: W divided by the trips in Panel 2.
A74: SECTION 2 - STATUTORY MARKUPS & RATE DERIVATION (CPWD carriage convention: 15% CPOH only)
A75: Step | B75: Description / Stage | C75: Apply? (YES/NO) | D75: Basis Applied | E75: Base Amount (Rs) | F75: Factor / % | G75: Amount (Rs) | H75: CPWD Statutory Rule & Guidance Note | I75: Cell Role
A76: W | B76: Direct operating cost of the shift (truck + labour + fuel) | C76: - | D76: Direct sum | E76: - | F76: - | G76: =G71 -> 7470.17 | H76: Carried straight down from Section 1. | I76: DERIVED
A77: X1 | B77: Add Water Charges | C77: NO | D77: On W | E77: =G76 -> 7470.17 | F77: =Factor_Water -> 0.01 | G77: =IF(C77="YES", ROUND(E77 * F77, 2), 0) -> 0 | H77: CPWD RULE: switched off for carriage - no water is consumed in haulage. DAR item 1.1.18 goes straight from TOTAL to "Add 15% CPOH". | I77: INPUT
A78: X | B78: Subtotal X (W + Water) | C78: - | D78: W + Water | E78: - | F78: - | G78: =G76 + G77 -> 7470.17 | H78: Running subtotal. | I78: DERIVED
A79: Y1 | B79: Add GST on works contract | C79: NO | D79: On X | E79: =G78 -> 7470.17 | F79: =Factor_GST -> 0.1405 | G79: =IF(C79="YES", ROUND(E79 * F79, 2), 0) -> 0 | H79: CPWD RULE: the printed DAR carriage rates exclude GST. Leave NO to stay comparable with the book; switch to YES only for a tender that requires it. | I79: INPUT
A80: Y | B80: Subtotal Y (X + GST) | C80: - | D80: X + GST | E80: - | F80: - | G80: =G78 + G79 -> 7470.17 | H80: Base for contractor profit and overheads. | I80: DERIVED
A81: Z1 | B81: Add Contractor Profit & Overheads (15% CPOH) | C81: YES | D81: On Y | E81: =G80 -> 7470.17 | F81: =Factor_CPOH -> 0.15 | G81: =IF(C81="YES", ROUND(E81 * F81, 2), 0) -> 1120.53 | H81: CPWD RULE: 15% CPOH is applied to every carriage item without exception. | I81: INPUT
A82: Z | B82: Subtotal Z (Y + CPOH) | C82: - | D82: Y + CPOH | E82: - | F82: - | G82: =G80 + G81 -> 8590.7 | H82: Named the same way as on the other eleven builder sheets. | I82: DERIVED
A83: Z2 | B83: Add BOCW Welfare Cess | C83: NO | D83: On Z | E83: =G82 -> 8590.7 | F83: =Factor_Cess -> 0.01 | G83: =IF(C83="YES", ROUND(E83 * F83, 2), 0) -> 0 | H83: CPWD RULE: excluded from the printed base rates. Switch to YES only if your circle requires it on carriage. | I83: INPUT
A84: Total | B84: Total cost of one 8-hour shift with overheads | C84: - | D84: Z + Cess | E84: - | F84: - | G84: =G82 + G83 -> 8590.7 | H84: The full shift cost that the payable output is divided into. | I84: RESULT
A85: - | B85: Cost per round trip with overheads | C85: - | D85: Total / N | E85: =G84 -> 8590.7 | F85: =B42 -> 2.86 | G85: =IFERROR(ROUND(G84 / B42, 2), 0) -> 3003.74 | H85: For comparison with the "Cost per Trip" column of Data Sheet 1. | I85: DERIVED
A86: - | B86: Rate per single payable unit, plus gate fee | C86: - | D86: Total / payable output | E86: =G84 -> 8590.7 | F86: =B57 -> 31.4028 | G86: =IFERROR(ROUND(G84 / B57, 2), 0) + B28 -> 273.56 | H86: Per cum / per tonne / per metre / per brick. Divided by the NET payable output from Panel 3, not by the gross truck payload. The gate fee is added here, after CPOH. | I86: DERIVED
A87: - | B87: Analysed rate per schedule unit | C87: - | D87: x scale factor | E87: =B56 -> 100 | F87: - | G87: =ROUND(G86 * B56, 2) -> 27356 | H87: Multiplied up to the DAR schedule unit - x1000 for "1000 Nos", x100 for "100 m", x1 otherwise. This unrounded figure is what the Table 1.1 base rates below are quoted at. | I87: DERIVED
A88: - | B88: DAR published rate at this lead (Table 1.1 ladder) | C88: - | D88: Book ladder | E88: =B34 -> 26 | F88: =B50 -> 37 | G88: =IFERROR(IF(B50="", "", IF(B34<=5, CHOOSE(MAX(1,MIN(5,CEILING(B34,1))), INDEX($G$180:$G$216,B50), INDEX($H$180:$H$216,B50), INDEX($I$180:$I$216,B50), INDEX($J$180:$J$216,B50), INDEX($K$180:$K$216,B50)), IF(B34<=10, INDEX($K$180:$K$216,B50) + (B34-5)*INDEX($L$180:$L$216,B50), IF(B34<=20, INDEX($K$180:$K$216,B50) + 5*INDEX($L$180:$L$216,B50) + (B34-10)*INDEX($M$180:$M$216,B50), INDEX($K$180:$K$216,B50) + 5*INDEX($L$180:$L$216,B50) + 10*INDEX($M$180:$M$216,B50) + (B34-20)*INDEX($N$180:$N$216,B50))))), "") -> 27208.96 | H88: THE BOOK'S OWN ANSWER for this material and lead, read from the Table 1.1 ladder in section 5B. Up to 5 km it is the printed column for the next tabulated kilometre; beyond that it is the 5 km rate plus the printed per-km band rates, which is how the DAR itself extends a carriage rate. Blank if the material is not one of the book's. | I88: LOOKUP
A89: - | B89: Simulator vs published rate | C89: - | D89: Variance | E89: =G87 -> 27356 | F89: =G88 -> 27208.96 | G89: =IF(OR(G88="", G88=0), "", ROUND(G87-G88, 2)) -> 147.04 | H89: A small difference here is NORMAL and is not an error. The book prints exact rates only at 1, 2, 3, 4, 5, 10, 20 and 30 km; between those anchors its ladder interpolates linearly from the per-km band rates, while this sheet computes the exact figure for your actual lead from Data Sheet 1. The two agree to the paisa at every anchor lead and diverge by up to about 1% mid-band - at 15 km, for example, by 1.09%. A variance beyond 2% is flagged in the audit bar and does mean something to check: a speed or payload override, a whole-trip basis, a non-standard handling scope, or a gate fee - any of which is a legitimate reason to depart from the book, but should be a deliberate one. | I89: DERIVED
A90: SAY | B90: CPWD OFFICIAL "SAY" RATE FOR THIS CARRIAGE ITEM | C90: - | D90: MROUND to Rs 0.05 | E90: - | F90: - | G90: =MROUND(G87, 0.05) -> 27356 | H90: The rate to quote in a BOQ or estimate. Rounded to the nearest 5 paise - see the note below. | I90: SAY
A91: WHY THE SAY RATE IS ROUNDED TO 5 PAISE: CPWD DAR 2019 quotes every "Say" rate to the nearest Rs 0.05, not to two decimals - e.g. item 1.3 computes 104.89 and is printed as 104.90; item 1.4.1 computes 155.47 and is printed as 155.45; item 10.1 computes 86.04 and is printed as 86.05. This sheet therefore uses MROUND(rate, 0.05) so the analysed rate matches the book exactly instead of sitting a paisa away from it. Change the 0.05 only if your circle office issues a different rounding rule.
A93: SECTION 3 - HEADING 1.2: MANUAL LABOUR CARRIAGE (lead under 0.50 km, 50 m to 500 m)
A94: CPWD DAR 2019 Heading 1.2 gang norms: Category A (lime, moorum, rubbish, earth, sand, aggregate, bricks) = 7.67 Beldars for the first 50 m plus 1.67 extra coolies for every additional 50 m. Category B (stone blocks, pipes, cement, steel, timber, bitumen) = 9.20 Beldars for the first 50 m plus 1.35 extra Beldars per additional 50 m. Every rupee figure below is derived from these gang sizes and the live day wage in Rates_Master, so a wage revision flows through automatically.
A95: Parameter | B95: Value | C95: Unit | D95: Cell Role | E95: Where this value comes from, and the CPWD DAR 2019 basis for it
A96: Material commodity (Table 1.2) | B96: R.C.C. / steel cylinder / R.C. / C.I. / unreinforced cement pipes 100 mm dia | C96: - | D96: INPUT | E96: DRIVES COST. Pick from the dropdown - the payable quantity and billing unit in the two rows below are looked up from Table 1.2 (section 5C) for whichever material you choose here. If your material is not in Table 1.2 leave this blank and type the quantity and unit directly in rows B109 and B110.
A97: Manual item code | B97: 1.2.CUSTOM | C97: - | D97: INPUT | E97: Your reference for the manual-carriage analysis.
A98: Material category | B98: Category B (Heavy / Pipes / Steel) | C98: - | D98: INPUT | E98: DRIVES COST. Selects the gang norms quoted in the banner above.
A99: Lead distance | B99: 100 | C99: metres | D99: INPUT | E99: DRIVES COST. The first 50 m is the base gang; every further 50 m adds labour.
A100: Additional 50 m steps (M) | B100: =MAX(0, ROUNDUP((B99 - 50) / 50, 0)) -> 1 | C100: steps | D100: DERIVED | E100: MAX(0, (lead - 50) / 50). A part step counts as a full step in CPWD practice.
A101: Gang for the first 50 m | B101: =IF(ISNUMBER(SEARCH("Category A", B98)), 7.67, 9.2) -> 9.2 | C101: labour days | D101: LOOKUP | E101: CPWD Heading 1.2 norm for the selected category.
A102: Extra gang per additional 50 m | B102: =IF(ISNUMBER(SEARCH("Category A", B98)), 1.67, 1.35) -> 1.35 | C102: labour days | D102: LOOKUP | E102: CPWD Heading 1.2 norm for the selected category.
A103: Labour day wage | B103: =IFERROR(INDEX(Rates_Master!$E:$E, MATCH("0114", Rates_Master!$A:$A, 0)), 0) -> 558 | C103: Rs per day | D103: LOOKUP | E103: Live rate for Beldar / Coolie (code 0114) from Rates_Master. Both grades are on the same day rate in DAR 2019.
A104: Labour cost, first 50 m | B104: =ROUND(B101 * B103, 2) -> 5133.6 | C104: Rs | D104: DERIVED | E104: Base gang x day wage.
A105: Labour cost, additional lead | B105: =ROUND(B100 * B102 * B103, 2) -> 753.3 | C105: Rs | D105: DERIVED | E105: Steps x extra gang x day wage.
A106: Total labour cost for the shift | B106: =B104 + B105 -> 5886.9 | C106: Rs | D106: DERIVED | E106: First 50 m plus additional lead.
A107: Add Contractor Profit & Overheads | B107: =ROUND(B106 * Factor_CPOH, 2) -> 883.04 | C107: Rs | D107: DERIVED | E107: Taken from Factor_CPOH on Global_Factors, so a project override reaches this engine too.
A108: Total 8-hour cost with CPOH | B108: =B106 + B107 -> 6769.94 | C108: Rs | D108: RESULT | E108: Compare with the "Base Cost 1st 50m" column of Table 1.2 below.
...

Sheet 02_Earth_Work
A1: CPWD DAR 2019 — SUB-HEAD 02: EARTH WORK (CUSTOM ITEM BUILDER)
A2: LEGEND: | B2: INPUT - you type it | C2: OVERRIDE - optional | D2: LOOKUP - fetched | E2: DERIVED - calculated | F2: RESULT - subtotal | G2: SAY - final rate | H2: CPWD rule / note | I2: Not editable
A3: CPWD DAR Sub-head 02: Earthwork operations (surface excavation, trench excavation, filling, compaction). Operates without raw material inputs, applying labour crews and earthmoving machinery hire with standard 5-step compounding statutory markups.
A4: 1. RATE ANALYSIS CONFIGURATION & OPERATIONAL PROFILE (Select parameters in D6, D7, D8, D9 to drive rate analysis)
A5: Parameter | D5: Selected Value / Parameter Input | E5: Unit | F5: Cell Role | G5: CPWD DAR 2019 Engineering Specification & Practical Field Guidance Notes
A6: Primary Work Scope | D6: Surface Excavation (≤30 cm) | E6: — | F6: INPUT | G6: Core civil work category: Surface excavation, Foundation/trenching, Embankment, Backfilling, Site clearance, Timbering, or Anti-termite.
A7: Ground Strata / Material | D7: All kinds of soil | E7: — | F7: INPUT | G7: Strata classification: All kinds of soil, Ordinary rock, Hard rock (blasting permitted), or Hard rock (blasting prohibited).
A8: Execution Method & Depth Condition | D8: Manual labor (depth ≤1.5m) | E8: — | F8: INPUT | G8: Execution technique: Manual labor (≤1.5m), Mechanical (Hydraulic Excavator 0.9 cum), Extra depth 1.5-3.0m, or Extra depth 3.0-4.5m.
A9: Operation / Task Specification | D9: General surface cut (≤30 cm deep) | E9: — | F9: INPUT | G9: Specific activity variant or application subtype (e.g. open areas, pipe trenches, post holes, tree girth band, chemical barrier stage).
A10: Standard Output Batch Quantity | D10: =IFERROR(INDEX($AC$105:$AC$153, MATCH(IF($D$9="", $D$6&"|"&$D$7&"|"&$D$8, $D$6&"|"&$D$7&"|"&$D$8&"|"&$D$9), $AA$105:$AA$153, 0)), IFERROR(INDEX($AC$105:$AC$153, MATCH($D$6&"|"&$D$7&"|"&$D$8, $AB$105:$AB$153, 0)), 100)) -> 100 | E10: units | F10: LOOKUP | G10: Standard output batch volume or area defined in CPWD DAR 2019 (100 sqm, 10 cum, 1 m, 1 tree, 10 holes).
A11: Standard Output Measurement Unit | D11: =IFERROR(INDEX($AD$105:$AD$153, MATCH(IF($D$9="", $D$6&"|"&$D$7&"|"&$D$8, $D$6&"|"&$D$7&"|"&$D$8&"|"&$D$9), $AA$105:$AA$153, 0)), IFERROR(INDEX($AD$105:$AD$153, MATCH($D$6&"|"&$D$7&"|"&$D$8, $AB$105:$AB$153, 0)), "sqm")) -> sqm | E11: — | F11: LOOKUP | G11: Billing measurement unit for work output (cum, sqm, metre, tree, hole).
A12: Custom Project Rate Reference Code | D12: C-02.01 | E12: — | F12: INPUT | G12: Project-specific non-DSR reference code when saving custom rate variations.
A13: Official Work Specification Nomenclature: | D13: =IFERROR(INDEX($AF$105:$AF$153, MATCH(IF($D$9="", $D$6&"|"&$D$7&"|"&$D$8, $D$6&"|"&$D$7&"|"&$D$8&"|"&$D$9), $AA$105:$AA$153, 0)), IFERROR(INDEX($AF$105:$AF$153, MATCH($D$6&"|"&$D$7&"|"&$D$8, $AB$105:$AB$153, 0)), "Earth Work Operation")) -> Earth work in surface excavation not exceeding 30 cm in depth but exceeding 1.5 m in width as well as 10 sqm on plan including getting out and disposal of excavated earth upto 50 m and lift upto 1.5 m, as directed by Engineer-in- Charge:: All kinds of soil Details of cost for 100 Sqm LABOUR
A14: Published Reference Say Rate (Benchmark) | D14: =IFERROR(INDEX($AE$105:$AE$153, MATCH(IF($D$9="", $D$6&"|"&$D$7&"|"&$D$8, $D$6&"|"&$D$7&"|"&$D$8&"|"&$D$9), $AA$105:$AA$153, 0)), IFERROR(INDEX($AE$105:$AE$153, MATCH($D$6&"|"&$D$7&"|"&$D$8, $AB$105:$AB$153, 0)), 92.55)) -> 92.55 | E14: =D11 -> sqm | F14: LOOKUP | G14: Official CPWD DAR 2019 Volume 1 published rate for identical scope and strata.
A15: AUDIT VERIFICATION STATUS: | D15: =IF(AND(H58<=0.05, H58>=-0.05), "[PASS] 100% DAR MATCH", "[ALERT] VARIANCE DETECTED") -> [PASS] 100% DAR MATCH | E15: Cost Base: | F15: =IF(H41>0, "OK", "ERR: W<=0") -> OK | G15: Live variance check against published CPWD DAR 2019 Volume 1 Say Rate. Target variance: ₹ 0.00.
A17: 1B. PARAMETRIC OPERATIONAL SPECIFICATION PROFILE (5 CORE CIVIL WORK LEVERS) | P17: HELPER TABLE 1B: OPERATIONAL LEVER MULTIPLIER RULES (Lookup Source for Table 2 Col Q)
A18: Operational Work Lever | D18: Active Execution Mechanism / Field Technique | E18: CPWD Standard Field Specification & Practical Engineering Scope Notes | P18: Resource Code | Q18: Resource Description & Trade Role | R18: Governing Civil Lever | S18: Active Multiplier
A19: 1. Loosening / Digging Mode | D19: =IFERROR(INDEX($AG$105:$AG$153, MATCH(IF($D$9="", $D$6&"|"&$D$7&"|"&$D$8, $D$6&"|"&$D$7&"|"&$D$8&"|"&$D$9), $AA$105:$AA$153, 0)), IFERROR(INDEX($AG$105:$AG$153, MATCH($D$6&"|"&$D$7&"|"&$D$8, $AB$105:$AB$153, 0)), "Standard Digging")) -> Manual Pickaxe / Beldar | E19: Loosening of soil/rock crust to required formation level or trench invert. | P19: 0101 | Q19: Bhishti (Compaction Watering to OMC) | R19: Lever 4: Compaction Watering ($D$22) | S19: =IF($D$22="NO", 0, 1) -> 1
A20: 2. Handling & Haulage Boundary | D20: =IFERROR(INDEX($AH$105:$AH$153, MATCH(IF($D$9="", $D$6&"|"&$D$7&"|"&$D$8, $D$6&"|"&$D$7&"|"&$D$8&"|"&$D$9), $AA$105:$AA$153, 0)), IFERROR(INDEX($AH$105:$AH$153, MATCH($D$6&"|"&$D$7&"|"&$D$8, $AB$105:$AB$153, 0)), "Standard Haulage")) -> Manual Basket (≤50m lead, ≤1.5m lift) | E20: Haulage boundary: lead up to 50 m and lift up to 1.5 m from excavation face. | P20: 0003 | Q20: 10 Tonne Road Roller (Compaction) | R20: Lever 5: Power Roller Compaction ($D$23) | S20: =IF($D$23="NO", 0, 1) -> 1
A21: 3. Layer Placement & Spreading | D21: =IFERROR(INDEX($AI$105:$AI$153, MATCH(IF($D$9="", $D$6&"|"&$D$7&"|"&$D$8, $D$6&"|"&$D$7&"|"&$D$8&"|"&$D$9), $AA$105:$AA$153, 0)), IFERROR(INDEX($AI$105:$AI$153, MATCH($D$6&"|"&$D$7&"|"&$D$8, $AB$105:$AB$153, 0)), "Standard Spreading")) -> Dressing & grading surface | E21: Depositing excavated earth in uniform layers ≤20 cm depth, breaking clods and shaping slopes. | P21: 0011 | Q21: Chowkidar (Road Roller Guard) | R21: Lever 5: Power Roller Compaction ($D$23) | S21: =IF($D$23="NO", 0, 1) -> 1
A22: 4. Compaction Watering to OMC | D22: YES | E22: =IF(ISNUMBER(SEARCH("Embankment", $D$6)), IF($D$22="YES", "Watering included in item specification (0.40 Bhishti-day / 10 cum to achieve OMC). Full rate applies.", "DEDUCTION APPLIED (DAR Item 2.5): 0.40 Bhishti-day @ Rs 617 = Rs 246.80 direct. With GST 14.05% (Rs 34.68) + CPOH 15% (Rs 42.22) + Cess 1% (Rs 3.24) = Total Rs 326.94/10 cum -> Rate reduced by Rs 33.00/cum (-Rs 32.70 exact)."), "Surface Excavation, Foundation Trenches, Jungle Clearance, Timbering Item specification does not include watering/compaction. (No deduction applicable).") -> Surface Excavation, Foundation Trenches, Jungle Clearance, Timbering Item specification does not include watering/compaction. (No deduction applicable). | P22: 0113 | Q22: Sundries (Road Roller) | R22: Lever 5: Power Roller Compaction ($D$23) | S22: =IF($D$23="NO", 0, 1) -> 1
A23: 5. Compaction Mechanism | D23: YES | E23: =IF(ISNUMBER(SEARCH("Embankment", $D$6)), IF($D$23="YES", "Power rolling included in item specification (0.008 roller-day / 10 cum). Full rate applies.", "DEDUCTION APPLIED (DAR Item 2.4): 0.008 Roller @ Rs 3000 (Rs 24.00) + 0.008 Chowkidar (Rs 4.46) + Sundries (Rs 3.64) = Rs 32.10 direct. Compounded total = Rs 42.95/10 cum -> Rate reduced by Rs 4.30/cum (-Rs 4.30 exact)."), "Surface Excavation, Foundation Trenches, Jungle Clearance, Timbering Item specification does not include watering/compaction. (No deduction applicable).") -> Surface Excavation, Foundation Trenches, Jungle Clearance, Timbering Item specification does not include watering/compaction. (No deduction applicable).
A25: 2. ACTIVE RESOURCE BUILD-UP (Auto-populated from Table 5E Ground-Truth Norms; Equipment codes include fuel & crew) | P25: HELPER TABLE 2: FIRST-PRINCIPLES QUANTITY RESOLVER (Calculates Table 2 Col F) | S25: DEDICATED ENGINEERING LOGIC, PRECEDENTS & AUDIT TABLE (Precedents, Site Mechanics & Shift Derivation)
A26: Line | B26: Resource Code | C26: Resource Name & Description | D26: Resource Category | E26: Unit | F26: Norm Input Qty | G26: Unit Rate (₹) | H26: Line Amount (₹) | I26: Include? / Apply | J26: Cost Share % | K26: Daily Productivity Norm | L26: Specific Effort | M26: Hourly Pace | N26: Field Guidance Note | O26: Engineering First-Principles & 8-Hour Shift Logic | P26: Base Physical Norm (D10 / Kr) | Q26: Lever Factor (Helper 1B Lookup) | R26: Net Calculated Quantity | S26: Governing Operational Precedent | T26: Live Precedent & Calculation Trace | U26: Engineering First-Principles (Physical Mechanics) | V26: CPWD 8-Hour Shift Logic (Mathematical Derivation) | W26: Contractual Omission & Deduction Audit Clause
A27: 1 | B27: =IFERROR(INDEX($F$105:$F$282, MATCH($D$6&"|"&$D$7&"|"&$D$8&"|"&$D$9&"|"&1, $J$105:$J$282, 0)), "") -> 0114 | C27: =IF(B27="","", IFERROR(INDEX(Rates_Master!$C:$C, MATCH(B27, Rates_Master!$A:$A, 0)), "Custom Resource")) -> Beldar | D27: =IF(B27="","", IFERROR(INDEX(Rates_Master!$B:$B, MATCH(B27, Rates_Master!$A:$A, 0)), "Labour")) -> Labour Wages | E27: =IF(B27="","", IFERROR(INDEX(Rates_Master!$D:$D, MATCH(B27, Rates_Master!$A:$A, 0)), "day")) -> day | F27: =IF(B27="","", R27) -> 6.8 | G27: =IF(B27="","", IFERROR(INDEX(Rates_Master!$E:$E, MATCH(B27, Rates_Master!$A:$A, 0)), 0)) -> 558 | H27: =IF(OR(B27="", F27=""), 0, ROUND(F27 * G27, 2)) -> 3794.4 | I27: =IF(B27="","", IF(ISNUMBER(SEARCH("2.10", B27)), "A", "W")) -> W | J27: =IF(H$41>0, ROUND(H27 / H$41 * 100, 1), 0) -> 54.8 | K27: =IFERROR(INDEX($G$105:$G$282, MATCH($D$6&"|"&$D$7&"|"&$D$8&"|"&$D$9&"|"&1, $J$105:$J$282, 0)), "") -> 14.705882 | L27: =IF(AND(ISNUMBER(F27), F27>0, D$10>0), ROUND(F27 * 8 / D$10, 4), "") -> 0.544 | M27: =IF(AND(ISNUMBER(F27), F27>0, D$10>0), ROUND(D$10 / (F27 * 8), 2), "") -> 1.84 | N27: =IF(B27="","", "CPWD Standard Earthwork Production Resource") -> CPWD Standard Earthwork Production Resource | O27: =IF(B27="","", V27) -> Gang: 4 Beldars × 13.60 h = 54.40 man-hrs ÷ 8.00 h = 6.800 Beldar-days per 100 sqm. Daily productivity norm P = 14.71 sqm/8-hr shift (SE = 0.544 hr/sqm, pace = 32.6 min/sqm). | P27: =IF(B27="","", IF(AND(ISNUMBER(K27), K27>0), ROUND(D$10/K27, 5), IFERROR(INDEX($K$105:$K$282, MATCH($D$6&"|"&$D$7&"|"&$D$8&"|"&$D$9&"|"&1, $J$105:$J$282, 0)), 0))) -> 6.8 | Q27: =IF(B27="","", IFERROR(VLOOKUP(B27, $P$19:$S$22, 4, FALSE), 1)) -> 1 | R27: =IF(B27="","", ROUND(P27 * Q27, 5)) -> 6.8 | S27: =IF(B27="","", IF(B27="0101", "Lever 4: Compaction Watering ($D$22 = " & $D$22 & ")", IF(OR(B27="0003", B27="0011", B27="0113"), "Lever 5: Power Rolling ($D$23 = " & $D$23 & ")", "Core Scope Baseline (Mandatory Execution)"))) -> Core Scope Baseline (Mandatory Execution) | T27: =IF(B27="","", "Batch Q=" & TEXT(D$10, "0.00") & " " & $D$11 & " | Norm K=" & TEXT(K27, "0.00") & " | Factor=" & TEXT(Q27, "0.00") & " | Qty F=" & TEXT(F27, "0.000") & " " & E27 & " | Rate G=Rs " & TEXT(G27, "0.00") & " | Amt H=Rs " & TEXT(H27, "0.00")) -> Batch Q=100.00 sqm | Norm K=14.71 | Factor=1.00 | Qty F=6.800 day | Rate G=Rs 558.00 | Amt H=Rs 3794.40 | U27: =IF(B27="","", IFERROR(INDEX($H$105:$H$282, MATCH($D$6&"|"&$D$7&"|"&$D$8&"|"&$D$9&"|"&1, $J$105:$J$282, 0)), "")) -> Manual pickaxe and phowrah loosening of hard dry soil crust up to 30 cm depth, spade trimming to formation level, and clod pulverization. | V27: =IF(B27="","", IFERROR(INDEX($I$105:$I$282, MATCH($D$6&"|"&$D$7&"|"&$D$8&"|"&$D$9&"|"&1, $J$105:$J$282, 0)), "")) -> Gang: 4 Beldars × 13.60 h = 54.40 man-hrs ÷ 8.00 h = 6.800 Beldar-days per 100 sqm. Daily productivity norm P = 14.71 sqm/8-hr shift (SE = 0.544 hr/sqm, pace = 32.6 min/sqm). | W27: =IF(B27="","", IF(B27="0101", IF($D$22="NO", "OMITTED DEDUCTION (DAR Item 2.5): 0.40 Bhishti @ Rs 617 = Rs 246.80 direct. Compounded total = Rs 326.94/10 cum -> Rate deduction Rs 33.00/cum.", "ACTIVE: Compaction watering included in standard item scope."), IF(OR(B27="0003", B27="0011", B27="0113"), IF($D$23="NO", "OMITTED DEDUCTION (DAR Item 2.4): 0.008 Roller + Chowkidar + Sundries = Rs 32.10 direct. Compounded total = Rs 42.95/10 cum -> Rate deduction Rs 4.30/cum.", "ACTIVE: Power rolling included in standard item scope."), "MANDATORY: Not subject to omission or separate deduction."))) -> MANDATORY: Not subject to omission or separate deduction.
A28: 2 | B28: =IFERROR(INDEX($F$105:$F$282, MATCH($D$6&"|"&$D$7&"|"&$D$8&"|"&$D$9&"|"&2, $J$105:$J$282, 0)), "") -> 0115 | C28: =IF(B28="","", IFERROR(INDEX(Rates_Master!$C:$C, MATCH(B28, Rates_Master!$A:$A, 0)), "Custom Resource")) -> Coolie | D28: =IF(B28="","", IFERROR(INDEX(Rates_Master!$B:$B, MATCH(B28, Rates_Master!$A:$A, 0)), "Labour")) -> Labour Wages | E28: =IF(B28="","", IFERROR(INDEX(Rates_Master!$D:$D, MATCH(B28, Rates_Master!$A:$A, 0)), "day")) -> day | F28: =IF(B28="","", R28) -> 5.6 | G28: =IF(B28="","", IFERROR(INDEX(Rates_Master!$E:$E, MATCH(B28, Rates_Master!$A:$A, 0)), 0)) -> 558 | H28: =IF(OR(B28="", F28=""), 0, ROUND(F28 * G28, 2)) -> 3124.8 | I28: =IF(B28="","", IF(ISNUMBER(SEARCH("2.10", B28)), "A", "W")) -> W | J28: =IF(H$41>0, ROUND(H28 / H$41 * 100, 1), 0) -> 45.2 | K28: =IFERROR(INDEX($G$105:$G$282, MATCH($D$6&"|"&$D$7&"|"&$D$8&"|"&$D$9&"|"&2, $J$105:$J$282, 0)), "") -> 17.857143 | L28: =IF(AND(ISNUMBER(F28), F28>0, D$10>0), ROUND(F28 * 8 / D$10, 4), "") -> 0.448 | M28: =IF(AND(ISNUMBER(F28), F28>0, D$10>0), ROUND(D$10 / (F28 * 8), 2), "") -> 2.23 | N28: =IF(B28="","", "CPWD Standard Earthwork Production Resource") -> CPWD Standard Earthwork Production Resource | O28: =IF(B28="","", V28) -> Gang: 4 Coolies × 11.20 h = 44.80 man-hrs ÷ 8.00 h = 5.600 Coolie-days per 100 sqm. Daily productivity norm P = 17.86 sqm/8-hr shift (SE = 0.448 hr/sqm, pace = 26.9 min/sqm). | P28: =IF(B28="","", IF(AND(ISNUMBER(K28), K28>0), ROUND(D$10/K28, 5), IFERROR(INDEX($K$105:$K$282, MATCH($D$6&"|"&$D$7&"|"&$D$8&"|"&$D$9&"|"&2, $J$105:$J$282, 0)), 0))) -> 5.6 | Q28: =IF(B28="","", IFERROR(VLOOKUP(B28, $P$19:$S$22, 4, FALSE), 1)) -> 1 | R28: =IF(B28="","", ROUND(P28 * Q28, 5)) -> 5.6 | S28: =IF(B28="","", IF(B28="0101", "Lever 4: Compaction Watering ($D$22 = " & $D$22 & ")", IF(OR(B28="0003", B28="0011", B28="0113"), "Lever 5: Power Rolling ($D$23 = " & $D$23 & ")", "Core Scope Baseline (Mandatory Execution)"))) -> Core Scope Baseline (Mandatory Execution) | T28: =IF(B28="","", "Batch Q=" & TEXT(D$10, "0.00") & " " & $D$11 & " | Norm K=" & TEXT(K28, "0.00") & " | Factor=" & TEXT(Q28, "0.00") & " | Qty F=" & TEXT(F28, "0.000") & " " & E28 & " | Rate G=Rs " & TEXT(G28, "0.00") & " | Amt H=Rs " & TEXT(H28, "0.00")) -> Batch Q=100.00 sqm | Norm K=17.86 | Factor=1.00 | Qty F=5.600 day | Rate G=Rs 558.00 | Amt H=Rs 3124.80 | U28: =IF(B28="","", IFERROR(INDEX($H$105:$H$282, MATCH($D$6&"|"&$D$7&"|"&$D$8&"|"&$D$9&"|"&2, $J$105:$J$282, 0)), "")) -> Manual tagari/basket loading with shovel, haulage within 50 m lead, and tipping onto spoil banks (lift ≤1.5 m). | V28: =IF(B28="","", IFERROR(INDEX($I$105:$I$282, MATCH($D$6&"|"&$D$7&"|"&$D$8&"|"&$D$9&"|"&2, $J$105:$J$282, 0)), "")) -> Gang: 4 Coolies × 11.20 h = 44.80 man-hrs ÷ 8.00 h = 5.600 Coolie-days per 100 sqm. Daily productivity norm P = 17.86 sqm/8-hr shift (SE = 0.448 hr/sqm, pace = 26.9 min/sqm). | W28: =IF(B28="","", IF(B28="0101", IF($D$22="NO", "OMITTED DEDUCTION (DAR Item 2.5): 0.40 Bhishti @ Rs 617 = Rs 246.80 direct. Compounded total = Rs 326.94/10 cum -> Rate deduction Rs 33.00/cum.", "ACTIVE: Compaction watering included in standard item scope."), IF(OR(B28="0003", B28="0011", B28="0113"), IF($D$23="NO", "OMITTED DEDUCTION (DAR Item 2.4): 0.008 Roller + Chowkidar + Sundries = Rs 32.10 direct. Compounded total = Rs 42.95/10 cum -> Rate deduction Rs 4.30/cum.", "ACTIVE: Power rolling included in standard item scope."), "MANDATORY: Not subject to omission or separate deduction."))) -> MANDATORY: Not subject to omission or separate deduction.
A29: 3 | B29: =IFERROR(INDEX($F$105:$F$282, MATCH($D$6&"|"&$D$7&"|"&$D$8&"|"&$D$9&"|"&3, $J$105:$J$282, 0)), "") | C29: =IF(B29="","", IFERROR(INDEX(Rates_Master!$C:$C, MATCH(B29, Rates_Master!$A:$A, 0)), "Custom Resource")) | D29: =IF(B29="","", IFERROR(INDEX(Rates_Master!$B:$B, MATCH(B29, Rates_Master!$A:$A, 0)), "Labour")) | E29: =IF(B29="","", IFERROR(INDEX(Rates_Master!$D:$D, MATCH(B29, Rates_Master!$A:$A, 0)), "day")) | F29: =IF(B29="","", R29) | G29: =IF(B29="","", IFERROR(INDEX(Rates_Master!$E:$E, MATCH(B29, Rates_Master!$A:$A, 0)), 0)) | H29: =IF(OR(B29="", F29=""), 0, ROUND(F29 * G29, 2)) -> 0 | I29: =IF(B29="","", IF(ISNUMBER(SEARCH("2.10", B29)), "A", "W")) | J29: =IF(H$41>0, ROUND(H29 / H$41 * 100, 1), 0) -> 0 | K29: =IFERROR(INDEX($G$105:$G$282, MATCH($D$6&"|"&$D$7&"|"&$D$8&"|"&$D$9&"|"&3, $J$105:$J$282, 0)), "") | L29: =IF(AND(ISNUMBER(F29), F29>0, D$10>0), ROUND(F29 * 8 / D$10, 4), "") | M29: =IF(AND(ISNUMBER(F29), F29>0, D$10>0), ROUND(D$10 / (F29 * 8), 2), "") | N29: =IF(B29="","", "CPWD Standard Earthwork Production Resource") | O29: =IF(B29="","", V29) | P29: =IF(B29="","", IF(AND(ISNUMBER(K29), K29>0), ROUND(D$10/K29, 5), IFERROR(INDEX($K$105:$K$282, MATCH($D$6&"|"&$D$7&"|"&$D$8&"|"&$D$9&"|"&3, $J$105:$J$282, 0)), 0))) | Q29: =IF(B29="","", IFERROR(VLOOKUP(B29, $P$19:$S$22, 4, FALSE), 1)) | R29: =IF(B29="","", ROUND(P29 * Q29, 5)) | S29: =IF(B29="","", IF(B29="0101", "Lever 4: Compaction Watering ($D$22 = " & $D$22 & ")", IF(OR(B29="0003", B29="0011", B29="0113"), "Lever 5: Power Rolling ($D$23 = " & $D$23 & ")", "Core Scope Baseline (Mandatory Execution)"))) | T29: =IF(B29="","", "Batch Q=" & TEXT(D$10, "0.00") & " " & $D$11 & " | Norm K=" & TEXT(K29, "0.00") & " | Factor=" & TEXT(Q29, "0.00") & " | Qty F=" & TEXT(F29, "0.000") & " " & E29 & " | Rate G=Rs " & TEXT(G29, "0.00") & " | Amt H=Rs " & TEXT(H29, "0.00")) | U29: =IF(B29="","", IFERROR(INDEX($H$105:$H$282, MATCH($D$6&"|"&$D$7&"|"&$D$8&"|"&$D$9&"|"&3, $J$105:$J$282, 0)), "")) | V29: =IF(B29="","", IFERROR(INDEX($I$105:$I$282, MATCH($D$6&"|"&$D$7&"|"&$D$8&"|"&$D$9&"|"&3, $J$105:$J$282, 0)), "")) | W29: =IF(B29="","", IF(B29="0101", IF($D$22="NO", "OMITTED DEDUCTION (DAR Item 2.5): 0.40 Bhishti @ Rs 617 = Rs 246.80 direct. Compounded total = Rs 326.94/10 cum -> Rate deduction Rs 33.00/cum.", "ACTIVE: Compaction watering included in standard item scope."), IF(OR(B29="0003", B29="0011", B29="0113"), IF($D$23="NO", "OMITTED DEDUCTION (DAR Item 2.4): 0.008 Roller + Chowkidar + Sundries = Rs 32.10 direct. Compounded total = Rs 42.95/10 cum -> Rate deduction Rs 4.30/cum.", "ACTIVE: Power rolling included in standard item scope."), "MANDATORY: Not subject to omission or separate deduction.")))
A30: 4 | B30: =IFERROR(INDEX($F$105:$F$282, MATCH($D$6&"|"&$D$7&"|"&$D$8&"|"&$D$9&"|"&4, $J$105:$J$282, 0)), "") | C30: =IF(B30="","", IFERROR(INDEX(Rates_Master!$C:$C, MATCH(B30, Rates_Master!$A:$A, 0)), "Custom Resource")) | D30: =IF(B30="","", IFERROR(INDEX(Rates_Master!$B:$B, MATCH(B30, Rates_Master!$A:$A, 0)), "Labour")) | E30: =IF(B30="","", IFERROR(INDEX(Rates_Master!$D:$D, MATCH(B30, Rates_Master!$A:$A, 0)), "day")) | F30: =IF(B30="","", R30) | G30: =IF(B30="","", IFERROR(INDEX(Rates_Master!$E:$E, MATCH(B30, Rates_Master!$A:$A, 0)), 0)) | H30: =IF(OR(B30="", F30=""), 0, ROUND(F30 * G30, 2)) -> 0 | I30: =IF(B30="","", IF(ISNUMBER(SEARCH("2.10", B30)), "A", "W")) | J30: =IF(H$41>0, ROUND(H30 / H$41 * 100, 1), 0) -> 0 | K30: =IFERROR(INDEX($G$105:$G$282, MATCH($D$6&"|"&$D$7&"|"&$D$8&"|"&$D$9&"|"&4, $J$105:$J$282, 0)), "") | L30: =IF(AND(ISNUMBER(F30), F30>0, D$10>0), ROUND(F30 * 8 / D$10, 4), "") | M30: =IF(AND(ISNUMBER(F30), F30>0, D$10>0), ROUND(D$10 / (F30 * 8), 2), "") | N30: =IF(B30="","", "CPWD Standard Earthwork Production Resource") | O30: =IF(B30="","", V30) | P30: =IF(B30="","", IF(AND(ISNUMBER(K30), K30>0), ROUND(D$10/K30, 5), IFERROR(INDEX($K$105:$K$282, MATCH($D$6&"|"&$D$7&"|"&$D$8&"|"&$D$9&"|"&4, $J$105:$J$282, 0)), 0))) | Q30: =IF(B30="","", IFERROR(VLOOKUP(B30, $P$19:$S$22, 4, FALSE), 1)) | R30: =IF(B30="","", ROUND(P30 * Q30, 5)) | S30: =IF(B30="","", IF(B30="0101", "Lever 4: Compaction Watering ($D$22 = " & $D$22 & ")", IF(OR(B30="0003", B30="0011", B30="0113"), "Lever 5: Power Rolling ($D$23 = " & $D$23 & ")", "Core Scope Baseline (Mandatory Execution)"))) | T30: =IF(B30="","", "Batch Q=" & TEXT(D$10, "0.00") & " " & $D$11 & " | Norm K=" & TEXT(K30, "0.00") & " | Factor=" & TEXT(Q30, "0.00") & " | Qty F=" & TEXT(F30, "0.000") & " " & E30 & " | Rate G=Rs " & TEXT(G30, "0.00") & " | Amt H=Rs " & TEXT(H30, "0.00")) | U30: =IF(B30="","", IFERROR(INDEX($H$105:$H$282, MATCH($D$6&"|"&$D$7&"|"&$D$8&"|"&$D$9&"|"&4, $J$105:$J$282, 0)), "")) | V30: =IF(B30="","", IFERROR(INDEX($I$105:$I$282, MATCH($D$6&"|"&$D$7&"|"&$D$8&"|"&$D$9&"|"&4, $J$105:$J$282, 0)), "")) | W30: =IF(B30="","", IF(B30="0101", IF($D$22="NO", "OMITTED DEDUCTION (DAR Item 2.5): 0.40 Bhishti @ Rs 617 = Rs 246.80 direct. Compounded total = Rs 326.94/10 cum -> Rate deduction Rs 33.00/cum.", "ACTIVE: Compaction watering included in standard item scope."), IF(OR(B30="0003", B30="0011", B30="0113"), IF($D$23="NO", "OMITTED DEDUCTION (DAR Item 2.4): 0.008 Roller + Chowkidar + Sundries = Rs 32.10 direct. Compounded total = Rs 42.95/10 cum -> Rate deduction Rs 4.30/cum.", "ACTIVE: Power rolling included in standard item scope."), "MANDATORY: Not subject to omission or separate deduction.")))
A31: 5 | B31: =IFERROR(INDEX($F$105:$F$282, MATCH($D$6&"|"&$D$7&"|"&$D$8&"|"&$D$9&"|"&5, $J$105:$J$282, 0)), "") | C31: =IF(B31="","", IFERROR(INDEX(Rates_Master!$C:$C, MATCH(B31, Rates_Master!$A:$A, 0)), "Custom Resource")) | D31: =IF(B31="","", IFERROR(INDEX(Rates_Master!$B:$B, MATCH(B31, Rates_Master!$A:$A, 0)), "Labour")) | E31: =IF(B31="","", IFERROR(INDEX(Rates_Master!$D:$D, MATCH(B31, Rates_Master!$A:$A, 0)), "day")) | F31: =IF(B31="","", R31) | G31: =IF(B31="","", IFERROR(INDEX(Rates_Master!$E:$E, MATCH(B31, Rates_Master!$A:$A, 0)), 0)) | H31: =IF(OR(B31="", F31=""), 0, ROUND(F31 * G31, 2)) -> 0 | I31: =IF(B31="","", IF(ISNUMBER(SEARCH("2.10", B31)), "A", "W")) | J31: =IF(H$41>0, ROUND(H31 / H$41 * 100, 1), 0) -> 0 | K31: =IFERROR(INDEX($G$105:$G$282, MATCH($D$6&"|"&$D$7&"|"&$D$8&"|"&$D$9&"|"&5, $J$105:$J$282, 0)), "") | L31: =IF(AND(ISNUMBER(F31), F31>0, D$10>0), ROUND(F31 * 8 / D$10, 4), "") | M31: =IF(AND(ISNUMBER(F31), F31>0, D$10>0), ROUND(D$10 / (F31 * 8), 2), "") | N31: =IF(B31="","", "CPWD Standard Earthwork Production Resource") | O31: =IF(B31="","", V31) | P31: =IF(B31="","", IF(AND(ISNUMBER(K31), K31>0), ROUND(D$10/K31, 5), IFERROR(INDEX($K$105:$K$282, MATCH($D$6&"|"&$D$7&"|"&$D$8&"|"&$D$9&"|"&5, $J$105:$J$282, 0)), 0))) | Q31: =IF(B31="","", IFERROR(VLOOKUP(B31, $P$19:$S$22, 4, FALSE), 1)) | R31: =IF(B31="","", ROUND(P31 * Q31, 5)) | S31: =IF(B31="","", IF(B31="0101", "Lever 4: Compaction Watering ($D$22 = " & $D$22 & ")", IF(OR(B31="0003", B31="0011", B31="0113"), "Lever 5: Power Rolling ($D$23 = " & $D$23 & ")", "Core Scope Baseline (Mandatory Execution)"))) | T31: =IF(B31="","", "Batch Q=" & TEXT(D$10, "0.00") & " " & $D$11 & " | Norm K=" & TEXT(K31, "0.00") & " | Factor=" & TEXT(Q31, "0.00") & " | Qty F=" & TEXT(F31, "0.000") & " " & E31 & " | Rate G=Rs " & TEXT(G31, "0.00") & " | Amt H=Rs " & TEXT(H31, "0.00")) | U31: =IF(B31="","", IFERROR(INDEX($H$105:$H$282, MATCH($D$6&"|"&$D$7&"|"&$D$8&"|"&$D$9&"|"&5, $J$105:$J$282, 0)), "")) | V31: =IF(B31="","", IFERROR(INDEX($I$105:$I$282, MATCH($D$6&"|"&$D$7&"|"&$D$8&"|"&$D$9&"|"&5, $J$105:$J$282, 0)), "")) | W31: =IF(B31="","", IF(B31="0101", IF($D$22="NO", "OMITTED DEDUCTION (DAR Item 2.5): 0.40 Bhishti @ Rs 617 = Rs 246.80 direct. Compounded total = Rs 326.94/10 cum -> Rate deduction Rs 33.00/cum.", "ACTIVE: Compaction watering included in standard item scope."), IF(OR(B31="0003", B31="0011", B31="0113"), IF($D$23="NO", "OMITTED DEDUCTION (DAR Item 2.4): 0.008 Roller + Chowkidar + Sundries = Rs 32.10 direct. Compounded total = Rs 42.95/10 cum -> Rate deduction Rs 4.30/cum.", "ACTIVE: Power rolling included in standard item scope."), "MANDATORY: Not subject to omission or separate deduction.")))
A32: 6 | B32: =IFERROR(INDEX($F$105:$F$282, MATCH($D$6&"|"&$D$7&"|"&$D$8&"|"&$D$9&"|"&6, $J$105:$J$282, 0)), "") | C32: =IF(B32="","", IFERROR(INDEX(Rates_Master!$C:$C, MATCH(B32, Rates_Master!$A:$A, 0)), "Custom Resource")) | D32: =IF(B32="","", IFERROR(INDEX(Rates_Master!$B:$B, MATCH(B32, Rates_Master!$A:$A, 0)), "Labour")) | E32: =IF(B32="","", IFERROR(INDEX(Rates_Master!$D:$D, MATCH(B32, Rates_Master!$A:$A, 0)), "day")) | F32: =IF(B32="","", R32) | G32: =IF(B32="","", IFERROR(INDEX(Rates_Master!$E:$E, MATCH(B32, Rates_Master!$A:$A, 0)), 0)) | H32: =IF(OR(B32="", F32=""), 0, ROUND(F32 * G32, 2)) -> 0 | I32: =IF(B32="","", IF(ISNUMBER(SEARCH("2.10", B32)), "A", "W")) | J32: =IF(H$41>0, ROUND(H32 / H$41 * 100, 1), 0) -> 0 | K32: =IFERROR(INDEX($G$105:$G$282, MATCH($D$6&"|"&$D$7&"|"&$D$8&"|"&$D$9&"|"&6, $J$105:$J$282, 0)), "") | L32: =IF(AND(ISNUMBER(F32), F32>0, D$10>0), ROUND(F32 * 8 / D$10, 4), "") | M32: =IF(AND(ISNUMBER(F32), F32>0, D$10>0), ROUND(D$10 / (F32 * 8), 2), "") | N32: =IF(B32="","", "CPWD Standard Earthwork Production Resource") | O32: =IF(B32="","", V32) | P32: =IF(B32="","", IF(AND(ISNUMBER(K32), K32>0), ROUND(D$10/K32, 5), IFERROR(INDEX($K$105:$K$282, MATCH($D$6&"|"&$D$7&"|"&$D$8&"|"&$D$9&"|"&6, $J$105:$J$282, 0)), 0))) | Q32: =IF(B32="","", IFERROR(VLOOKUP(B32, $P$19:$S$22, 4, FALSE), 1)) | R32: =IF(B32="","", ROUND(P32 * Q32, 5)) | S32: =IF(B32="","", IF(B32="0101", "Lever 4: Compaction Watering ($D$22 = " & $D$22 & ")", IF(OR(B32="0003", B32="0011", B32="0113"), "Lever 5: Power Rolling ($D$23 = " & $D$23 & ")", "Core Scope Baseline (Mandatory Execution)"))) | T32: =IF(B32="","", "Batch Q=" & TEXT(D$10, "0.00") & " " & $D$11 & " | Norm K=" & TEXT(K32, "0.00") & " | Factor=" & TEXT(Q32, "0.00") & " | Qty F=" & TEXT(F32, "0.000") & " " & E32 & " | Rate G=Rs " & TEXT(G32, "0.00") & " | Amt H=Rs " & TEXT(H32, "0.00")) | U32: =IF(B32="","", IFERROR(INDEX($H$105:$H$282, MATCH($D$6&"|"&$D$7&"|"&$D$8&"|"&$D$9&"|"&6, $J$105:$J$282, 0)), "")) | V32: =IF(B32="","", IFERROR(INDEX($I$105:$I$282, MATCH($D$6&"|"&$D$7&"|"&$D$8&"|"&$D$9&"|"&6, $J$105:$J$282, 0)), "")) | W32: =IF(B32="","", IF(B32="0101", IF($D$22="NO", "OMITTED DEDUCTION (DAR Item 2.5): 0.40 Bhishti @ Rs 617 = Rs 246.80 direct. Compounded total = Rs 326.94/10 cum -> Rate deduction Rs 33.00/cum.", "ACTIVE: Compaction watering included in standard item scope."), IF(OR(B32="0003", B32="0011", B32="0113"), IF($D$23="NO", "OMITTED DEDUCTION (DAR Item 2.4): 0.008 Roller + Chowkidar + Sundries = Rs 32.10 direct. Compounded total = Rs 42.95/10 cum -> Rate deduction Rs 4.30/cum.", "ACTIVE: Power rolling included in standard item scope."), "MANDATORY: Not subject to omission or separate deduction.")))
A33: 7 | B33: =IFERROR(INDEX($F$105:$F$282, MATCH($D$6&"|"&$D$7&"|"&$D$8&"|"&$D$9&"|"&7, $J$105:$J$282, 0)), "") | C33: =IF(B33="","", IFERROR(INDEX(Rates_Master!$C:$C, MATCH(B33, Rates_Master!$A:$A, 0)), "Custom Resource")) | D33: =IF(B33="","", IFERROR(INDEX(Rates_Master!$B:$B, MATCH(B33, Rates_Master!$A:$A, 0)), "Labour")) | E33: =IF(B33="","", IFERROR(INDEX(Rates_Master!$D:$D, MATCH(B33, Rates_Master!$A:$A, 0)), "day")) | F33: =IF(B33="","", R33) | G33: =IF(B33="","", IFERROR(INDEX(Rates_Master!$E:$E, MATCH(B33, Rates_Master!$A:$A, 0)), 0)) | H33: =IF(OR(B33="", F33=""), 0, ROUND(F33 * G33, 2)) -> 0 | I33: =IF(B33="","", IF(ISNUMBER(SEARCH("2.10", B33)), "A", "W")) | J33: =IF(H$41>0, ROUND(H33 / H$41 * 100, 1), 0) -> 0 | K33: =IFERROR(INDEX($G$105:$G$282, MATCH($D$6&"|"&$D$7&"|"&$D$8&"|"&$D$9&"|"&7, $J$105:$J$282, 0)), "") | L33: =IF(AND(ISNUMBER(F33), F33>0, D$10>0), ROUND(F33 * 8 / D$10, 4), "") | M33: =IF(AND(ISNUMBER(F33), F33>0, D$10>0), ROUND(D$10 / (F33 * 8), 2), "") | N33: =IF(B33="","", "CPWD Standard Earthwork Production Resource") | O33: =IF(B33="","", V33) | P33: =IF(B33="","", IF(AND(ISNUMBER(K33), K33>0), ROUND(D$10/K33, 5), IFERROR(INDEX($K$105:$K$282, MATCH($D$6&"|"&$D$7&"|"&$D$8&"|"&$D$9&"|"&7, $J$105:$J$282, 0)), 0))) | Q33: =IF(B33="","", IFERROR(VLOOKUP(B33, $P$19:$S$22, 4, FALSE), 1)) | R33: =IF(B33="","", ROUND(P33 * Q33, 5)) | S33: =IF(B33="","", IF(B33="0101", "Lever 4: Compaction Watering ($D$22 = " & $D$22 & ")", IF(OR(B33="0003", B33="0011", B33="0113"), "Lever 5: Power Rolling ($D$23 = " & $D$23 & ")", "Core Scope Baseline (Mandatory Execution)"))) | T33: =IF(B33="","", "Batch Q=" & TEXT(D$10, "0.00") & " " & $D$11 & " | Norm K=" & TEXT(K33, "0.00") & " | Factor=" & TEXT(Q33, "0.00") & " | Qty F=" & TEXT(F33, "0.000") & " " & E33 & " | Rate G=Rs " & TEXT(G33, "0.00") & " | Amt H=Rs " & TEXT(H33, "0.00")) | U33: =IF(B33="","", IFERROR(INDEX($H$105:$H$282, MATCH($D$6&"|"&$D$7&"|"&$D$8&"|"&$D$9&"|"&7, $J$105:$J$282, 0)), "")) | V33: =IF(B33="","", IFERROR(INDEX($I$105:$I$282, MATCH($D$6&"|"&$D$7&"|"&$D$8&"|"&$D$9&"|"&7, $J$105:$J$282, 0)), "")) | W33: =IF(B33="","", IF(B33="0101", IF($D$22="NO", "OMITTED DEDUCTION (DAR Item 2.5): 0.40 Bhishti @ Rs 617 = Rs 246.80 direct. Compounded total = Rs 326.94/10 cum -> Rate deduction Rs 33.00/cum.", "ACTIVE: Compaction watering included in standard item scope."), IF(OR(B33="0003", B33="0011", B33="0113"), IF($D$23="NO", "OMITTED DEDUCTION (DAR Item 2.4): 0.008 Roller + Chowkidar + Sundries = Rs 32.10 direct. Compounded total = Rs 42.95/10 cum -> Rate deduction Rs 4.30/cum.", "ACTIVE: Power rolling included in standard item scope."), "MANDATORY: Not subject to omission or separate deduction.")))
A34: 8 | B34: =IFERROR(INDEX($F$105:$F$282, MATCH($D$6&"|"&$D$7&"|"&$D$8&"|"&$D$9&"|"&8, $J$105:$J$282, 0)), "") | C34: =IF(B34="","", IFERROR(INDEX(Rates_Master!$C:$C, MATCH(B34, Rates_Master!$A:$A, 0)), "Custom Resource")) | D34: =IF(B34="","", IFERROR(INDEX(Rates_Master!$B:$B, MATCH(B34, Rates_Master!$A:$A, 0)), "Labour")) | E34: =IF(B34="","", IFERROR(INDEX(Rates_Master!$D:$D, MATCH(B34, Rates_Master!$A:$A, 0)), "day")) | F34: =IF(B34="","", R34) | G34: =IF(B34="","", IFERROR(INDEX(Rates_Master!$E:$E, MATCH(B34, Rates_Master!$A:$A, 0)), 0)) | H34: =IF(OR(B34="", F34=""), 0, ROUND(F34 * G34, 2)) -> 0 | I34: =IF(B34="","", IF(ISNUMBER(SEARCH("2.10", B34)), "A", "W")) | J34: =IF(H$41>0, ROUND(H34 / H$41 * 100, 1), 0) -> 0 | K34: =IFERROR(INDEX($G$105:$G$282, MATCH($D$6&"|"&$D$7&"|"&$D$8&"|"&$D$9&"|"&8, $J$105:$J$282, 0)), "") | L34: =IF(AND(ISNUMBER(F34), F34>0, D$10>0), ROUND(F34 * 8 / D$10, 4), "") | M34: =IF(AND(ISNUMBER(F34), F34>0, D$10>0), ROUND(D$10 / (F34 * 8), 2), "") | N34: =IF(B34="","", "CPWD Standard Earthwork Production Resource") | O34: =IF(B34="","", V34) | P34: =IF(B34="","", IF(AND(ISNUMBER(K34), K34>0), ROUND(D$10/K34, 5), IFERROR(INDEX($K$105:$K$282, MATCH($D$6&"|"&$D$7&"|"&$D$8&"|"&$D$9&"|"&8, $J$105:$J$282, 0)), 0))) | Q34: =IF(B34="","", IFERROR(VLOOKUP(B34, $P$19:$S$22, 4, FALSE), 1)) | R34: =IF(B34="","", ROUND(P34 * Q34, 5)) | S34: =IF(B34="","", IF(B34="0101", "Lever 4: Compaction Watering ($D$22 = " & $D$22 & ")", IF(OR(B34="0003", B34="0011", B34="0113"), "Lever 5: Power Rolling ($D$23 = " & $D$23 & ")", "Core Scope Baseline (Mandatory Execution)"))) | T34: =IF(B34="","", "Batch Q=" & TEXT(D$10, "0.00") & " " & $D$11 & " | Norm K=" & TEXT(K34, "0.00") & " | Factor=" & TEXT(Q34, "0.00") & " | Qty F=" & TEXT(F34, "0.000") & " " & E34 & " | Rate G=Rs " & TEXT(G34, "0.00") & " | Amt H=Rs " & TEXT(H34, "0.00")) | U34: =IF(B34="","", IFERROR(INDEX($H$105:$H$282, MATCH($D$6&"|"&$D$7&"|"&$D$8&"|"&$D$9&"|"&8, $J$105:$J$282, 0)), "")) | V34: =IF(B34="","", IFERROR(INDEX($I$105:$I$282, MATCH($D$6&"|"&$D$7&"|"&$D$8&"|"&$D$9&"|"&8, $J$105:$J$282, 0)), "")) | W34: =IF(B34="","", IF(B34="0101", IF($D$22="NO", "OMITTED DEDUCTION (DAR Item 2.5): 0.40 Bhishti @ Rs 617 = Rs 246.80 direct. Compounded total = Rs 326.94/10 cum -> Rate deduction Rs 33.00/cum.", "ACTIVE: Compaction watering included in standard item scope."), IF(OR(B34="0003", B34="0011", B34="0113"), IF($D$23="NO", "OMITTED DEDUCTION (DAR Item 2.4): 0.008 Roller + Chowkidar + Sundries = Rs 32.10 direct. Compounded total = Rs 42.95/10 cum -> Rate deduction Rs 4.30/cum.", "ACTIVE: Power rolling included in standard item scope."), "MANDATORY: Not subject to omission or separate deduction.")))
A35: 9 | B35: =IFERROR(INDEX($F$105:$F$282, MATCH($D$6&"|"&$D$7&"|"&$D$8&"|"&$D$9&"|"&9, $J$105:$J$282, 0)), "") | C35: =IF(B35="","", IFERROR(INDEX(Rates_Master!$C:$C, MATCH(B35, Rates_Master!$A:$A, 0)), "Custom Resource")) | D35: =IF(B35="","", IFERROR(INDEX(Rates_Master!$B:$B, MATCH(B35, Rates_Master!$A:$A, 0)), "Labour")) | E35: =IF(B35="","", IFERROR(INDEX(Rates_Master!$D:$D, MATCH(B35, Rates_Master!$A:$A, 0)), "day")) | F35: =IF(B35="","", R35) | G35: =IF(B35="","", IFERROR(INDEX(Rates_Master!$E:$E, MATCH(B35, Rates_Master!$A:$A, 0)), 0)) | H35: =IF(OR(B35="", F35=""), 0, ROUND(F35 * G35, 2)) -> 0 | I35: =IF(B35="","", IF(ISNUMBER(SEARCH("2.10", B35)), "A", "W")) | J35: =IF(H$41>0, ROUND(H35 / H$41 * 100, 1), 0) -> 0 | K35: =IFERROR(INDEX($G$105:$G$282, MATCH($D$6&"|"&$D$7&"|"&$D$8&"|"&$D$9&"|"&9, $J$105:$J$282, 0)), "") | L35: =IF(AND(ISNUMBER(F35), F35>0, D$10>0), ROUND(F35 * 8 / D$10, 4), "") | M35: =IF(AND(ISNUMBER(F35), F35>0, D$10>0), ROUND(D$10 / (F35 * 8), 2), "") | N35: =IF(B35="","", "CPWD Standard Earthwork Production Resource") | O35: =IF(B35="","", V35) | P35: =IF(B35="","", IF(AND(ISNUMBER(K35), K35>0), ROUND(D$10/K35, 5), IFERROR(INDEX($K$105:$K$282, MATCH($D$6&"|"&$D$7&"|"&$D$8&"|"&$D$9&"|"&9, $J$105:$J$282, 0)), 0))) | Q35: =IF(B35="","", IFERROR(VLOOKUP(B35, $P$19:$S$22, 4, FALSE), 1)) | R35: =IF(B35="","", ROUND(P35 * Q35, 5)) | S35: =IF(B35="","", IF(B35="0101", "Lever 4: Compaction Watering ($D$22 = " & $D$22 & ")", IF(OR(B35="0003", B35="0011", B35="0113"), "Lever 5: Power Rolling ($D$23 = " & $D$23 & ")", "Core Scope Baseline (Mandatory Execution)"))) | T35: =IF(B35="","", "Batch Q=" & TEXT(D$10, "0.00") & " " & $D$11 & " | Norm K=" & TEXT(K35, "0.00") & " | Factor=" & TEXT(Q35, "0.00") & " | Qty F=" & TEXT(F35, "0.000") & " " & E35 & " | Rate G=Rs " & TEXT(G35, "0.00") & " | Amt H=Rs " & TEXT(H35, "0.00")) | U35: =IF(B35="","", IFERROR(INDEX($H$105:$H$282, MATCH($D$6&"|"&$D$7&"|"&$D$8&"|"&$D$9&"|"&9, $J$105:$J$282, 0)), "")) | V35: =IF(B35="","", IFERROR(INDEX($I$105:$I$282, MATCH($D$6&"|"&$D$7&"|"&$D$8&"|"&$D$9&"|"&9, $J$105:$J$282, 0)), "")) | W35: =IF(B35="","", IF(B35="0101", IF($D$22="NO", "OMITTED DEDUCTION (DAR Item 2.5): 0.40 Bhishti @ Rs 617 = Rs 246.80 direct. Compounded total = Rs 326.94/10 cum -> Rate deduction Rs 33.00/cum.", "ACTIVE: Compaction watering included in standard item scope."), IF(OR(B35="0003", B35="0011", B35="0113"), IF($D$23="NO", "OMITTED DEDUCTION (DAR Item 2.4): 0.008 Roller + Chowkidar + Sundries = Rs 32.10 direct. Compounded total = Rs 42.95/10 cum -> Rate deduction Rs 4.30/cum.", "ACTIVE: Power rolling included in standard item scope."), "MANDATORY: Not subject to omission or separate deduction.")))
A36: 10 | B36: =IFERROR(INDEX($F$105:$F$282, MATCH($D$6&"|"&$D$7&"|"&$D$8&"|"&$D$9&"|"&10, $J$105:$J$282, 0)), "") | C36: =IF(B36="","", IFERROR(INDEX(Rates_Master!$C:$C, MATCH(B36, Rates_Master!$A:$A, 0)), "Custom Resource")) | D36: =IF(B36="","", IFERROR(INDEX(Rates_Master!$B:$B, MATCH(B36, Rates_Master!$A:$A, 0)), "Labour")) | E36: =IF(B36="","", IFERROR(INDEX(Rates_Master!$D:$D, MATCH(B36, Rates_Master!$A:$A, 0)), "day")) | F36: =IF(B36="","", R36) | G36: =IF(B36="","", IFERROR(INDEX(Rates_Master!$E:$E, MATCH(B36, Rates_Master!$A:$A, 0)), 0)) | H36: =IF(OR(B36="", F36=""), 0, ROUND(F36 * G36, 2)) -> 0 | I36: =IF(B36="","", IF(ISNUMBER(SEARCH("2.10", B36)), "A", "W")) | J36: =IF(H$41>0, ROUND(H36 / H$41 * 100, 1), 0) -> 0 | K36: =IFERROR(INDEX($G$105:$G$282, MATCH($D$6&"|"&$D$7&"|"&$D$8&"|"&$D$9&"|"&10, $J$105:$J$282, 0)), "") | L36: =IF(AND(ISNUMBER(F36), F36>0, D$10>0), ROUND(F36 * 8 / D$10, 4), "") | M36: =IF(AND(ISNUMBER(F36), F36>0, D$10>0), ROUND(D$10 / (F36 * 8), 2), "") | N36: =IF(B36="","", "CPWD Standard Earthwork Production Resource") | O36: =IF(B36="","", V36) | P36: =IF(B36="","", IF(AND(ISNUMBER(K36), K36>0), ROUND(D$10/K36, 5), IFERROR(INDEX($K$105:$K$282, MATCH($D$6&"|"&$D$7&"|"&$D$8&"|"&$D$9&"|"&10, $J$105:$J$282, 0)), 0))) | Q36: =IF(B36="","", IFERROR(VLOOKUP(B36, $P$19:$S$22, 4, FALSE), 1)) | R36: =IF(B36="","", ROUND(P36 * Q36, 5)) | S36: =IF(B36="","", IF(B36="0101", "Lever 4: Compaction Watering ($D$22 = " & $D$22 & ")", IF(OR(B36="0003", B36="0011", B36="0113"), "Lever 5: Power Rolling ($D$23 = " & $D$23 & ")", "Core Scope Baseline (Mandatory Execution)"))) | T36: =IF(B36="","", "Batch Q=" & TEXT(D$10, "0.00") & " " & $D$11 & " | Norm K=" & TEXT(K36, "0.00") & " | Factor=" & TEXT(Q36, "0.00") & " | Qty F=" & TEXT(F36, "0.000") & " " & E36 & " | Rate G=Rs " & TEXT(G36, "0.00") & " | Amt H=Rs " & TEXT(H36, "0.00")) | U36: =IF(B36="","", IFERROR(INDEX($H$105:$H$282, MATCH($D$6&"|"&$D$7&"|"&$D$8&"|"&$D$9&"|"&10, $J$105:$J$282, 0)), "")) | V36: =IF(B36="","", IFERROR(INDEX($I$105:$I$282, MATCH($D$6&"|"&$D$7&"|"&$D$8&"|"&$D$9&"|"&10, $J$105:$J$282, 0)), "")) | W36: =IF(B36="","", IF(B36="0101", IF($D$22="NO", "OMITTED DEDUCTION (DAR Item 2.5): 0.40 Bhishti @ Rs 617 = Rs 246.80 direct. Compounded total = Rs 326.94/10 cum -> Rate deduction Rs 33.00/cum.", "ACTIVE: Compaction watering included in standard item scope."), IF(OR(B36="0003", B36="0011", B36="0113"), IF($D$23="NO", "OMITTED DEDUCTION (DAR Item 2.4): 0.008 Roller + Chowkidar + Sundries = Rs 32.10 direct. Compounded total = Rs 42.95/10 cum -> Rate deduction Rs 4.30/cum.", "ACTIVE: Power rolling included in standard item scope."), "MANDATORY: Not subject to omission or separate deduction.")))
A37: 11 | B37: =IFERROR(INDEX($F$105:$F$282, MATCH($D$6&"|"&$D$7&"|"&$D$8&"|"&$D$9&"|"&11, $J$105:$J$282, 0)), "") | C37: =IF(B37="","", IFERROR(INDEX(Rates_Master!$C:$C, MATCH(B37, Rates_Master!$A:$A, 0)), "Custom Resource")) | D37: =IF(B37="","", IFERROR(INDEX(Rates_Master!$B:$B, MATCH(B37, Rates_Master!$A:$A, 0)), "Labour")) | E37: =IF(B37="","", IFERROR(INDEX(Rates_Master!$D:$D, MATCH(B37, Rates_Master!$A:$A, 0)), "day")) | F37: =IF(B37="","", R37) | G37: =IF(B37="","", IFERROR(INDEX(Rates_Master!$E:$E, MATCH(B37, Rates_Master!$A:$A, 0)), 0)) | H37: =IF(OR(B37="", F37=""), 0, ROUND(F37 * G37, 2)) -> 0 | I37: =IF(B37="","", IF(ISNUMBER(SEARCH("2.10", B37)), "A", "W")) | J37: =IF(H$41>0, ROUND(H37 / H$41 * 100, 1), 0) -> 0 | K37: =IFERROR(INDEX($G$105:$G$282, MATCH($D$6&"|"&$D$7&"|"&$D$8&"|"&$D$9&"|"&11, $J$105:$J$282, 0)), "") | L37: =IF(AND(ISNUMBER(F37), F37>0, D$10>0), ROUND(F37 * 8 / D$10, 4), "") | M37: =IF(AND(ISNUMBER(F37), F37>0, D$10>0), ROUND(D$10 / (F37 * 8), 2), "") | N37: =IF(B37="","", "CPWD Standard Earthwork Production Resource") | O37: =IF(B37="","", V37) | P37: =IF(B37="","", IF(AND(ISNUMBER(K37), K37>0), ROUND(D$10/K37, 5), IFERROR(INDEX($K$105:$K$282, MATCH($D$6&"|"&$D$7&"|"&$D$8&"|"&$D$9&"|"&11, $J$105:$J$282, 0)), 0))) | Q37: =IF(B37="","", IFERROR(VLOOKUP(B37, $P$19:$S$22, 4, FALSE), 1)) | R37: =IF(B37="","", ROUND(P37 * Q37, 5)) | S37: =IF(B37="","", IF(B37="0101", "Lever 4: Compaction Watering ($D$22 = " & $D$22 & ")", IF(OR(B37="0003", B37="0011", B37="0113"), "Lever 5: Power Rolling ($D$23 = " & $D$23 & ")", "Core Scope Baseline (Mandatory Execution)"))) | T37: =IF(B37="","", "Batch Q=" & TEXT(D$10, "0.00") & " " & $D$11 & " | Norm K=" & TEXT(K37, "0.00") & " | Factor=" & TEXT(Q37, "0.00") & " | Qty F=" & TEXT(F37, "0.000") & " " & E37 & " | Rate G=Rs " & TEXT(G37, "0.00") & " | Amt H=Rs " & TEXT(H37, "0.00")) | U37: =IF(B37="","", IFERROR(INDEX($H$105:$H$282, MATCH($D$6&"|"&$D$7&"|"&$D$8&"|"&$D$9&"|"&11, $J$105:$J$282, 0)), "")) | V37: =IF(B37="","", IFERROR(INDEX($I$105:$I$282, MATCH($D$6&"|"&$D$7&"|"&$D$8&"|"&$D$9&"|"&11, $J$105:$J$282, 0)), "")) | W37: =IF(B37="","", IF(B37="0101", IF($D$22="NO", "OMITTED DEDUCTION (DAR Item 2.5): 0.40 Bhishti @ Rs 617 = Rs 246.80 direct. Compounded total = Rs 326.94/10 cum -> Rate deduction Rs 33.00/cum.", "ACTIVE: Compaction watering included in standard item scope."), IF(OR(B37="0003", B37="0011", B37="0113"), IF($D$23="NO", "OMITTED DEDUCTION (DAR Item 2.4): 0.008 Roller + Chowkidar + Sundries = Rs 32.10 direct. Compounded total = Rs 42.95/10 cum -> Rate deduction Rs 4.30/cum.", "ACTIVE: Power rolling included in standard item scope."), "MANDATORY: Not subject to omission or separate deduction.")))
A38: 12 | B38: =IFERROR(INDEX($F$105:$F$282, MATCH($D$6&"|"&$D$7&"|"&$D$8&"|"&$D$9&"|"&12, $J$105:$J$282, 0)), "") | C38: =IF(B38="","", IFERROR(INDEX(Rates_Master!$C:$C, MATCH(B38, Rates_Master!$A:$A, 0)), "Custom Resource")) | D38: =IF(B38="","", IFERROR(INDEX(Rates_Master!$B:$B, MATCH(B38, Rates_Master!$A:$A, 0)), "Labour")) | E38: =IF(B38="","", IFERROR(INDEX(Rates_Master!$D:$D, MATCH(B38, Rates_Master!$A:$A, 0)), "day")) | F38: =IF(B38="","", R38) | G38: =IF(B38="","", IFERROR(INDEX(Rates_Master!$E:$E, MATCH(B38, Rates_Master!$A:$A, 0)), 0)) | H38: =IF(OR(B38="", F38=""), 0, ROUND(F38 * G38, 2)) -> 0 | I38: =IF(B38="","", IF(ISNUMBER(SEARCH("2.10", B38)), "A", "W")) | J38: =IF(H$41>0, ROUND(H38 / H$41 * 100, 1), 0) -> 0 | K38: =IFERROR(INDEX($G$105:$G$282, MATCH($D$6&"|"&$D$7&"|"&$D$8&"|"&$D$9&"|"&12, $J$105:$J$282, 0)), "") | L38: =IF(AND(ISNUMBER(F38), F38>0, D$10>0), ROUND(F38 * 8 / D$10, 4), "") | M38: =IF(AND(ISNUMBER(F38), F38>0, D$10>0), ROUND(D$10 / (F38 * 8), 2), "") | N38: =IF(B38="","", "CPWD Standard Earthwork Production Resource") | O38: =IF(B38="","", V38) | P38: =IF(B38="","", IF(AND(ISNUMBER(K38), K38>0), ROUND(D$10/K38, 5), IFERROR(INDEX($K$105:$K$282, MATCH($D$6&"|"&$D$7&"|"&$D$8&"|"&$D$9&"|"&12, $J$105:$J$282, 0)), 0))) | Q38: =IF(B38="","", IFERROR(VLOOKUP(B38, $P$19:$S$22, 4, FALSE), 1)) | R38: =IF(B38="","", ROUND(P38 * Q38, 5)) | S38: =IF(B38="","", IF(B38="0101", "Lever 4: Compaction Watering ($D$22 = " & $D$22 & ")", IF(OR(B38="0003", B38="0011", B38="0113"), "Lever 5: Power Rolling ($D$23 = " & $D$23 & ")", "Core Scope Baseline (Mandatory Execution)"))) | T38: =IF(B38="","", "Batch Q=" & TEXT(D$10, "0.00") & " " & $D$11 & " | Norm K=" & TEXT(K38, "0.00") & " | Factor=" & TEXT(Q38, "0.00") & " | Qty F=" & TEXT(F38, "0.000") & " " & E38 & " | Rate G=Rs " & TEXT(G38, "0.00") & " | Amt H=Rs " & TEXT(H38, "0.00")) | U38: =IF(B38="","", IFERROR(INDEX($H$105:$H$282, MATCH($D$6&"|"&$D$7&"|"&$D$8&"|"&$D$9&"|"&12, $J$105:$J$282, 0)), "")) | V38: =IF(B38="","", IFERROR(INDEX($I$105:$I$282, MATCH($D$6&"|"&$D$7&"|"&$D$8&"|"&$D$9&"|"&12, $J$105:$J$282, 0)), "")) | W38: =IF(B38="","", IF(B38="0101", IF($D$22="NO", "OMITTED DEDUCTION (DAR Item 2.5): 0.40 Bhishti @ Rs 617 = Rs 246.80 direct. Compounded total = Rs 326.94/10 cum -> Rate deduction Rs 33.00/cum.", "ACTIVE: Compaction watering included in standard item scope."), IF(OR(B38="0003", B38="0011", B38="0113"), IF($D$23="NO", "OMITTED DEDUCTION (DAR Item 2.4): 0.008 Roller + Chowkidar + Sundries = Rs 32.10 direct. Compounded total = Rs 42.95/10 cum -> Rate deduction Rs 4.30/cum.", "ACTIVE: Power rolling included in standard item scope."), "MANDATORY: Not subject to omission or separate deduction.")))
A39: 13 | B39: =IFERROR(INDEX($F$105:$F$282, MATCH($D$6&"|"&$D$7&"|"&$D$8&"|"&$D$9&"|"&13, $J$105:$J$282, 0)), "") | C39: =IF(B39="","", IFERROR(INDEX(Rates_Master!$C:$C, MATCH(B39, Rates_Master!$A:$A, 0)), "Custom Resource")) | D39: =IF(B39="","", IFERROR(INDEX(Rates_Master!$B:$B, MATCH(B39, Rates_Master!$A:$A, 0)), "Labour")) | E39: =IF(B39="","", IFERROR(INDEX(Rates_Master!$D:$D, MATCH(B39, Rates_Master!$A:$A, 0)), "day")) | F39: =IF(B39="","", R39) | G39: =IF(B39="","", IFERROR(INDEX(Rates_Master!$E:$E, MATCH(B39, Rates_Master!$A:$A, 0)), 0)) | H39: =IF(OR(B39="", F39=""), 0, ROUND(F39 * G39, 2)) -> 0 | I39: =IF(B39="","", IF(ISNUMBER(SEARCH("2.10", B39)), "A", "W")) | J39: =IF(H$41>0, ROUND(H39 / H$41 * 100, 1), 0) -> 0 | K39: =IFERROR(INDEX($G$105:$G$282, MATCH($D$6&"|"&$D$7&"|"&$D$8&"|"&$D$9&"|"&13, $J$105:$J$282, 0)), "") | L39: =IF(AND(ISNUMBER(F39), F39>0, D$10>0), ROUND(F39 * 8 / D$10, 4), "") | M39: =IF(AND(ISNUMBER(F39), F39>0, D$10>0), ROUND(D$10 / (F39 * 8), 2), "") | N39: =IF(B39="","", "CPWD Standard Earthwork Production Resource") | O39: =IF(B39="","", V39) | P39: =IF(B39="","", IF(AND(ISNUMBER(K39), K39>0), ROUND(D$10/K39, 5), IFERROR(INDEX($K$105:$K$282, MATCH($D$6&"|"&$D$7&"|"&$D$8&"|"&$D$9&"|"&13, $J$105:$J$282, 0)), 0))) | Q39: =IF(B39="","", IFERROR(VLOOKUP(B39, $P$19:$S$22, 4, FALSE), 1)) | R39: =IF(B39="","", ROUND(P39 * Q39, 5)) | S39: =IF(B39="","", IF(B39="0101", "Lever 4: Compaction Watering ($D$22 = " & $D$22 & ")", IF(OR(B39="0003", B39="0011", B39="0113"), "Lever 5: Power Rolling ($D$23 = " & $D$23 & ")", "Core Scope Baseline (Mandatory Execution)"))) | T39: =IF(B39="","", "Batch Q=" & TEXT(D$10, "0.00") & " " & $D$11 & " | Norm K=" & TEXT(K39, "0.00") & " | Factor=" & TEXT(Q39, "0.00") & " | Qty F=" & TEXT(F39, "0.000") & " " & E39 & " | Rate G=Rs " & TEXT(G39, "0.00") & " | Amt H=Rs " & TEXT(H39, "0.00")) | U39: =IF(B39="","", IFERROR(INDEX($H$105:$H$282, MATCH($D$6&"|"&$D$7&"|"&$D$8&"|"&$D$9&"|"&13, $J$105:$J$282, 0)), "")) | V39: =IF(B39="","", IFERROR(INDEX($I$105:$I$282, MATCH($D$6&"|"&$D$7&"|"&$D$8&"|"&$D$9&"|"&13, $J$105:$J$282, 0)), "")) | W39: =IF(B39="","", IF(B39="0101", IF($D$22="NO", "OMITTED DEDUCTION (DAR Item 2.5): 0.40 Bhishti @ Rs 617 = Rs 246.80 direct. Compounded total = Rs 326.94/10 cum -> Rate deduction Rs 33.00/cum.", "ACTIVE: Compaction watering included in standard item scope."), IF(OR(B39="0003", B39="0011", B39="0113"), IF($D$23="NO", "OMITTED DEDUCTION (DAR Item 2.4): 0.008 Roller + Chowkidar + Sundries = Rs 32.10 direct. Compounded total = Rs 42.95/10 cum -> Rate deduction Rs 4.30/cum.", "ACTIVE: Power rolling included in standard item scope."), "MANDATORY: Not subject to omission or separate deduction.")))
A40: 14 | B40: =IFERROR(INDEX($F$105:$F$282, MATCH($D$6&"|"&$D$7&"|"&$D$8&"|"&$D$9&"|"&14, $J$105:$J$282, 0)), "") | C40: =IF(B40="","", IFERROR(INDEX(Rates_Master!$C:$C, MATCH(B40, Rates_Master!$A:$A, 0)), "Custom Resource")) | D40: =IF(B40="","", IFERROR(INDEX(Rates_Master!$B:$B, MATCH(B40, Rates_Master!$A:$A, 0)), "Labour")) | E40: =IF(B40="","", IFERROR(INDEX(Rates_Master!$D:$D, MATCH(B40, Rates_Master!$A:$A, 0)), "day")) | F40: =IF(B40="","", R40) | G40: =IF(B40="","", IFERROR(INDEX(Rates_Master!$E:$E, MATCH(B40, Rates_Master!$A:$A, 0)), 0)) | H40: =IF(OR(B40="", F40=""), 0, ROUND(F40 * G40, 2)) -> 0 | I40: =IF(B40="","", IF(ISNUMBER(SEARCH("2.10", B40)), "A", "W")) | J40: =IF(H$41>0, ROUND(H40 / H$41 * 100, 1), 0) -> 0 | K40: =IFERROR(INDEX($G$105:$G$282, MATCH($D$6&"|"&$D$7&"|"&$D$8&"|"&$D$9&"|"&14, $J$105:$J$282, 0)), "") | L40: =IF(AND(ISNUMBER(F40), F40>0, D$10>0), ROUND(F40 * 8 / D$10, 4), "") | M40: =IF(AND(ISNUMBER(F40), F40>0, D$10>0), ROUND(D$10 / (F40 * 8), 2), "") | N40: =IF(B40="","", "CPWD Standard Earthwork Production Resource") | O40: =IF(B40="","", V40) | P40: =IF(B40="","", IF(AND(ISNUMBER(K40), K40>0), ROUND(D$10/K40, 5), IFERROR(INDEX($K$105:$K$282, MATCH($D$6&"|"&$D$7&"|"&$D$8&"|"&$D$9&"|"&14, $J$105:$J$282, 0)), 0))) | Q40: =IF(B40="","", IFERROR(VLOOKUP(B40, $P$19:$S$22, 4, FALSE), 1)) | R40: =IF(B40="","", ROUND(P40 * Q40, 5)) | S40: =IF(B40="","", IF(B40="0101", "Lever 4: Compaction Watering ($D$22 = " & $D$22 & ")", IF(OR(B40="0003", B40="0011", B40="0113"), "Lever 5: Power Rolling ($D$23 = " & $D$23 & ")", "Core Scope Baseline (Mandatory Execution)"))) | T40: =IF(B40="","", "Batch Q=" & TEXT(D$10, "0.00") & " " & $D$11 & " | Norm K=" & TEXT(K40, "0.00") & " | Factor=" & TEXT(Q40, "0.00") & " | Qty F=" & TEXT(F40, "0.000") & " " & E40 & " | Rate G=Rs " & TEXT(G40, "0.00") & " | Amt H=Rs " & TEXT(H40, "0.00")) | U40: =IF(B40="","", IFERROR(INDEX($H$105:$H$282, MATCH($D$6&"|"&$D$7&"|"&$D$8&"|"&$D$9&"|"&14, $J$105:$J$282, 0)), "")) | V40: =IF(B40="","", IFERROR(INDEX($I$105:$I$282, MATCH($D$6&"|"&$D$7&"|"&$D$8&"|"&$D$9&"|"&14, $J$105:$J$282, 0)), "")) | W40: =IF(B40="","", IF(B40="0101", IF($D$22="NO", "OMITTED DEDUCTION (DAR Item 2.5): 0.40 Bhishti @ Rs 617 = Rs 246.80 direct. Compounded total = Rs 326.94/10 cum -> Rate deduction Rs 33.00/cum.", "ACTIVE: Compaction watering included in standard item scope."), IF(OR(B40="0003", B40="0011", B40="0113"), IF($D$23="NO", "OMITTED DEDUCTION (DAR Item 2.4): 0.008 Roller + Chowkidar + Sundries = Rs 32.10 direct. Compounded total = Rs 42.95/10 cum -> Rate deduction Rs 4.30/cum.", "ACTIVE: Power rolling included in standard item scope."), "MANDATORY: Not subject to omission or separate deduction.")))
A41: Direct Production Cost W = Σ Amount (all active resource lines): | H41: =ROUND(SUM(H27:H40), 2) -> 6919.2 | I41: W | J41: Base for statutory markup calculations before exclusion of pre-marked reference items.
A42: A-tagged Total (pre-marked composite reference items excluded from markups): | H42: =ROUND(SUMIF(I27:I40, "A", H27:H40), 2) -> 0 | I42: A | J42: Uses robust SUMIF to guarantee error-free evaluation even with empty slots.
A44: 3. STATUTORY MARKUPS & FINAL RATE DERIVATION (CPWD DAR Standard Compounded Markup Chain)
A45: Step | B45: Component / Markup Description | C45: Apply? | D45: Basis Applied | E45: Base Amount (₹) | F45: Factor / % | G45: Added (₹) | H45: Running Total (₹) | I45: Cell Role | J45: CPWD Statutory Guidance Rule & Practical Field Note
A46: W | B46: Direct Production Cost W (all resources) | C46: — | D46: Direct Sum | E46: =H41 -> 6919.2 | F46: — | G46: =0 -> 0 | H46: =H41 -> 6919.2 | I46: DERIVED | J46: Sum of all direct labour, machinery and sundries from Section 2.
A47: X1 | B47: Add: Water Charges (1% on W-A) | C47: YES | D47: On (W - A) | E47: =H46 - H42 -> 6919.2 | F47: =Factor_Water -> 0.01 | G47: =IF(C47="YES", ROUND(E47 * F47, 2), 0) -> 69.19 | H47: =H46 + G47 -> 6988.39 | I47: INPUT | J47: CPWD standard: 1% for site compaction watering, trench dampening and dust control. Live-linked to Factor_Water.
A48: X | B48: Subtotal X (W + Water Charges) | C48: — | D48: W + Water | E48: =H47 -> 6988.39 | F48: — | G48: =0 -> 0 | H48: =H47 -> 6988.39 | I48: DERIVED | J48: Compounded base passed to Works Contract GST calculation.
A49: Y1 | B49: Add: GST on Works Contract (14.05% on X-A) | C49: YES | D49: On (X - A) | E49: =H48 - H42 -> 6988.39 | F49: =Factor_GST -> 0.1405 | G49: =IF(C49="YES", ROUND(E49 * F49, 2), 0) -> 981.87 | H49: =H48 + G49 -> 7970.26 | I49: INPUT | J49: CPWD DAR statutory works contract tax factor (0.1405). Live-linked to Factor_GST on Global_Factors.
A50: Y | B50: Subtotal Y (X + GST) | C50: — | D50: X + GST | E50: =H49 -> 7970.26 | F50: — | G50: =0 -> 0 | H50: =H49 -> 7970.26 | I50: DERIVED | J50: Compounded base passed to Contractor Profit & Overheads calculation.
A51: Z1 | B51: Add: Contractor Profit & Overheads (15% CPOH on Y-A) | C51: YES | D51: On (Y - A) | E51: =H50 - H42 -> 7970.26 | F51: =Factor_CPOH -> 0.15 | G51: =IF(C51="YES", ROUND(E51 * F51, 2), 0) -> 1195.54 | H51: =H50 + G51 -> 9165.8 | I51: INPUT | J51: Standard 15% allowance for contractor overheads, plant depreciation and profit. Live-linked to Factor_CPOH.
A52: Z | B52: Subtotal Z (Y + CPOH) | C52: — | D52: Y + CPOH | E52: =H51 -> 9165.8 | F52: — | G52: =0 -> 0 | H52: =H51 -> 9165.8 | I52: DERIVED | J52: Compounded base passed to Building and Other Construction Workers Welfare Cess calculation.
A53: Z2 | B53: Add: Building and Other Construction Workers Welfare Cess (1% on Z) | C53: YES | D53: On Z | E53: =H52 -> 9165.8 | F53: =Factor_Cess -> 0.01 | G53: =IF(C53="YES", ROUND(E53 * F53, 2), 0) -> 91.66 | H53: =H52 + G53 -> 9257.46 | I53: INPUT | J53: Statutory 1% BOCW Welfare Cess levied on overall cost including CPOH. Live-linked to Factor_Cess.
A54: Cost | B54: ="Cost for " & D10 & " " & D11 -> Cost for 100 sqm | C54: — | D54: Standard Output Batch | E54: =H53 -> 9257.46 | F54: — | G54: =0 -> 0 | H54: =H53 -> 9257.46 | I54: RESULT | J54: Fully compounded cost for the standard DAR batch quantity before unit-rate derivation.
A55: Rate | B55: ="Rate per " & D11 & " (unrounded)" -> Rate per sqm (unrounded) | C55: — | D55: =D11 -> sqm | E55: =H54 / D10 -> 92.5746 | F55: — | G55: =0 -> 0 | H55: =H54 / D10 -> 92.5746 | I55: DERIVED | J55: Exact rate per unit output (Cost / Batch Qty) carried into statutory rounding.
A56: SAY | B56: ="FINAL ANALYSED SAY RATE (Rs per " & D11 & ")" -> FINAL ANALYSED SAY RATE (Rs per sqm) | C56: — | D56: MROUND 0.05 | E56: =H55 -> 92.5746 | F56: — | G56: =0 -> 0 | H56: =MROUND(H55, 0.05) -> 92.55 | I56: SAY | J56: Final published billing rate rounded to the nearest 5 paise in accordance with CPWD DAR Section 0 conventions.
A57: REF | B57: ="Published Benchmark Say Rate (Rs per " & D11 & "):" -> Published Benchmark Say Rate (Rs per sqm): | C57: — | D57: Benchmark | E57: =D14 -> 92.55 | F57: — | G57: =0 -> 0 | H57: =D14 -> 92.55 | I57: LOOKUP | J57: Official CPWD DAR 2019 Volume 1 published rate for verification.
A58: DIFF | B58: Audit Variance (Analysed Say - Published Say): | C58: — | D58: Say - Ref | E58: =H56 - H57 -> 0 | F58: — | G58: =0 -> 0 | H58: =ROUND(H56 - H57, 2) -> 0 | I58: RESULT | J58: Discrepancy audit against published benchmark. Target = ₹ 0.00.
A60: 4. FIRST-PRINCIPLES LABOUR & MACHINERY PRODUCTIVITY BENCHMARK MATRIX (8-Hour Working Shift Basis)
A61: FIRST-PRINCIPLES DERIVATION MECHANICS: Shows how physical labour and equipment operations in an 8-hour shift translate into CPWD norm factors. Standard Gang (G) × Task Duration (H) = Total Man-Hours (MH) → Day Coeff (D) = MH / 8.00 h → Daily Output (P) = Batch Q / D → Specific Effort (SE) = MH / Q → Hourly Pace = P / 8.00. Every calculation cell is a live Excel formula. No CPWD code numbering; Resource Code is placed in its own dedicated column (Col C).
A62: Civil Work Scope / Operation | B62: Operation / Sub-Task | C62: Resource Code | D62: Resource Trade / Fleet Role | E62: Batch Qty (Q) | F62: Unit | G62: Gang Size (G) | H62: Duration (H hrs) | I62: Total Man-Hours (MH) | J62: Shift (h) | K62: Day Coeff (D) | L62: Daily Output (P) | M62: Unit Effort (SE) | N62: Hourly Pace | O62: Engineering Task Breakdown & First-Principles 8-Hour Logic
A63: Surface excavation <= 30cm depth (100 sqm) | B63: Pickaxe & phowrah loosening hard crust | C63: 0114 | D63: Beldar (Semi-Skilled / Operational Earthwork) | E63: 100 | F63: sqm | G63: 4 | H63: 13.6 | I63: =ROUND(G63 * H63, 3) -> 54.4 | J63: 8 | K63: =ROUND(I63 / J63, 4) -> 6.8 | L63: =IFERROR(ROUND(E63 / K63, 2), "") -> 14.71 | M63: =IFERROR(ROUND(I63 / E63, 4), "") -> 0.544 | N63: =IFERROR(ROUND(L63 / J63, 2), "") -> 1.84 | O63: Pickaxe loosening of hard dry soil crust up to 30 cm depth. 1 Beldar loosens 14.71 sqm per 8-hr shift (1.84 sqm/hr). Total 54.40 man-hrs.
A64: Surface excavation <= 30cm depth (100 sqm) | B64: Basket loading, haulage & 50m disposal | C64: 0115 | D64: Coolie (Unskilled / Haulage & Spoil Handling) | E64: 100 | F64: sqm | G64: 4 | H64: 11.2 | I64: =ROUND(G64 * H64, 3) -> 44.8 | J64: 8 | K64: =ROUND(I64 / J64, 4) -> 5.6 | L64: =IFERROR(ROUND(E64 / K64, 2), "") -> 17.86 | M64: =IFERROR(ROUND(I64 / E64, 4), "") -> 0.448 | N64: =IFERROR(ROUND(L64 / J64, 2), "") -> 2.23 | O64: Shoveling into iron tagaris, basket haulage and dumping up to 50 m lead and 1.5 m lift. 1 Coolie moves 17.86 sqm per 8-hr shift.
A65: Rough excav, banking, water & roll (10 cum) | B65: Rough soil digging & heavy clod breaking | C65: 0114 | D65: Beldar (Semi-Skilled / Operational Earthwork) | E65: 10 | F65: cum | G65: 4 | H65: 11.8 | I65: =ROUND(G65 * H65, 3) -> 47.2 | J65: 8 | K65: =ROUND(I65 / J65, 4) -> 5.9 | L65: =IFERROR(ROUND(E65 / K65, 2), "") -> 1.69 | M65: =IFERROR(ROUND(I65 / E65, 4), "") -> 4.72 | N65: =IFERROR(ROUND(L65 / J65, 2), "") -> 0.21 | O65: Rough digging in soil + breaking heavy clods + dressing embankment slope profile. 1 Beldar yields 1.695 cum per 8-hr shift.
A66: Rough excav, banking, water & roll (10 cum) | B66: Basket haulage 50m & 20cm layer spread | C66: 0115 | D66: Coolie (Unskilled / Haulage & Spoil Handling) | E66: 10 | F66: cum | G66: 3 | H66: 9.6 | I66: =ROUND(G66 * H66, 3) -> 28.8 | J66: 8 | K66: =ROUND(I66 / J66, 4) -> 3.6 | L66: =IFERROR(ROUND(E66 / K66, 2), "") -> 2.78 | M66: =IFERROR(ROUND(I66 / E66, 4), "") -> 2.88 | N66: =IFERROR(ROUND(L66 / J66, 2), "") -> 0.35 | O66: Basket haulage within 50 m lead, tipping and uniform spreading in layers not exceeding 20 cm depth.
A67: Rough excav, banking, water & roll (10 cum) | B67: OMC compaction layer watering | C67: 0101 | D67: Bhishti (Compaction Layer Watering to OMC) | E67: 10 | F67: cum | G67: 1 | H67: 3.2 | I67: =ROUND(G67 * H67, 3) -> 3.2 | J67: 8 | K67: =ROUND(I67 / J67, 4) -> 0.4 | L67: =IFERROR(ROUND(E67 / K67, 2), "") -> 25 | M67: =IFERROR(ROUND(I67 / E67, 4), "") -> 0.32 | N67: =IFERROR(ROUND(L67 / J67, 2), "") -> 3.13 | O67: Spraying water over loose 20 cm layers from mashak/hose to optimum moisture content (OMC) before rolling. 25 cum per 8-hr day.
A68: Rough excav, banking, water & roll (10 cum) | B68: 8-10t power roller 6 passes on 20cm layer | C68: 0011 | D68: Road Roller 8-10t Diesel Power (incl Fuel & Crew) | E68: 10 | F68: cum | G68: 1 | H68: 0.064 | I68: =ROUND(G68 * H68, 3) -> 0.064 | J68: 8 | K68: =ROUND(I68 / J68, 4) -> 0.008 | L68: =IFERROR(ROUND(E68 / K68, 2), "") -> 1250 | M68: =IFERROR(ROUND(I68 / E68, 4), "") -> 0.0064 | N68: =IFERROR(ROUND(L68 / J68, 2), "") -> 156.25 | O68: Compacting loose 20 cm layers: 6 passes with 8-10t roller covering 1.8 m width at 2.5 km/h = 156.25 cum/hr (1250 cum per 8-hr shift).
A69: Rough excavation only (10 cum) | B69: Rough soil digging & loosening | C69: 0114 | D69: Beldar (Semi-Skilled / Operational Earthwork) | E69: 10 | F69: cum | G69: 2 | H69: 14.8 | I69: =ROUND(G69 * H69, 3) -> 29.6 | J69: 8 | K69: =ROUND(I69 / J69, 4) -> 3.7 | L69: =IFERROR(ROUND(E69 / K69, 2), "") -> 2.7 | M69: =IFERROR(ROUND(I69 / E69, 4), "") -> 2.96 | N69: =IFERROR(ROUND(L69 / J69, 2), "") -> 0.34 | O69: Pure rough soil digging and loosening without banking or clod pulverization: 29.60 man-hrs / 10 cum (3.70 bd). Daily output: 2.703 cum per 8-hr shift.
A70: Embankment banking excl digging (10 cum) | B70: Breaking clods & shaping slope profile | C70: 0114 | D70: Beldar (Semi-Skilled / Operational Earthwork) | E70: 10 | F70: cum | G70: 2 | H70: 8.8 | I70: =ROUND(G70 * H70, 3) -> 17.6 | J70: 8 | K70: =ROUND(I70 / J70, 4) -> 2.2 | L70: =IFERROR(ROUND(E70 / K70, 2), "") -> 4.55 | M70: =IFERROR(ROUND(I70 / E70, 4), "") -> 1.76 | N70: =IFERROR(ROUND(L70 / J70, 2), "") -> 0.57 | O70: Pulverizing clods, leveling into 20 cm layers and shaping embankment slope profiles: 17.60 man-hrs / 10 cum (2.20 bd). Daily output: 4.545 cum per 8-hr shift. (Full cycle = 3.70 dig + 2.20 bank = 5.90 bd).
A71: Embankment banking excl digging (10 cum) | B71: Haulage & layer spreading | C71: 0115 | D71: Coolie (Unskilled / Haulage & Spoil Handling) | E71: 10 | F71: cum | G71: 3 | H71: 9.6 | I71: =ROUND(G71 * H71, 3) -> 28.8 | J71: 8 | K71: =ROUND(I71 / J71, 4) -> 3.6 | L71: =IFERROR(ROUND(E71 / K71, 2), "") -> 2.78 | M71: =IFERROR(ROUND(I71 / E71, 4), "") -> 2.88 | N71: =IFERROR(ROUND(L71 / J71, 2), "") -> 0.35 | O71: Haulage within 50m lead and spreading in layers not exceeding 20cm.
A72: Embankment banking excl digging (10 cum) | B72: OMC compaction layer watering | C72: 0101 | D72: Bhishti (Compaction Layer Watering to OMC) | E72: 10 | F72: cum | G72: 1 | H72: 3.2 | I72: =ROUND(G72 * H72, 3) -> 3.2 | J72: 8 | K72: =ROUND(I72 / J72, 4) -> 0.4 | L72: =IFERROR(ROUND(E72 / K72, 2), "") -> 25 | M72: =IFERROR(ROUND(I72 / E72, 4), "") -> 0.32 | N72: =IFERROR(ROUND(L72 / J72, 2), "") -> 3.13 | O72: Compaction watering: 25 cum conditioned per 8-hr shift.
A73: Embankment banking excl digging (10 cum) | B73: 8-10t power rolling 6 passes | C73: 0011 | D73: Road Roller 8-10t Diesel Power (incl Fuel & Crew) | E73: 10 | F73: cum | G73: 1 | H73: 0.064 | I73: =ROUND(G73 * H73, 3) -> 0.064 | J73: 8 | K73: =ROUND(I73 / J73, 4) -> 0.008 | L73: =IFERROR(ROUND(E73 / K73, 2), "") -> 1250 | M73: =IFERROR(ROUND(I73 / E73, 4), "") -> 0.0064 | N73: =IFERROR(ROUND(L73 / J73, 2), "") -> 156.25 | O73: Layer consolidation: 1250 cum per 8-hr shift (0.008 machine-day per 10 cum).
A74: Deduct not rolling embankment (10 cum) | B74: Omission of 8-10t power rolling | C74: 0011 | D74: Road Roller 8-10t Diesel Power (incl Fuel & Crew) | E74: 10 | F74: cum | G74: -1 | H74: 0.064 | I74: =ROUND(G74 * H74, 3) -> -0.064 | J74: 8 | K74: =ROUND(I74 / J74, 4) -> -0.008 | L74: =IFERROR(ROUND(E74 / K74, 2), "") -> -1250 | M74: =IFERROR(ROUND(I74 / E74, 4), "") -> -0.0064 | N74: =IFERROR(ROUND(L74 / J74, 2), "") -> -156.25 | O74: Reverses the 8-10t road roller compaction allowance where embankment rolling is omitted: -0.008 roller-day.
... A89: Clearing jungle & rank vegetation (100 sqm) | B89: Stacking & disposal outside 50m periphery | C89: 0115 | D89: Coolie (Unskilled / Haulage & Spoil Handling) | E89: 100 | F89: sqm | G89: 1 | H89: 1.6 | I89: =ROUND(G89 * H89, 3) -> 1.6 | J89: 8 | K89: =ROUND(I89 / J89, 4) -> 0.2 | L89: =IFERROR(ROUND(E89 / K89, 2), "") -> 500 | M89: =IFERROR(ROUND(I89 / E89, 4), "") -> 0.016 | N89: =IFERROR(ROUND(L89 / J89, 2), "") -> 62.5 | O89: Stacking cut brushwood and carrying all unserviceable debris outside 50 m perimeter (500 sqm/day).
A90: 5. RUNNING CUSTOM NON-DSR ITEMS LIBRARY FOR EARTH WORK
A91: Log custom non-DSR earthwork rate analyses below. Results generated above can be archived here for tender schedules.
A92: Custom Code | B92: Item Nomenclature / Scope | C92: Unit | D92: Batch | E92: Mode | F92: CPOH Base | G92: Direct Cost W (₹) | H92: Unit Rate (₹) | I92: Say Rate (₹) | J92: Status | K92: Technical Basis & Remarks
A93: C-02.01 | B93: Earth work surface excavation in soil ≤30cm depth (DAR baseline) | C93: sqm | D93: 100 | E93: DIRECT | F93: W | G93: 6919.2 | H93: 92.55 | I93: 92.55 | J93: COMPLETE | K93: Standard DAR surface excavation benchmark
A94: C-02.02 | B94: Earth work rough excavation, banking, watering & rolling (DAR baseline) | C94: cum | D94: 10 | E94: DIRECT | F94: W | G94: 5581.72 | H94: 746.8 | I94: 746.8 | J94: COMPLETE | K94: Standard DAR embankment benchmark
A95: C-02.03 | B95: Hydraulic excavator 0.9 cum area excavation (DAR baseline) | C95: cum | D95: 10 | E95: DIRECT | F95: W | G95: 1358 | H95: 181.85 | I95: 181.85 | J95: COMPLETE | K95: Standard DAR excavator benchmark
A96: C-02.04 | B96: (Available for custom earthwork specification) | C96: cum | D96: 10 | E96: DIRECT | F96: W | J96: DRAFT | K96: Custom item slot
A97: C-02.05 | B97: (Available for custom earthwork specification) | C97: cum | D97: 10 | E97: DIRECT | F97: W | J97: DRAFT | K97: Custom item slot
A98: C-02.06 | B98: (Available for custom earthwork specification) | C98: sqm | D98: 100 | E98: DIRECT | F98: W | J98: DRAFT | K98: Custom item slot
A99: C-02.07 | B99: (Available for custom earthwork specification) | C99: cum | D99: 10 | E99: DIRECT | F99: W | J99: DRAFT | K99: Custom item slot
A100: C-02.08 | B100: (Available for custom earthwork specification) | C100: m | D100: 100 | E100: DIRECT | F100: W | J100: DRAFT | K100: Custom item slot
A102: TABLE 5E — GROUND-TRUTH RESOURCE NORMS & ACTIVITY SPECIFICATION CATALOG (178 Verified Records)
A103: Ground-truth reference norms transcribed from official CPWD DAR 2019 Volume 1 (Sub-Head 02: Earth Work, PDF pages 88-140). Streamlined into 11 high-value civil engineering columns with separated First-Principles and 8-Hour Shift Derivations.
A104: Primary Work Scope | B104: Ground Strata / Material | C104: Execution Method & Depth Condition | D104: Operation / Task Specification | E104: Line No | F104: Resource Code | G104: Daily Productivity Norm (P) | H104: Engineering First-Principles (Site Mechanics) | I104: CPWD 8-Hour Shift Logic (Mathematical Derivation) | J104: Internal Activity Key | K104: Catalog Norm Input Qty | AA104: Master Activity Full Key | AB104: Master Fallback Key | AC104: Batch Qty | AD104: Batch Unit | AE104: Published Say Rate (₹) | AF104: Official Nomenclature | AG104: Loosening Lever | AH104: Handling Lever | AI104: Spreading Lever | AJ104: Watering Lever | AK104: Compaction Lever | AL104: Task / Operation Specification Options (D9 Dropdown Source)
A105: Surface Excavation (≤30 cm) | B105: All kinds of soil | C105: Manual labor (depth ≤1.5m) | D105: General surface cut (≤30 cm deep) | E105: 1 | F105: 0114 | G105: 14.705882 | H105: Manual pickaxe and phowrah loosening of hard dry soil crust up to 30 cm depth, spade trimming to formation level, and clod pulverization. | I105: Gang: 4 Beldars × 13.60 h = 54.40 man-hrs ÷ 8.00 h = 6.800 Beldar-days per 100 sqm. Daily productivity norm P = 14.71 sqm/8-hr shift (SE = 0.544 hr/sqm, pace = 32.6 min/sqm). | J105: Surface Excavation (≤30 cm)|All kinds of soil|Manual labor (depth ≤1.5m)|General surface cut (≤30 cm deep)|1 | K105: 6.8 | AA105: Surface Excavation (≤30 cm)|All kinds of soil|Manual labor (depth ≤1.5m)|General surface cut (≤30 cm deep) | AB105: Surface Excavation (≤30 cm)|All kinds of soil|Manual labor (depth ≤1.5m) | AC105: 100 | AD105: sqm | AE105: 92.55 | AF105: Earth work in surface excavation not exceeding 30 cm in depth but exceeding 1.5 m in width as well as 10 sqm on plan including getting out and disposal of excavated earth upto 50 m and lift upto 1.5 m, as directed by Engineer-in- Charge:: All kinds of soil Details of cost for 100 Sqm LABOUR | AG105: Manual Pickaxe / Beldar | AH105: Manual Basket (≤50m lead, ≤1.5m lift) | AI105: Dressing & grading surface | AJ105: None | AK105: None | AL105: Banking & rolling only (excavation excluded)
A106: Surface Excavation (≤30 cm) | B106: All kinds of soil | C106: Manual labor (depth ≤1.5m) | D106: General surface cut (≤30 cm deep) | E106: 2 | F106: 0115 | G106: 17.857143 | H106: Manual tagari/basket loading with shovel, haulage within 50 m lead, and tipping onto spoil banks (lift ≤1.5 m). | I106: Gang: 4 Coolies × 11.20 h = 44.80 man-hrs ÷ 8.00 h = 5.600 Coolie-days per 100 sqm. Daily productivity norm P = 17.86 sqm/8-hr shift (SE = 0.448 hr/sqm, pace = 26.9 min/sqm). | J106: Surface Excavation (≤30 cm)|All kinds of soil|Manual labor (depth ≤1.5m)|General surface cut (≤30 cm deep)|2 | K106: 5.6 | AA106: Foundation & Pipeline Trenching|All kinds of soil|Manual labor (depth ≤1.5m)|Pipe / Cable trenches (dia ≤ 80 mm) | AB106: Foundation & Pipeline Trenching|All kinds of soil|Manual labor (depth ≤1.5m) | AC106: 1 | AD106: m | AE106: 223 | AF106: CPWD DAR Item 2.10.1.1 - Earth Work | AG106: Narrow trench spade / pickaxe | AH106: Basket Coolie along trench edge | AI106: Trench bank disposal | AJ106: None | AK106: None | AL106: Clearing grass & removal of rubbish
A107: Embankment Banking & Dressing | B107: All kinds of soil | C107: Manual labor (depth ≤1.5m) | D107: Full cycle: rough excavation + banking + roll | E107: 1 | F107: 0114 | G107: 1.6949153 | H107: Rough soil digging, heavy clod breaking, spreading in 20 cm layers and dressing embankment side slopes. | I107: Gang: 4 Beldars × 11.80 h = 47.20 man-hrs ÷ 8.00 h = 5.900 Beldar-days per 10 cum. Daily output P = 1.695 cum/8-hr shift (SE = 4.72 hr/cum). | J107: Embankment Banking & Dressing|All kinds of soil|Manual labor (depth ≤1.5m)|Full cycle: rough excavation + banking + roll|1 | K107: 5.9 | AA107: Foundation & Pipeline Trenching|All kinds of soil|Manual labor (depth ≤1.5m)|Pipe / Cable trenches (dia 80-300 mm) | AB107: Foundation & Pipeline Trenching|All kinds of soil|Manual labor (depth ≤1.5m) | AC107: 1 | AD107: m | AE107: 364.2 | AF107: CPWD DAR Item 2.10.1.2 - Earth Work | AG107: Narrow trench spade / pickaxe | AH107: Basket Coolie along trench edge | AI107: Trench bank disposal | AJ107: None | AK107: None | AL107: Clearing jungle & rank vegetation uprooting
A108: Embankment Banking & Dressing | B108: All kinds of soil | C108: Manual labor (depth ≤1.5m) | D108: Full cycle: rough excavation + banking + roll | E108: 2 | F108: 0115 | G108: 2.7777778 | H108: Basket haulage within 50 m lead, tipping and uniform spreading in layers not exceeding 20 cm depth. | I108: Gang: 3 Coolies × 9.60 h = 28.80 man-hrs ÷ 8.00 h = 3.600 Coolie-days per 10 cum. Daily output P = 2.778 cum/8-hr shift (SE = 2.88 hr/cum). | J108: Embankment Banking & Dressing|All kinds of soil|Manual labor (depth ≤1.5m)|Full cycle: rough excavation + banking + roll|2 | K108: 3.6 | AA108: Foundation & Pipeline Trenching|All kinds of soil|Manual labor (depth ≤1.5m)|Pipe / Cable trenches (dia > 300 mm) | AB108: Foundation & Pipeline Trenching|All kinds of soil|Manual labor (depth ≤1.5m) | AC108: 1 | AD108: m | AE108: 568.8 | AF108: CPWD DAR Item 2.10.1.3 - Earth Work | AG108: Pickaxe & shovel Beldar | AH108: Basket Coolie along trench edge | AI108: Trench bank disposal | AJ108: None | AK108: None | AL108: Close timbering depth 1.5m-3.0m (90 sqm face)
A109: Embankment Banking & Dressing | B109: All kinds of soil | C109: Manual labor (depth ≤1.5m) | D109: Full cycle: rough excavation + banking + roll | E109: 3 | F109: 0101 | G109: 25 | H109: Spraying water over loose 20 cm layers from leather mashak or hose to reach Optimum Moisture Content (OMC) prior to rolling. | I109: Gang: 1 Bhishti × 3.20 h = 3.20 man-hrs ÷ 8.00 h = 0.400 Bhishti-day per 10 cum. Daily output P = 25.00 cum/8-hr shift (SE = 0.32 hr/cum). | J109: Embankment Banking & Dressing|All kinds of soil|Manual labor (depth ≤1.5m)|Full cycle: rough excavation + banking + roll|3 | K109: 0.4 | AA109: Foundation & Pipeline Trenching|All kinds of soil|Extra depth >1.5m to 3.0m|Extra for pipe trench depth 1.5m to 3.0m | AB109: Foundation & Pipeline Trenching|All kinds of soil|Extra depth >1.5m to 3.0m | AC109: 1 | AD109: m | AE109: 127 | AF109: Extra for excavating trenches for pipes, cables etc. in all kinds of soil for depth exceeding 1.5 m, but not exceeding 3 m. (Rate is over corresponding basic item for depth upto 1.5 metre). Details of cost for 300m length of pipe of an average dia. say 200mm (rate in percentage), Slope assumed 1 in 200. 100x0.60x1.75 = 105.00 cum, 200x 0.60x2.00 = 240.00 cum. Total = 345.00 cum. Collars 5%= 17.25 cum. Total = 362.25 cum. | AG109: Deep trench pickaxe | AH109: Double handling stage lift | AI109: Trench bank disposal | AJ109: None | AK109: None | AL109: Close timbering depth 3.0m-4.5m (90 sqm face)
A110: Embankment Banking & Dressing | B110: All kinds of soil | C110: Manual labor (depth ≤1.5m) | D110: Full cycle: rough excavation + banking + roll | E110: 4 | F110: 0113 | G110: 1250 | H110: Road roller attendant / chowkidar: monitoring compaction passes, edge guidance and equipment safety. | I110: Crew: 1 Chowkidar × 0.064 h ÷ 8.00 h = 0.008 man-day per 10 cum matching roller operating hours. | J110: Embankment Banking & Dressing|All kinds of soil|Manual labor (depth ≤1.5m)|Full cycle: rough excavation + banking + roll|4 | K110: 0.008 | AA110: Foundation & Pipeline Trenching|All kinds of soil|Extra depth >3.0m to 4.5m|Extra for pipe trench depth 3.0m to 4.5m | AB110: Foundation & Pipeline Trenching|All kinds of soil|Extra depth >3.0m to 4.5m | AC110: 1 | AD110: m | AE110: 315.05 | AF110: Extra for excavating trenches for pipes, cables, etc, in all kinds of soil for depth exceeding 3 m in depth, but not exceeding 4.5 m. (Rate is over corresponding basic item for depth upto 1.5 metre.) Details of cost for a 100m length of a pipe of an average dia. say 200mm Slope assumed 1 in 200. Earth work and filling- 1x100x0.60x2 = 120 cum Collars 5% = 6 cum. Total = 126 cum. | AG110: Deep trench pickaxe | AH110: Triple stage hoist / lift | AI110: Trench bank disposal | AJ110: None | AK110: None | AL110: Close timbering depth ≤1.5m (90 sqm face)
A111: Embankment Banking & Dressing | B111: All kinds of soil | C111: Manual labor (depth ≤1.5m) | D111: Full cycle: rough excavation + banking + roll | E111: 5 | F111: 0003 | G111: 1250 | H111: 8-10 tonne diesel 3-wheel power roller conducting 6-8 passes on 20 cm loose layers for roadbed embankment. | I111: Plant: 1 Roller × 0.064 h (3.84 min) ÷ 8.00 h = 0.008 roller-day per 10 cum. Output P = 1,250 cum/8-hr shift. | J111: Embankment Banking & Dressing|All kinds of soil|Manual labor (depth ≤1.5m)|Full cycle: rough excavation + banking + roll|5 | K111: 0.008 | AA111: Foundation & Pipeline Trenching|Ordinary rock|Manual labor (depth ≤1.5m)|Pipe trenches in ordinary rock (≤80mm) | AB111: Foundation & Pipeline Trenching|Ordinary rock|Manual labor (depth ≤1.5m) | AC111: 1 | AD111: m | AE111: 323.85 | AF111: CPWD DAR Item 2.13.1.1 - Earth Work | AG111: Crowbar & sledge hammer | AH111: Basket Coolie along trench edge | AI111: Trench bank disposal | AJ111: None | AK111: None | AL111: DEDUCT: Omission of 8-10t power rolling
A112: Embankment Banking & Dressing | B112: All kinds of soil | C112: Manual labor (depth ≤1.5m) | D112: Full cycle: rough excavation + banking + roll | E112: 6 | F112: 9999 | H112: Sundries: maintenance of digging tools, pickaxe sharpening, wicker baskets and profile templates. | I112: Lump sum tools & plant consumable allowance per standard batch of 10 cum. | J112: Embankment Banking & Dressing|All kinds of soil|Manual labor (depth ≤1.5m)|Full cycle: rough excavation + banking + roll|6 | K112: 2.73 | AA112: Timbering & Shoring|All kinds of soil|Manual labor (depth ≤1.5m)|Close timbering depth ≤1.5m (90 sqm face) | AB112: Timbering & Shoring|All kinds of soil|Manual labor (depth ≤1.5m) | AC112: 90 | AD112: sqm | AE112: 129.95 | AF112: Close timbering in trenches including strutting, shoring and packing cavities (wherever required) complete. (Measurements to be taken of the face area timbered).: Depth not exceeding 1.5 m Details of cost for a trench 30m long and 1.5m deep area 2x30x1.50=90 sqm MATERIAL The Material can be used four times on the same work and after use of material credit is given @ 75% of cost Poling boards of | AG112: Sal wood runners, open/close poling boards | AH112: Lowering into trench & positioning | AI112: Strutting with adjustable screw jacks / timber | AJ112: None | AK112: Tight wedge wedging against trench sides | AL112: DEDUCT: Omission of OMC compaction watering
A113: Embankment Banking & Dressing | B113: All kinds of soil | C113: Manual labor (depth ≤1.5m) | D113: Banking & rolling only (excavation excluded) | E113: 1 | F113: 0114 | G113: 4.5454545 | H113: Pulverizing clods, leveling dumped earth into 20 cm loose layers and shaping embankment slope profiles. | I113: Gang: 2 Beldars × 8.80 h = 17.60 man-hrs ÷ 8.00 h = 2.200 Beldar-days per 10 cum. Daily output P = 4.55 cum/8-hr shift (SE = 1.76 hr/cum). | J113: Embankment Banking & Dressing|All kinds of soil|Manual labor (depth ≤1.5m)|Banking & rolling only (excavation excluded)|1 | K113: 2.2 | AA113: Timbering & Shoring|All kinds of soil|Extra depth >1.5m to 3.0m|Close timbering depth 1.5m-3.0m (90 sqm face) | AB113: Timbering & Shoring|All kinds of soil|Extra depth >1.5m to 3.0m | AC113: 90 | AD113: sqm | AE113: 141.2 | AF113: Close timbering in trenches including strutting, shoring and packing cavities (wherever required) complete. (Measurements to be taken of the face area timbered).: Depth exceeding 1.5 m but not exceeding 3 m Details of cost for a trench 30m long and 1.5m deep Area 2x30x1.50=90 sqm MATERIAL The Material can be used four times on the same work and after use of material credit is given @ 75% of cost Poling boards of | AG113: Sal wood runners, open/close poling boards | AH113: Lowering into trench & positioning | AI113: Strutting with adjustable screw jacks / timber | AJ113: None | AK113: Tight wedge wedging against trench sides | AL113: Excavating post holes 0.1-0.5 cum in hard rock blast
A114: Embankment Banking & Dressing | B114: All kinds of soil | C114: Manual labor (depth ≤1.5m) | D114: Banking & rolling only (excavation excluded) | E114: 2 | F114: 0115 | G114: 2.7777778 | H114: Basket haulage within 50 m lead, tipping and uniform spreading in layers not exceeding 20 cm depth. | I114: Gang: 3 Coolies × 9.60 h = 28.80 man-hrs ÷ 8.00 h = 3.600 Coolie-days per 10 cum. Daily output P = 2.778 cum/8-hr shift (SE = 2.88 hr/cum). | J114: Embankment Banking & Dressing|All kinds of soil|Manual labor (depth ≤1.5m)|Banking & rolling only (excavation excluded)|2 | K114: 3.6 | AA114: Timbering & Shoring|All kinds of soil|Extra depth >3.0m to 4.5m|Close timbering depth 3.0m-4.5m (90 sqm face) | AB114: Timbering & Shoring|All kinds of soil|Extra depth >3.0m to 4.5m | AC114: 90 | AD114: sqm | AE114: 166.55 | AF114: Close timbering in trenches including strutting, shoring and packing cavities (wherever required) complete. (Measurements to be taken of the face area timbered).: Depth exceeding 3 m but not exceeding 4.5 m Details of cost for a trench 30m long and 1.5m deep Area 2x30x1.5=90 sqm- MATERIAL The Material can be used four times on the same work and after use of material credit is given @ 75% of cost Poling boards of | AG114: Sal wood runners, open/close poling boards | AH114: Lowering into trench & positioning | AI114: Strutting with adjustable screw jacks / timber | AJ114: None | AK114: Tight wedge wedging against trench sides | AL114: Excavating post holes 0.1-0.5 cum in hard rock chiseled
A115: Embankment Banking & Dressing | B115: All kinds of soil | C115: Manual labor (depth ≤1.5m) | D115: Banking & rolling only (excavation excluded) | E115: 3 | F115: 0101 | G115: 25 | H115: Spraying water over loose 20 cm layers from leather mashak or hose to reach Optimum Moisture Content (OMC) prior to rolling. | I115: Gang: 1 Bhishti × 3.20 h = 3.20 man-hrs ÷ 8.00 h = 0.400 Bhishti-day per 10 cum. Daily output P = 25.00 cum/8-hr shift (SE = 0.32 hr/cum). | J115: Embankment Banking & Dressing|All kinds of soil|Manual labor (depth ≤1.5m)|Banking & rolling only (excavation excluded)|3 | K115: 0.4 | AA115: Embankment Banking & Dressing|All kinds of soil|Manual labor (depth ≤1.5m)|Full cycle: rough excavation + banking + roll | AB115: Embankment Banking & Dressing|All kinds of soil|Manual labor (depth ≤1.5m) | AC115: 10 | AD115: cum | AE115: 746.8 | AF115: Earth work in rough excavation, banking excavated earth in layers not exceeding 20cm in depth, breaking clods, watering, rolling each layer with ½ tonne roller or wooden or steel rammers, and rolling every 3rd and top-most layer with power roller of minimum 8 tonnes and dressing up in embankments for roads, flood banks, marginal banks and guide banks or filling up ground depressions, lead upto 50 m and lift upto 1.5 m :: All kinds of soil Details of cost for 10 cum. LABOUR | AG115: Rough excavation by Beldar | AH115: Basket Coolie (50m lead / 1.5m lift) | AI115: Spreading in 20cm layers & breaking clods | AJ115: Watering to OMC by Bhishti | AK115: 8-10t Power Roller (every 3rd & top layer) | AL115: Excavating post holes 0.1-0.5 cum in ord rock
A116: Embankment Banking & Dressing | B116: All kinds of soil | C116: Manual labor (depth ≤1.5m) | D116: Banking & rolling only (excavation excluded) | E116: 4 | F116: 0113 | G116: 1250 | H116: Road roller attendant / chowkidar: monitoring compaction passes, edge guidance and equipment safety. | I116: Crew: 1 Chowkidar × 0.064 h ÷ 8.00 h = 0.008 man-day per 10 cum matching roller operating hours. | J116: Embankment Banking & Dressing|All kinds of soil|Manual labor (depth ≤1.5m)|Banking & rolling only (excavation excluded)|4 | K116: 0.008 | AA116: Foundation & Pipeline Trenching|All kinds of soil|Manual labor (depth ≤1.5m)|Extra for wet/water position (+20%) | AB116: Foundation & Pipeline Trenching|All kinds of soil|Manual labor (depth ≤1.5m) | AC116: 1 | AD116: m-depth | AE116: 20 | AF116: CPWD DAR Item 2.24.1 - Earth Work | AG116: Excavation under wet / foul conditions | AH116: Mud / slush bailing & haulage | AI116: Disposal | AJ116: Submerged / wet | AK116: None | AL116: Excavating post holes 0.1-0.5 cum in soil
A117: Embankment Banking & Dressing | B117: All kinds of soil | C117: Manual labor (depth ≤1.5m) | D117: Banking & rolling only (excavation excluded) | E117: 5 | F117: 0003 | G117: 1250 | H117: 8-10 tonne diesel 3-wheel power roller conducting 6-8 passes on 20 cm loose layers for roadbed embankment. | I117: Plant: 1 Roller × 0.064 h (3.84 min) ÷ 8.00 h = 0.008 roller-day per 10 cum. Output P = 1,250 cum/8-hr shift. | J117: Embankment Banking & Dressing|All kinds of soil|Manual labor (depth ≤1.5m)|Banking & rolling only (excavation excluded)|5 | K117: 0.008 | AA117: Foundation & Pipeline Trenching|All kinds of soil|Manual labor (depth ≤1.5m)|Extra for foul position (+25%) | AB117: Foundation & Pipeline Trenching|All kinds of soil|Manual labor (depth ≤1.5m) | AC117: 1 | AD117: m-depth | AE117: 25 | AF117: CPWD DAR Item 2.24.2 - Earth Work | AG117: Excavation under wet / foul conditions | AH117: Mud / slush bailing & haulage | AI117: Disposal | AJ117: Submerged / wet | AK117: None | AL117: Extra for foul position (+25%)
A118: Embankment Banking & Dressing | B118: All kinds of soil | C118: Manual labor (depth ≤1.5m) | D118: Banking & rolling only (excavation excluded) | E118: 6 | F118: 9999 | H118: Sundries: maintenance of digging tools, pickaxe sharpening, wicker baskets and profile templates. | I118: Lump sum tools & plant consumable allowance per standard batch of 10 cum. | J118: Embankment Banking & Dressing|All kinds of soil|Manual labor (depth ≤1.5m)|Banking & rolling only (excavation excluded)|6 | K118: 2.73 | AA118: Backfilling & Compaction|All kinds of soil|Manual labor (depth ≤1.5m)|Filling available excavated earth in plinth/trenches | AB118: Backfilling & Compaction|All kinds of soil|Manual labor (depth ≤1.5m) | AC118: 10 | AD118: cum | AE118: 219.65 | AF118: Filling available excavated earth (excluding rock) in trenches, plinth, sides of foundations etc. in layers not exceeding 20cm in depth, consolidating each deposited layer by ramming and watering, lead up to 50 m and lift upto 1.5 m. Details of cost for 10 cum. LABOUR | AG118: Available excavated spoil (no digging) | AH118: Basket Coolie return lead ≤50m | AI118: Spreading in layers ≤20 cm | AJ118: Watering each layer | AK118: Durmat ramming / hand compaction | AL118: Extra for pipe trench depth 1.5m to 3.0m
A119: Embankment Banking & Dressing | B119: All kinds of soil | C119: Manual labor (depth ≤1.5m) | D119: DEDUCT: Omission of 8-10t power rolling | E119: 1 | F119: 0113 | G119: 1250 | H119: Omission of power rolling: eliminates 8-10t 3-wheel diesel roller consolidation. | I119: Crew: 1 Chowkidar × 0.064 h ÷ 8.00 h = 0.008 man-day per 10 cum matching roller operating hours. | J119: Embankment Banking & Dressing|All kinds of soil|Manual labor (depth ≤1.5m)|DEDUCT: Omission of 8-10t power rolling|1 | K119: 0.008 | AA119: Foundation & Pipeline Trenching|All kinds of soil|Extra depth >1.5m to 3.0m|Extra lift for every additional 1.5m | AB119: Foundation & Pipeline Trenching|All kinds of soil|Extra depth >1.5m to 3.0m | AC119: 10 | AD119: cum | AE119: 90.4 | AF119: Extra for every additional lift of 1.5 m or part thereof in excavation / banking excavated or stacked materials.: All kinds of soil Details of cost for 10 cum. LABOUR | AG119: Deep excavation lift | AH119: Staged manual lifting per 1.5m | AI119: Disposal | AJ119: None | AK119: None | AL119: Extra for pipe trench depth 3.0m to 4.5m
...

Sheet 03_Mortars
A1: CPWD DAR 2019 — SUB-HEAD 03: MORTARS (INTERMEDIATE MIX BUILDER)
A2: LEGEND: | B2: INPUT - you type it | C2: OVERRIDE - optional | D2: LOOKUP - fetched | E2: DERIVED - calculated | F2: RESULT - subtotal | G2: SAY - final rate | H2: CPWD rule / note | I2: Not editable
A3: CPWD DAR Sub-head 03: Mortars serve as intermediate building blocks for Masonry, Stone, Cladding, and Flooring. Direct Cost (W) equals Final Cost. Markup chain is turned OFF by default to avoid double-taxation and double-profit in consuming trades.
A4: HOW TO USE THIS SHEET (read this before typing anything)
A5: HOW TO USE THIS SHEET - STEP 1: fill in PANEL 1 to say WHAT is being built; each row tells you whether that choice actually changes the cost. STEP 2: set the quantities in PANEL 2. STEP 3: enter the MATERIAL and LABOUR lines - type a code in the yellow "Code / Source" cell and the description, unit and rate fill themselves in. STEP 4: read the gold SAY rate at the bottom. Everything between Step 3 and the SAY rate is calculated for you - if a cell is not yellow or orange, do not type in it.
A6: WHAT THE COLOURS MEAN - YELLOW = INPUT, you type it. ORANGE = OVERRIDE, optional; leave it blank to use the looked-up value, or type here to force your own. BLUE = LOOKUP, fetched from Rates_Master or another reference sheet. WHITE = DERIVED, calculated from the cells above it. GREEN = a subtotal to read. GOLD = the final SAY rate. The sheet is protected, so only the yellow and orange cells will let you type at all.
A8: 1. PANEL 1 - SCOPE & SPECIFICATION INPUTS (what is being built, and which clauses actually move cost)
A9: Nomenclature Clause / Dimension | B9: Selected Value | C9: Cost Impact | D9: Drives | E9: What changes when this selection changes, and the DAR 2019 evidence for it
A10: Binder type | B10: Ordinary Portland cement | C10: DRIVES COST | D10: Material row 1 | E10: DAR 3.1-3.14 use ordinary cement (code 0367); 3.15-3.17 use white cement at a different rate. Changing the binder changes the material code and rate.
A11: Mix ratio (binder : aggregate) | B11: 1:4 | C11: DRIVES COST | D11: Material coeffs | E11: DAR 3.1 (1:1) through 3.11 (1:6) print a different cement volume for every ratio - 0.7175 cum of cement at 1:1 down to 0.178 cum at 1:6. This is the strongest cost driver on the sheet.
A12: Fine aggregate type | B12: coarse sand | C12: DRIVES COST | D12: Material row 3 | E12: DAR splits the same ratios by aggregate: 3.1-3.6 fine sand, 3.7-3.11 coarse sand, 3.12 stone dust, 3.13-3.14 marble dust - each a different Rates_Master code and rate.
A13: Mixing method | B13: Manual (hand mixing) | C13: DRIVES COST | D13: Labour rows | E13: Hand mixing is priced with Beldar days; mechanical mixing adds a plant hire line (code 0002 onwards) whose day rate already includes operator and fuel per CPWD Note 1.
A14: Location / lift of use | B14: at ground level | C14: NOMENCLATURE ONLY | D14: - | E14: The Mortars sub-head prices the mix itself, not its placement. Lifting to upper floors is priced in the consuming trade (see the "extra labour for lifting material" lines inside DAR 4.2.5), not here.
A15: Purpose of the mix | B15: for masonry bedding | C15: NOMENCLATURE ONLY | D15: - | E15: The DAR does not vary a mortar rate by what it will be used for; the same item 3.9 is imported by Masonry, Stone, Cladding and Flooring alike.
A16: Custom Item Code: | B16: C-03.01 | C16: Batch Output Basis: | D16: 1 | E16: Output Unit: | F16: cum | G16: Trade Sub-Head: | H16: 03 Mortars | I16: Output Unit Note:
A17: Assembled Item Nomenclature: | B17: =IF(I17<>"", I17, "Providing and mixing " & B10 & ", " & B11 & ", " & B12 & ", " & B13 & ", " & B14 & ", " & B15 & ", complete as per CPWD specifications and directions of Engineer-in-charge.") -> Providing and mixing Ordinary Portland cement, 1:4, coarse sand, Manual (hand mixing), at ground level, for masonry bedding, complete as per CPWD specifications and directions of Engineer-in-charge. | H17: Manual Override:
A18: 2. PANEL 2 - OPERATIONAL & DERIVATION DRIVERS (quantities and allowances that scale the build-up below)
A19: Driver | B19: Value | C19: Unit | D19: Applies To | E19: How this driver is used, and the DAR 2019 basis for the default
A20: Dry volume factor | B20: 1.3 | C20: ratio | D20: Material coeffs | E20: The DAR derives wet-to-dry mortar volume inside each item header (e.g. 3.9 "0.268 cum of cement"). Adjust only if you are deriving a ratio the book does not print.
A21: Cement bulk density | B21: 1.44 | C21: tonne / cum | D21: Cement coeff | E21: Used to convert the printed cement volume into the tonne basis that code 0367 is rated in - the conversion the DAR performs inline (0.269 cum = 0.38 tonne).
A22: Batch output basis | B22: 1 | C22: cum | D22: Batch basis | E22: Every DAR mortar item is analysed for 1.00 cum. Keep 1.00 unless you deliberately want a batch rate.
A23: Wastage allowance | B23: 0 | C23: % | D23: Material coeffs | E23: The DAR mortar items carry no wastage percentage - wastage on mortar is absorbed in the consuming trade. Leave at 0 to stay faithful to the book.
A24: COST-IMPACT KEY - "DRIVES COST" = the DAR 2019 prints different figures for the listed choices, and changing the selection changes a code, coefficient or imported rate on this sheet. "NOMENCLATURE ONLY" = the clause changes the wording of the item but the DAR prices one rate for every variant, so there is no differential data to apply. "USER-SUPPLIED COST" = the clause has a real cost but the DAR gives no figure for it, so enter the amount yourself (normally as a Sundries / L.S. line).
A25: AUDIT STATUS: | B25: =IF(AND(D25="OK", F25="OK", H25="OK"), "[PASS] ALL CHECKS OK", "[ALERT] CHECKS FAILED") -> [PASS] ALL CHECKS OK | C25: Output Qty Check: | D25: =IF(D16>0, "OK", "ERR: Qty<=0") -> OK | E25: Direct Cost Check: | F25: =IF(G59>0, "OK", "ERR: W<=0") -> OK | G25: Markup Flow Check: | H25: =IF(AND(G59<=G61, G61<=G63, G63<=G65, G39<=G59), "OK", "ERR: Markups Broken") -> OK | I25: =IF(G39>0, "A-rule active", "No A imports") -> No A imports
A26: 3. MATERIAL COMPONENT BUILD-UP (tag column I with "A" for any line whose rate already includes statutory markups)
A27: Line | B27: Code / Source | C27: Description / Specification | D27: Unit | E27: Quantity / Coeff | F27: Basic Rate (Rs) | G27: Amount (Rs) | H27: Source Reference / Remarks | I27: Markup Tag
A28: 1 | B28: 0367 | C28: =IF(B28="","", IFERROR(INDEX(Rates_Master!$C:$C, MATCH(B28, Rates_Master!$A:$A, 0)), "Custom / Intermediate Material")) -> Portland Cement (OPC-43 Grade) | D28: =IF(B28="","", IFERROR(INDEX(Rates_Master!$D:$D, MATCH(B28, Rates_Master!$A:$A, 0)), "")) -> tonne | E28: 0.38 | F28: =IF(B28="","", IFERROR(INDEX(Rates_Master!$E:$E, MATCH(B28, Rates_Master!$A:$A, 0)), 0)) -> 4940 | G28: =IF(OR(B28="", E28=""), 0, ROUND(E28 * F28, 2)) -> 1877.2 | H28: Portland Cement (0.269 cum = 0.38 tonne)
A29: 2 | B29: 2209 | C29: =IF(B29="","", IFERROR(INDEX(Rates_Master!$C:$C, MATCH(B29, Rates_Master!$A:$A, 0)), "Custom / Intermediate Material")) -> Carriage of Cement | D29: =IF(B29="","", IFERROR(INDEX(Rates_Master!$D:$D, MATCH(B29, Rates_Master!$A:$A, 0)), "")) -> tonne | E29: 0.38 | F29: =IF(B29="","", IFERROR(INDEX(Rates_Master!$E:$E, MATCH(B29, Rates_Master!$A:$A, 0)), 0)) -> 92.24 | G29: =IF(OR(B29="", E29=""), 0, ROUND(E29 * F29, 2)) -> 35.05 | H29: Carriage of Cement
A30: 3 | B30: 0982 | C30: =IF(B30="","", IFERROR(INDEX(Rates_Master!$C:$C, MATCH(B30, Rates_Master!$A:$A, 0)), "Custom / Intermediate Material")) -> Coarse sand (zone III) | D30: =IF(B30="","", IFERROR(INDEX(Rates_Master!$D:$D, MATCH(B30, Rates_Master!$A:$A, 0)), "")) -> cum | E30: 1.07 | F30: =IF(B30="","", IFERROR(INDEX(Rates_Master!$E:$E, MATCH(B30, Rates_Master!$A:$A, 0)), 0)) -> 1350 | G30: =IF(OR(B30="", E30=""), 0, ROUND(E30 * F30, 2)) -> 1444.5 | H30: Coarse sand (zone III)
A31: 4 | B31: 2203 | C31: =IF(B31="","", IFERROR(INDEX(Rates_Master!$C:$C, MATCH(B31, Rates_Master!$A:$A, 0)), "Custom / Intermediate Material")) -> Carriage of Coarse sand | D31: =IF(B31="","", IFERROR(INDEX(Rates_Master!$D:$D, MATCH(B31, Rates_Master!$A:$A, 0)), "")) -> cum | E31: 1.07 | F31: =IF(B31="","", IFERROR(INDEX(Rates_Master!$E:$E, MATCH(B31, Rates_Master!$A:$A, 0)), 0)) -> 103.77 | G31: =IF(OR(B31="", E31=""), 0, ROUND(E31 * F31, 2)) -> 111.03 | H31: Carriage of Coarse sand
A32: 5 | C32: =IF(B32="","", IFERROR(INDEX(Rates_Master!$C:$C, MATCH(B32, Rates_Master!$A:$A, 0)), "Custom / Intermediate Material")) | D32: =IF(B32="","", IFERROR(INDEX(Rates_Master!$D:$D, MATCH(B32, Rates_Master!$A:$A, 0)), "")) | F32: =IF(B32="","", IFERROR(INDEX(Rates_Master!$E:$E, MATCH(B32, Rates_Master!$A:$A, 0)), 0)) | G32: =IF(OR(B32="", E32=""), 0, ROUND(E32 * F32, 2)) -> 0
A33: 6 | C33: =IF(B33="","", IFERROR(INDEX(Rates_Master!$C:$C, MATCH(B33, Rates_Master!$A:$A, 0)), "Custom / Intermediate Material")) | D33: =IF(B33="","", IFERROR(INDEX(Rates_Master!$D:$D, MATCH(B33, Rates_Master!$A:$A, 0)), "")) | F33: =IF(B33="","", IFERROR(INDEX(Rates_Master!$E:$E, MATCH(B33, Rates_Master!$A:$A, 0)), 0)) | G33: =IF(OR(B33="", E33=""), 0, ROUND(E33 * F33, 2)) -> 0
A34: 7 | C34: =IF(B34="","", IFERROR(INDEX(Rates_Master!$C:$C, MATCH(B34, Rates_Master!$A:$A, 0)), "Custom / Intermediate Material")) | D34: =IF(B34="","", IFERROR(INDEX(Rates_Master!$D:$D, MATCH(B34, Rates_Master!$A:$A, 0)), "")) | F34: =IF(B34="","", IFERROR(INDEX(Rates_Master!$E:$E, MATCH(B34, Rates_Master!$A:$A, 0)), 0)) | G34: =IF(OR(B34="", E34=""), 0, ROUND(E34 * F34, 2)) -> 0
A35: 8 | C35: =IF(B35="","", IFERROR(INDEX(Rates_Master!$C:$C, MATCH(B35, Rates_Master!$A:$A, 0)), "Custom / Intermediate Material")) | D35: =IF(B35="","", IFERROR(INDEX(Rates_Master!$D:$D, MATCH(B35, Rates_Master!$A:$A, 0)), "")) | F35: =IF(B35="","", IFERROR(INDEX(Rates_Master!$E:$E, MATCH(B35, Rates_Master!$A:$A, 0)), 0)) | G35: =IF(OR(B35="", E35=""), 0, ROUND(E35 * F35, 2)) -> 0
A36: 9 | C36: =IF(B36="","", IFERROR(INDEX(Rates_Master!$C:$C, MATCH(B36, Rates_Master!$A:$A, 0)), "Custom / Intermediate Material")) | D36: =IF(B36="","", IFERROR(INDEX(Rates_Master!$D:$D, MATCH(B36, Rates_Master!$A:$A, 0)), "")) | F36: =IF(B36="","", IFERROR(INDEX(Rates_Master!$E:$E, MATCH(B36, Rates_Master!$A:$A, 0)), 0)) | G36: =IF(OR(B36="", E36=""), 0, ROUND(E36 * F36, 2)) -> 0
A37: 10 | C37: =IF(B37="","", IFERROR(INDEX(Rates_Master!$C:$C, MATCH(B37, Rates_Master!$A:$A, 0)), "Custom / Intermediate Material")) | D37: =IF(B37="","", IFERROR(INDEX(Rates_Master!$D:$D, MATCH(B37, Rates_Master!$A:$A, 0)), "")) | F37: =IF(B37="","", IFERROR(INDEX(Rates_Master!$E:$E, MATCH(B37, Rates_Master!$A:$A, 0)), 0)) | G37: =IF(OR(B37="", E37=""), 0, ROUND(E37 * F37, 2)) -> 0
A38: Subtotal Materials (Rs): | G38: =SUM(G28:G37) -> 3467.78
A39: of which "A" - imported lines already carrying statutory markups: | G39: =ROUND(SUMIF($I$28:$I$37, "A", $G$28:$G$37), 2) -> 0 | H39: CPWD (W-A) convention: this amount stays inside W and inside every subtotal, but is subtracted from each markup BASE so an already-marked-up import is not marked up twice. Verified against DAR 2019 items 10.1, 18.78 and 18.79.
A40: 4. LABOUR & MACHINERY COMPONENT BUILD-UP (crew suggestions: see the work-type summary on Labour_Machinery_Productivity. Plant codes 0001-0083 already include operator, fuel and lubricants for an 8-hour shift per CPWD Note 1)
A41: Line | B41: Code / Source | C41: Description / Specification | D41: Unit | E41: Quantity / Coeff | F41: Basic Rate (Rs) | G41: Amount (Rs) | H41: Source Reference / Remarks | I41: Markup Tag
A42: 1 | B42: 0114 | C42: =IF(B42="","", IFERROR(INDEX(Rates_Master!$C:$C, MATCH(B42, Rates_Master!$A:$A, 0)), "Custom Labour / Plant")) -> Beldar | D42: =IF(B42="","", IFERROR(INDEX(Rates_Master!$D:$D, MATCH(B42, Rates_Master!$A:$A, 0)), "")) -> day | E42: 0.75 | F42: =IF(B42="","", IFERROR(INDEX(Rates_Master!$E:$E, MATCH(B42, Rates_Master!$A:$A, 0)), 0)) -> 558 | G42: =IF(OR(B42="", E42=""), 0, ROUND(E42 * F42, 2)) -> 418.5 | H42: Beldar (measuring, carrying & mixing)
A43: 2 | B43: 0101 | C43: =IF(B43="","", IFERROR(INDEX(Rates_Master!$C:$C, MATCH(B43, Rates_Master!$A:$A, 0)), "Custom Labour / Plant")) -> Bhisti | D43: =IF(B43="","", IFERROR(INDEX(Rates_Master!$D:$D, MATCH(B43, Rates_Master!$A:$A, 0)), "")) -> day | E43: 0.07 | F43: =IF(B43="","", IFERROR(INDEX(Rates_Master!$E:$E, MATCH(B43, Rates_Master!$A:$A, 0)), 0)) -> 617 | G43: =IF(OR(B43="", E43=""), 0, ROUND(E43 * F43, 2)) -> 43.19 | H43: Bhisti (watering)
A44: 3 | C44: =IF(B44="","", IFERROR(INDEX(Rates_Master!$C:$C, MATCH(B44, Rates_Master!$A:$A, 0)), "Custom Labour / Plant")) | D44: =IF(B44="","", IFERROR(INDEX(Rates_Master!$D:$D, MATCH(B44, Rates_Master!$A:$A, 0)), "")) | F44: =IF(B44="","", IFERROR(INDEX(Rates_Master!$E:$E, MATCH(B44, Rates_Master!$A:$A, 0)), 0)) | G44: =IF(OR(B44="", E44=""), 0, ROUND(E44 * F44, 2)) -> 0
A45: 4 | C45: =IF(B45="","", IFERROR(INDEX(Rates_Master!$C:$C, MATCH(B45, Rates_Master!$A:$A, 0)), "Custom Labour / Plant")) | D45: =IF(B45="","", IFERROR(INDEX(Rates_Master!$D:$D, MATCH(B45, Rates_Master!$A:$A, 0)), "")) | F45: =IF(B45="","", IFERROR(INDEX(Rates_Master!$E:$E, MATCH(B45, Rates_Master!$A:$A, 0)), 0)) | G45: =IF(OR(B45="", E45=""), 0, ROUND(E45 * F45, 2)) -> 0
A46: 5 | C46: =IF(B46="","", IFERROR(INDEX(Rates_Master!$C:$C, MATCH(B46, Rates_Master!$A:$A, 0)), "Custom Labour / Plant")) | D46: =IF(B46="","", IFERROR(INDEX(Rates_Master!$D:$D, MATCH(B46, Rates_Master!$A:$A, 0)), "")) | F46: =IF(B46="","", IFERROR(INDEX(Rates_Master!$E:$E, MATCH(B46, Rates_Master!$A:$A, 0)), 0)) | G46: =IF(OR(B46="", E46=""), 0, ROUND(E46 * F46, 2)) -> 0
A47: 6 | C47: =IF(B47="","", IFERROR(INDEX(Rates_Master!$C:$C, MATCH(B47, Rates_Master!$A:$A, 0)), "Custom Labour / Plant")) | D47: =IF(B47="","", IFERROR(INDEX(Rates_Master!$D:$D, MATCH(B47, Rates_Master!$A:$A, 0)), "")) | F47: =IF(B47="","", IFERROR(INDEX(Rates_Master!$E:$E, MATCH(B47, Rates_Master!$A:$A, 0)), 0)) | G47: =IF(OR(B47="", E47=""), 0, ROUND(E47 * F47, 2)) -> 0
A48: 7 | C48: =IF(B48="","", IFERROR(INDEX(Rates_Master!$C:$C, MATCH(B48, Rates_Master!$A:$A, 0)), "Custom Labour / Plant")) | D48: =IF(B48="","", IFERROR(INDEX(Rates_Master!$D:$D, MATCH(B48, Rates_Master!$A:$A, 0)), "")) | F48: =IF(B48="","", IFERROR(INDEX(Rates_Master!$E:$E, MATCH(B48, Rates_Master!$A:$A, 0)), 0)) | G48: =IF(OR(B48="", E48=""), 0, ROUND(E48 * F48, 2)) -> 0
A49: 8 | C49: =IF(B49="","", IFERROR(INDEX(Rates_Master!$C:$C, MATCH(B49, Rates_Master!$A:$A, 0)), "Custom Labour / Plant")) | D49: =IF(B49="","", IFERROR(INDEX(Rates_Master!$D:$D, MATCH(B49, Rates_Master!$A:$A, 0)), "")) | F49: =IF(B49="","", IFERROR(INDEX(Rates_Master!$E:$E, MATCH(B49, Rates_Master!$A:$A, 0)), 0)) | G49: =IF(OR(B49="", E49=""), 0, ROUND(E49 * F49, 2)) -> 0
A50: 9 | C50: =IF(B50="","", IFERROR(INDEX(Rates_Master!$C:$C, MATCH(B50, Rates_Master!$A:$A, 0)), "Custom Labour / Plant")) | D50: =IF(B50="","", IFERROR(INDEX(Rates_Master!$D:$D, MATCH(B50, Rates_Master!$A:$A, 0)), "")) | F50: =IF(B50="","", IFERROR(INDEX(Rates_Master!$E:$E, MATCH(B50, Rates_Master!$A:$A, 0)), 0)) | G50: =IF(OR(B50="", E50=""), 0, ROUND(E50 * F50, 2)) -> 0
A51: 10 | C51: =IF(B51="","", IFERROR(INDEX(Rates_Master!$C:$C, MATCH(B51, Rates_Master!$A:$A, 0)), "Custom Labour / Plant")) | D51: =IF(B51="","", IFERROR(INDEX(Rates_Master!$D:$D, MATCH(B51, Rates_Master!$A:$A, 0)), "")) | F51: =IF(B51="","", IFERROR(INDEX(Rates_Master!$E:$E, MATCH(B51, Rates_Master!$A:$A, 0)), 0)) | G51: =IF(OR(B51="", E51=""), 0, ROUND(E51 * F51, 2)) -> 0
A52: Subtotal Labour & Plant Hire (Rs): | G52: =SUM(G42:G51) -> 461.69
A54: 5. SUNDRIES & LUMP-SUM ALLOWANCES (manual entry - the DAR gives no reproducible formula; use Sundries_Reference to find a comparable item)
A55: 1 | B55: 9999 | C55: Sundries (guided by Sundries_Reference sheet) | D55: L.S. | E55: 13.52 | F55: =Factor_Sundries -> 2 | G55: =ROUND(E55 * F55, 2) -> 27.04 | H55: Base L.S. allowance x Cost Index Multiplier (2.00) from Global_Factors
A57: 6. STATUTORY MARKUPS & FINAL RATE DERIVATION (CPWD DAR METHOD, WITH THE (W-A) EXCLUSION)
A58: Step | B58: Component / Markup Description | C58: Apply? (YES/NO) | D58: Basis Applied | E58: Base Amount (Rs) | F58: Factor / % | G58: Amount (Rs) | H58: CPWD Statutory Rule & Guidance Note | I58: A-Rule
A59: W | B59: Base Direct Production Cost (Materials + Labour + Sundries) | C59: - | D59: Direct Sum | E59: - | F59: - | G59: =G38 + G52 + G55 -> 3956.51 | H59: Total direct cost of production (W), A-tagged imports included, exactly as the book totals it. | I59: includes A
A60: X1 | B60: Add Water Charges | C60: NO | D60: On (W - A) | E60: =G59 - G39 -> 3956.51 | F60: =Factor_Water -> 0.01 | G60: =IF(C60="YES", ROUND(E60 * F60, 2), 0) -> 0 | H60: CPWD RULE: 0% markup default. Water is not added here as it is marked up once in Masonry/Flooring. | I60: net of A
A61: X | B61: Subtotal "X" (W + Water Charges) | C61: - | D61: W + Water | E61: - | F61: - | G61: =G59 + G60 -> 3956.51 | H61: Compounded base for GST calculation | I61: includes A
A62: Y1 | B62: Add GST on Works Contract | C62: NO | D62: On (X - A) | E62: =G61 - G39 -> 3956.51 | F62: =Factor_GST -> 0.1405 | G62: =IF(C62="YES", ROUND(E62 * F62, 2), 0) -> 0 | H62: CPWD RULE: GST is not added here to prevent double taxation when imported into Masonry. | I62: net of A
A63: Y | B63: Subtotal "Y" (X + GST) | C63: - | D63: X + GST | E63: - | F63: - | G63: =G61 + G62 -> 3956.51 | H63: Compounded base for Contractor Profit & Overheads | I63: includes A
A64: Z1 | B64: Add Contractor Profit & Overheads (15% CPOH) | C64: NO | D64: On (Y - A) | E64: =G63 - G39 -> 3956.51 | F64: =Factor_CPOH -> 0.15 | G64: =IF(C64="YES", ROUND(E64 * F64, 2), 0) -> 0 | H64: CPWD RULE: Contractor profit is not added to intermediate mortar. Consuming trades add 15% CPOH over combined total. | I64: net of A
A65: Z | B65: Subtotal "Z" (Y + CPOH) | C65: - | D65: Y + CPOH | E65: - | F65: - | G65: =G63 + G64 -> 3956.51 | H65: Compounded base for Labour Welfare Cess | I65: includes A
A66: Z2 | B66: Add Labour Welfare Cess (1% BOCW Cess) | C66: NO | D66: On (Z - A) | E66: =G65 - G39 -> 3956.51 | F66: =Factor_Cess -> 0.01 | G66: =IF(C66="YES", ROUND(E66 * F66, 2), 0) -> 0 | H66: CPWD RULE: 0% Cess here; applied once at the end of the consuming trade item. | I66: net of A
A67: Cost | B67: ="Total Cost of Batch (" & TEXT(D16, "0.00") & " " & F16 & "):" -> Total Cost of Batch (1.00 cum): | C67: - | D67: Z + Cess | E67: - | F67: - | G67: =G65 + G66 -> 3956.51 | H67: Total evaluated cost for the batch size in the Panel 1 header row | I67: -
A68: Rate | B68: ="Analyzed Unit Rate per 1.00 " & F16 & ":" -> Analyzed Unit Rate per 1.00 cum: | C68: - | D68: Cost / Batch Qty | E68: - | F68: - | G68: =ROUND(G67 / D16, 2) -> 3956.51 | H68: Calculated cost per standard unit of measurement | I68: -
A69: SAY | B69: ="OFFICIAL SAY RATE (Rs per " & F16 & "):" -> OFFICIAL SAY RATE (Rs per cum): | C69: - | D69: MROUND to Rs 0.05 | E69: - | F69: - | G69: =MROUND(G68, 0.05) -> 3956.5 | H69: OFFICIAL CPWD ROUNDED RATE FOR TENDER SCHEDULES & ESTIMATES. CPWD quotes Say rates to the nearest 5 paise - see the note directly below this row. | I69: -
A70: WHY THE SAY RATE IS ROUNDED TO 5 PAISE: CPWD DAR 2019 quotes every "Say" rate to the nearest Rs 0.05, not to two decimals - e.g. item 1.3 computes 104.89 and is printed as 104.90; item 1.4.1 computes 155.47 and is printed as 155.45; item 10.1 computes 86.04 and is printed as 86.05. This sheet therefore uses MROUND(rate, 0.05) so the analysed rate matches the book exactly instead of sitting a paisa away from it. Change the 0.05 only if your circle office issues a different rounding rule.
A72: 7. RUNNING CUSTOM NON-DSR ITEMS LIBRARY FOR THIS TRADE
A73: Log all completed custom rate analyses for this trade below. Items logged here maintain an internal project audit trail and can be referenced from other builder sheets.
A74: Item Code | B74: Item Nomenclature / Specification | C74: Unit | D74: Output Basis | E74: Direct Cost W (Rs) | F74: Markups Applied | G74: Unit Rate (Rs) | H74: Say Rate (Rs) | I74: A-Total (Rs)
A75: 3.1 | B75: Cement mortar 1:1 (1 cement : 1 fine sand) | C75: cum | D75: 1 | E75: 6390.6 | F75: No markups (base cost) | G75: 6390.6 | H75: 6390.6
A76: 3.9 | B76: Cement mortar 1:4 (1 cement : 4 coarse sand) | C76: cum | D76: 1 | E76: 4010.35 | F76: No markups (base cost) | G76: 4010.35 | H76: 4010.35
A77: C-03.03 | B77: (Available for new custom item) | C77: cum | D77: 1 | F77: Full W->X->Y->Z
A78: C-03.04 | B78: (Available for new custom item) | C78: cum | D78: 1 | F78: Full W->X->Y->Z
A79: C-03.05 | B79: (Available for new custom item) | C79: cum | D79: 1 | F79: Full W->X->Y->Z
A80: C-03.06 | B80: (Available for new custom item) | C80: cum | D80: 1 | F80: Full W->X->Y->Z
A81: C-03.07 | B81: (Available for new custom item) | C81: cum | D81: 1 | F81: Full W->X->Y->Z
A82: C-03.08 | B82: (Available for new custom item) | C82: cum | D82: 1 | F82: Full W->X->Y->Z

Sheet 04_Concrete_Work
A1: CPWD DAR 2019 — SUB-HEAD 04: CONCRETE WORK (CUSTOM ITEM BUILDER)
A2: LEGEND: | B2: INPUT - you type it | C2: OVERRIDE - optional | D2: LOOKUP - fetched | E2: DERIVED - calculated | F2: RESULT - subtotal | G2: SAY - final rate | H2: CPWD rule / note | I2: Not editable
A3: CPWD DAR Sub-head 04: Plain cement concrete. Built from coarse aggregate, fine aggregate, cement, carriage lines, mixing & placing labour, mixer and vibrator hire. Full 5-step compounding markup chain applies.
A4: HOW TO USE THIS SHEET (read this before typing anything)
A5: HOW TO USE THIS SHEET - STEP 1: fill in PANEL 1 to say WHAT is being built; each row tells you whether that choice actually changes the cost. STEP 2: set the quantities in PANEL 2. STEP 3: enter the MATERIAL and LABOUR lines - type a code in the yellow "Code / Source" cell and the description, unit and rate fill themselves in. STEP 4: read the gold SAY rate at the bottom. Everything between Step 3 and the SAY rate is calculated for you - if a cell is not yellow or orange, do not type in it.
A6: WHAT THE COLOURS MEAN - YELLOW = INPUT, you type it. ORANGE = OVERRIDE, optional; leave it blank to use the looked-up value, or type here to force your own. BLUE = LOOKUP, fetched from Rates_Master or another reference sheet. WHITE = DERIVED, calculated from the cells above it. GREEN = a subtotal to read. GOLD = the final SAY rate. The sheet is protected, so only the yellow and orange cells will let you type at all.
A8: 1. PANEL 1 - SCOPE & SPECIFICATION INPUTS (what is being built, and which clauses actually move cost)
A9: Nomenclature Clause / Dimension | B9: Selected Value | C9: Cost Impact | D9: Drives | E9: What changes when this selection changes, and the DAR 2019 evidence for it
A10: Mix / grade | B10: 1:2:4 | C10: DRIVES COST | D10: Material coeffs | E10: DAR 4.1.2 (1:1.5:3) through 4.1.8 (1:4:8) print different cement, sand and aggregate volumes for each grade, giving Say rates from about Rs 8,025 to well over Rs 10,000 per cum.
A11: Coarse aggregate nominal size | B11: 20 mm nominal size | C11: DRIVES COST | D11: Material rows 1-2 | E11: DAR 4.1.3 (20 mm) and 4.1.4 (40 mm) are the same 1:2:4 grade but use different aggregate codes and a different voids deduction, so the two print different rates.
A12: Placement location in the structure | B12: in foundation and plinth | C12: NOMENCLATURE ONLY | D12: - | E12: The DAR does not print a separate concrete rate per structural element; what changes with height is the lifting labour, which the book adds as an explicit extra Coolie line (see 4.2.5, "extra labour for lifting material upto floor V level"). Add that as a labour row rather than expecting a different base rate.
A13: Centering and shuttering | B13: excluding centering and shuttering | C13: NOMENCLATURE ONLY | D13: - | E13: Every DAR concrete and RCC item is analysed excluding the cost of centering and shuttering, which is measured under its own sub-head. There is no in-item differential.
A14: Reinforcement | B14: not applicable (plain concrete) | C14: NOMENCLATURE ONLY | D14: - | E14: RCC items in the DAR exclude reinforcement, which is measured and priced separately under Steel Work. No in-item figure exists.
A15: Finish to exposed surface | B15: no special finish | C15: USER-SUPPLIED COST | D15: Sundries row | E15: Float finish, hardener topping and similar finishes are priced in Flooring items (11.3-11.5), not inside the concrete item. If required here, enter the allowance as a Sundries line.
A16: Custom Item Code: | B16: C-04.01 | C16: Batch Output Basis: | D16: 1 | E16: Output Unit: | F16: cum | G16: Trade Sub-Head: | H16: 04 Concrete Work | I16: Output Unit Note:
A17: Assembled Item Nomenclature: | B17: =IF(I17<>"", I17, "Providing and laying in position cement concrete of grade " & B10 & ", " & B11 & ", " & B12 & ", " & B13 & ", " & B14 & ", " & B15 & ", complete as per CPWD specifications and directions of Engineer-in-charge.") -> Providing and laying in position cement concrete of grade 1:2:4, 20 mm nominal size, in foundation and plinth, excluding centering and shuttering, not applicable (plain concrete), no special finish, complete as per CPWD specifications and directions of Engineer-in-charge. | H17: Manual Override:
A18: 2. PANEL 2 - OPERATIONAL & DERIVATION DRIVERS (quantities and allowances that scale the build-up below)
A19: Driver | B19: Value | C19: Unit | D19: Applies To | E19: How this driver is used, and the DAR 2019 basis for the default
A20: Voids deduction in aggregate | B20: 0.075 | C20: fraction | D20: Aggregate coeff | E20: DAR 4.1.4 deducts 7.5% for voids inline ("0.56 - 7.5% for voids = 0.52 cum"). Adjust only with a documented reason.
A21: Extra lift labour (floor level) | B21: 0 | C21: Coolie days | D21: Labour rows | E21: The DAR adds this as its own Coolie line - 4.2.5 uses 0.75 x 2.5 = 1.88 Coolie days for lifting material up to floor V level. Enter the days here and mirror them on a Coolie row.
A22: Concrete mixer productivity | B22: 0.07 | C22: days / cum | D22: Plant row | E22: DAR 4.2.5 uses 0.07 mixer-days per cum. Plant codes 0001-0083 already include operator, fuel and lubricants for an 8-hour shift per CPWD Note 1.
A23: Vibrator productivity | B23: 0.07 | C23: days / cum | D23: Plant row | E23: DAR 4.2.5 uses 0.07 needle-vibrator days per cum on the same basis.
A24: COST-IMPACT KEY - "DRIVES COST" = the DAR 2019 prints different figures for the listed choices, and changing the selection changes a code, coefficient or imported rate on this sheet. "NOMENCLATURE ONLY" = the clause changes the wording of the item but the DAR prices one rate for every variant, so there is no differential data to apply. "USER-SUPPLIED COST" = the clause has a real cost but the DAR gives no figure for it, so enter the amount yourself (normally as a Sundries / L.S. line).
A25: AUDIT STATUS: | B25: =IF(AND(D25="OK", F25="OK", H25="OK"), "[PASS] ALL CHECKS OK", "[ALERT] CHECKS FAILED") -> [PASS] ALL CHECKS OK | C25: Output Qty Check: | D25: =IF(D16>0, "OK", "ERR: Qty<=0") -> OK | E25: Direct Cost Check: | F25: =IF(G59>0, "OK", "ERR: W<=0") -> OK | G25: Markup Flow Check: | H25: =IF(AND(G59<=G61, G61<=G63, G63<=G65, G39<=G59), "OK", "ERR: Markups Broken") -> OK | I25: =IF(G39>0, "A-rule active", "No A imports") -> No A imports
A26: 3. MATERIAL COMPONENT BUILD-UP (tag column I with "A" for any line whose rate already includes statutory markups)
A27: Line | B27: Code / Source | C27: Description / Specification | D27: Unit | E27: Quantity / Coeff | F27: Basic Rate (Rs) | G27: Amount (Rs) | H27: Source Reference / Remarks | I27: Markup Tag
A28: 1 | B28: 0295 | C28: =IF(B28="","", IFERROR(INDEX(Rates_Master!$C:$C, MATCH(B28, Rates_Master!$A:$A, 0)), "Custom / Intermediate Material")) -> Stone Aggregate (Single size) : 20 mm nominal size | D28: =IF(B28="","", IFERROR(INDEX(Rates_Master!$D:$D, MATCH(B28, Rates_Master!$A:$A, 0)), "")) -> cum | E28: 0.57 | F28: =IF(B28="","", IFERROR(INDEX(Rates_Master!$E:$E, MATCH(B28, Rates_Master!$A:$A, 0)), 0)) -> 1350 | G28: =IF(OR(B28="", E28=""), 0, ROUND(E28 * F28, 2)) -> 769.5 | H28: Stone Aggregate 20 mm nominal size
A29: 2 | B29: 0297 | C29: =IF(B29="","", IFERROR(INDEX(Rates_Master!$C:$C, MATCH(B29, Rates_Master!$A:$A, 0)), "Custom / Intermediate Material")) -> Stone Aggregate (Single size) : 10 mm nominal size | D29: =IF(B29="","", IFERROR(INDEX(Rates_Master!$D:$D, MATCH(B29, Rates_Master!$A:$A, 0)), "")) -> cum | E29: 0.28 | F29: =IF(B29="","", IFERROR(INDEX(Rates_Master!$E:$E, MATCH(B29, Rates_Master!$A:$A, 0)), 0)) -> 1350 | G29: =IF(OR(B29="", E29=""), 0, ROUND(E29 * F29, 2)) -> 378 | H29: Stone Aggregate 10 mm nominal size
A30: 3 | B30: 2202 | C30: =IF(B30="","", IFERROR(INDEX(Rates_Master!$C:$C, MATCH(B30, Rates_Master!$A:$A, 0)), "Custom / Intermediate Material")) -> Carriage of Stone aggregate below 40 mm nominal size | D30: =IF(B30="","", IFERROR(INDEX(Rates_Master!$D:$D, MATCH(B30, Rates_Master!$A:$A, 0)), "")) -> cum | E30: 0.85 | F30: =IF(B30="","", IFERROR(INDEX(Rates_Master!$E:$E, MATCH(B30, Rates_Master!$A:$A, 0)), 0)) -> 103.77 | G30: =IF(OR(B30="", E30=""), 0, ROUND(E30 * F30, 2)) -> 88.2 | H30: Carriage of Stone aggregate below 40 mm
A31: 4 | B31: 0982 | C31: =IF(B31="","", IFERROR(INDEX(Rates_Master!$C:$C, MATCH(B31, Rates_Master!$A:$A, 0)), "Custom / Intermediate Material")) -> Coarse sand (zone III) | D31: =IF(B31="","", IFERROR(INDEX(Rates_Master!$D:$D, MATCH(B31, Rates_Master!$A:$A, 0)), "")) -> cum | E31: 0.425 | F31: =IF(B31="","", IFERROR(INDEX(Rates_Master!$E:$E, MATCH(B31, Rates_Master!$A:$A, 0)), 0)) -> 1350 | G31: =IF(OR(B31="", E31=""), 0, ROUND(E31 * F31, 2)) -> 573.75 | H31: Coarse sand (zone III)
A32: 5 | B32: 2203 | C32: =IF(B32="","", IFERROR(INDEX(Rates_Master!$C:$C, MATCH(B32, Rates_Master!$A:$A, 0)), "Custom / Intermediate Material")) -> Carriage of Coarse sand | D32: =IF(B32="","", IFERROR(INDEX(Rates_Master!$D:$D, MATCH(B32, Rates_Master!$A:$A, 0)), "")) -> cum | E32: 0.425 | F32: =IF(B32="","", IFERROR(INDEX(Rates_Master!$E:$E, MATCH(B32, Rates_Master!$A:$A, 0)), 0)) -> 103.77 | G32: =IF(OR(B32="", E32=""), 0, ROUND(E32 * F32, 2)) -> 44.1 | H32: Carriage of Coarse sand
A33: 6 | B33: 0367 | C33: =IF(B33="","", IFERROR(INDEX(Rates_Master!$C:$C, MATCH(B33, Rates_Master!$A:$A, 0)), "Custom / Intermediate Material")) -> Portland Cement (OPC-43 Grade) | D33: =IF(B33="","", IFERROR(INDEX(Rates_Master!$D:$D, MATCH(B33, Rates_Master!$A:$A, 0)), "")) -> tonne | E33: 0.32 | F33: =IF(B33="","", IFERROR(INDEX(Rates_Master!$E:$E, MATCH(B33, Rates_Master!$A:$A, 0)), 0)) -> 4940 | G33: =IF(OR(B33="", E33=""), 0, ROUND(E33 * F33, 2)) -> 1580.8 | H33: Portland Cement
A34: 7 | B34: 2209 | C34: =IF(B34="","", IFERROR(INDEX(Rates_Master!$C:$C, MATCH(B34, Rates_Master!$A:$A, 0)), "Custom / Intermediate Material")) -> Carriage of Cement | D34: =IF(B34="","", IFERROR(INDEX(Rates_Master!$D:$D, MATCH(B34, Rates_Master!$A:$A, 0)), "")) -> tonne | E34: 0.32 | F34: =IF(B34="","", IFERROR(INDEX(Rates_Master!$E:$E, MATCH(B34, Rates_Master!$A:$A, 0)), 0)) -> 92.24 | G34: =IF(OR(B34="", E34=""), 0, ROUND(E34 * F34, 2)) -> 29.52 | H34: Carriage of Cement
A35: 8 | C35: =IF(B35="","", IFERROR(INDEX(Rates_Master!$C:$C, MATCH(B35, Rates_Master!$A:$A, 0)), "Custom / Intermediate Material")) | D35: =IF(B35="","", IFERROR(INDEX(Rates_Master!$D:$D, MATCH(B35, Rates_Master!$A:$A, 0)), "")) | F35: =IF(B35="","", IFERROR(INDEX(Rates_Master!$E:$E, MATCH(B35, Rates_Master!$A:$A, 0)), 0)) | G35: =IF(OR(B35="", E35=""), 0, ROUND(E35 * F35, 2)) -> 0
A36: 9 | C36: =IF(B36="","", IFERROR(INDEX(Rates_Master!$C:$C, MATCH(B36, Rates_Master!$A:$A, 0)), "Custom / Intermediate Material")) | D36: =IF(B36="","", IFERROR(INDEX(Rates_Master!$D:$D, MATCH(B36, Rates_Master!$A:$A, 0)), "")) | F36: =IF(B36="","", IFERROR(INDEX(Rates_Master!$E:$E, MATCH(B36, Rates_Master!$A:$A, 0)), 0)) | G36: =IF(OR(B36="", E36=""), 0, ROUND(E36 * F36, 2)) -> 0
A37: 10 | C37: =IF(B37="","", IFERROR(INDEX(Rates_Master!$C:$C, MATCH(B37, Rates_Master!$A:$A, 0)), "Custom / Intermediate Material")) | D37: =IF(B37="","", IFERROR(INDEX(Rates_Master!$D:$D, MATCH(B37, Rates_Master!$A:$A, 0)), "")) | F37: =IF(B37="","", IFERROR(INDEX(Rates_Master!$E:$E, MATCH(B37, Rates_Master!$A:$A, 0)), 0)) | G37: =IF(OR(B37="", E37=""), 0, ROUND(E37 * F37, 2)) -> 0
A38: Subtotal Materials (Rs): | G38: =SUM(G28:G37) -> 3463.87
A39: of which "A" - imported lines already carrying statutory markups: | G39: =ROUND(SUMIF($I$28:$I$37, "A", $G$28:$G$37), 2) -> 0 | H39: CPWD (W-A) convention: this amount stays inside W and inside every subtotal, but is subtracted from each markup BASE so an already-marked-up import is not marked up twice. Verified against DAR 2019 items 10.1, 18.78 and 18.79.
A40: 4. LABOUR & MACHINERY COMPONENT BUILD-UP (crew suggestions: see the work-type summary on Labour_Machinery_Productivity. Plant codes 0001-0083 already include operator, fuel and lubricants for an 8-hour shift per CPWD Note 1)
A41: Line | B41: Code / Source | C41: Description / Specification | D41: Unit | E41: Quantity / Coeff | F41: Basic Rate (Rs) | G41: Amount (Rs) | H41: Source Reference / Remarks | I41: Markup Tag
A42: 1 | B42: 0155 | C42: =IF(B42="","", IFERROR(INDEX(Rates_Master!$C:$C, MATCH(B42, Rates_Master!$A:$A, 0)), "Custom Labour / Plant")) -> Mason (average) | D42: =IF(B42="","", IFERROR(INDEX(Rates_Master!$D:$D, MATCH(B42, Rates_Master!$A:$A, 0)), "")) -> day | E42: 0.1 | F42: =IF(B42="","", IFERROR(INDEX(Rates_Master!$E:$E, MATCH(B42, Rates_Master!$A:$A, 0)), 0)) -> 709 | G42: =IF(OR(B42="", E42=""), 0, ROUND(E42 * F42, 2)) -> 70.9 | H42: Mason (average)
A43: 2 | B43: 0114 | C43: =IF(B43="","", IFERROR(INDEX(Rates_Master!$C:$C, MATCH(B43, Rates_Master!$A:$A, 0)), "Custom Labour / Plant")) -> Beldar | D43: =IF(B43="","", IFERROR(INDEX(Rates_Master!$D:$D, MATCH(B43, Rates_Master!$A:$A, 0)), "")) -> day | E43: 1.63 | F43: =IF(B43="","", IFERROR(INDEX(Rates_Master!$E:$E, MATCH(B43, Rates_Master!$A:$A, 0)), 0)) -> 558 | G43: =IF(OR(B43="", E43=""), 0, ROUND(E43 * F43, 2)) -> 909.54 | H43: Beldar (carrying & placing)
A44: 3 | B44: 0101 | C44: =IF(B44="","", IFERROR(INDEX(Rates_Master!$C:$C, MATCH(B44, Rates_Master!$A:$A, 0)), "Custom Labour / Plant")) -> Bhisti | D44: =IF(B44="","", IFERROR(INDEX(Rates_Master!$D:$D, MATCH(B44, Rates_Master!$A:$A, 0)), "")) -> day | E44: 0.7 | F44: =IF(B44="","", IFERROR(INDEX(Rates_Master!$E:$E, MATCH(B44, Rates_Master!$A:$A, 0)), 0)) -> 617 | G44: =IF(OR(B44="", E44=""), 0, ROUND(E44 * F44, 2)) -> 431.9 | H44: Bhisti (curing)
A45: 4 | B45: 0002 | C45: =IF(B45="","", IFERROR(INDEX(Rates_Master!$C:$C, MATCH(B45, Rates_Master!$A:$A, 0)), "Custom Labour / Plant")) -> Hire charges of Concrete Mixer 0.25 to 0.40 cum with Hopper | D45: =IF(B45="","", IFERROR(INDEX(Rates_Master!$D:$D, MATCH(B45, Rates_Master!$A:$A, 0)), "")) -> day | E45: 0.07 | F45: =IF(B45="","", IFERROR(INDEX(Rates_Master!$E:$E, MATCH(B45, Rates_Master!$A:$A, 0)), 0)) -> 800 | G45: =IF(OR(B45="", E45=""), 0, ROUND(E45 * F45, 2)) -> 56 | H45: Hire charges of Concrete Mixer with hopper
A46: 5 | B46: 0012 | C46: =IF(B46="","", IFERROR(INDEX(Rates_Master!$C:$C, MATCH(B46, Rates_Master!$A:$A, 0)), "Custom Labour / Plant")) -> Vibrator (Needle type 40 mm) | D46: =IF(B46="","", IFERROR(INDEX(Rates_Master!$D:$D, MATCH(B46, Rates_Master!$A:$A, 0)), "")) -> day | E46: 0.07 | F46: =IF(B46="","", IFERROR(INDEX(Rates_Master!$E:$E, MATCH(B46, Rates_Master!$A:$A, 0)), 0)) -> 370 | G46: =IF(OR(B46="", E46=""), 0, ROUND(E46 * F46, 2)) -> 25.9 | H46: Vibrator (Needle type 40mm)
A47: 6 | C47: =IF(B47="","", IFERROR(INDEX(Rates_Master!$C:$C, MATCH(B47, Rates_Master!$A:$A, 0)), "Custom Labour / Plant")) | D47: =IF(B47="","", IFERROR(INDEX(Rates_Master!$D:$D, MATCH(B47, Rates_Master!$A:$A, 0)), "")) | F47: =IF(B47="","", IFERROR(INDEX(Rates_Master!$E:$E, MATCH(B47, Rates_Master!$A:$A, 0)), 0)) | G47: =IF(OR(B47="", E47=""), 0, ROUND(E47 * F47, 2)) -> 0
A48: 7 | C48: =IF(B48="","", IFERROR(INDEX(Rates_Master!$C:$C, MATCH(B48, Rates_Master!$A:$A, 0)), "Custom Labour / Plant")) | D48: =IF(B48="","", IFERROR(INDEX(Rates_Master!$D:$D, MATCH(B48, Rates_Master!$A:$A, 0)), "")) | F48: =IF(B48="","", IFERROR(INDEX(Rates_Master!$E:$E, MATCH(B48, Rates_Master!$A:$A, 0)), 0)) | G48: =IF(OR(B48="", E48=""), 0, ROUND(E48 * F48, 2)) -> 0
A49: 8 | C49: =IF(B49="","", IFERROR(INDEX(Rates_Master!$C:$C, MATCH(B49, Rates_Master!$A:$A, 0)), "Custom Labour / Plant")) | D49: =IF(B49="","", IFERROR(INDEX(Rates_Master!$D:$D, MATCH(B49, Rates_Master!$A:$A, 0)), "")) | F49: =IF(B49="","", IFERROR(INDEX(Rates_Master!$E:$E, MATCH(B49, Rates_Master!$A:$A, 0)), 0)) | G49: =IF(OR(B49="", E49=""), 0, ROUND(E49 * F49, 2)) -> 0
A50: 9 | C50: =IF(B50="","", IFERROR(INDEX(Rates_Master!$C:$C, MATCH(B50, Rates_Master!$A:$A, 0)), "Custom Labour / Plant")) | D50: =IF(B50="","", IFERROR(INDEX(Rates_Master!$D:$D, MATCH(B50, Rates_Master!$A:$A, 0)), "")) | F50: =IF(B50="","", IFERROR(INDEX(Rates_Master!$E:$E, MATCH(B50, Rates_Master!$A:$A, 0)), 0)) | G50: =IF(OR(B50="", E50=""), 0, ROUND(E50 * F50, 2)) -> 0
A51: 10 | C51: =IF(B51="","", IFERROR(INDEX(Rates_Master!$C:$C, MATCH(B51, Rates_Master!$A:$A, 0)), "Custom Labour / Plant")) | D51: =IF(B51="","", IFERROR(INDEX(Rates_Master!$D:$D, MATCH(B51, Rates_Master!$A:$A, 0)), "")) | F51: =IF(B51="","", IFERROR(INDEX(Rates_Master!$E:$E, MATCH(B51, Rates_Master!$A:$A, 0)), 0)) | G51: =IF(OR(B51="", E51=""), 0, ROUND(E51 * F51, 2)) -> 0
A52: Subtotal Labour & Plant Hire (Rs): | G52: =SUM(G42:G51) -> 1494.24
A54: 5. SUNDRIES & LUMP-SUM ALLOWANCES (manual entry - the DAR gives no reproducible formula; use Sundries_Reference to find a comparable item)
A55: 1 | B55: 9999 | C55: Sundries (guided by Sundries_Reference sheet) | D55: L.S. | E55: 14.3 | F55: =Factor_Sundries -> 2 | G55: =ROUND(E55 * F55, 2) -> 28.6 | H55: Base L.S. allowance x Cost Index Multiplier (2.00) from Global_Factors
A57: 6. STATUTORY MARKUPS & FINAL RATE DERIVATION (CPWD DAR METHOD, WITH THE (W-A) EXCLUSION)
A58: Step | B58: Component / Markup Description | C58: Apply? (YES/NO) | D58: Basis Applied | E58: Base Amount (Rs) | F58: Factor / % | G58: Amount (Rs) | H58: CPWD Statutory Rule & Guidance Note | I58: A-Rule
A59: W | B59: Base Direct Production Cost (Materials + Labour + Sundries) | C59: - | D59: Direct Sum | E59: - | F59: - | G59: =G38 + G52 + G55 -> 4986.71 | H59: Total direct cost of production (W), A-tagged imports included, exactly as the book totals it. | I59: includes A
A60: X1 | B60: Add Water Charges | C60: YES | D60: On (W - A) | E60: =G59 - G39 -> 4986.71 | F60: =Factor_Water -> 0.01 | G60: =IF(C60="YES", ROUND(E60 * F60, 2), 0) -> 49.87 | H60: CPWD Standard: 1% for curing & concrete water. | I60: net of A
A61: X | B61: Subtotal "X" (W + Water Charges) | C61: - | D61: W + Water | E61: - | F61: - | G61: =G59 + G60 -> 5036.58 | H61: Compounded base for GST calculation | I61: includes A
A62: Y1 | B62: Add GST on Works Contract | C62: YES | D62: On (X - A) | E62: =G61 - G39 -> 5036.58 | F62: =Factor_GST -> 0.1405 | G62: =IF(C62="YES", ROUND(E62 * F62, 2), 0) -> 707.64 | H62: CPWD DAR factor 0.1405 (works contract tax). | I62: net of A
A63: Y | B63: Subtotal "Y" (X + GST) | C63: - | D63: X + GST | E63: - | F63: - | G63: =G61 + G62 -> 5744.22 | H63: Compounded base for Contractor Profit & Overheads | I63: includes A
A64: Z1 | B64: Add Contractor Profit & Overheads (15% CPOH) | C64: YES | D64: On (Y - A) | E64: =G63 - G39 -> 5744.22 | F64: =Factor_CPOH -> 0.15 | G64: =IF(C64="YES", ROUND(E64 * F64, 2), 0) -> 861.63 | H64: Standard 15% Contractor Profit & Overheads. | I64: net of A
A65: Z | B65: Subtotal "Z" (Y + CPOH) | C65: - | D65: Y + CPOH | E65: - | F65: - | G65: =G63 + G64 -> 6605.85 | H65: Compounded base for Labour Welfare Cess | I65: includes A
A66: Z2 | B66: Add Labour Welfare Cess (1% BOCW Cess) | C66: YES | D66: On (Z - A) | E66: =G65 - G39 -> 6605.85 | F66: =Factor_Cess -> 0.01 | G66: =IF(C66="YES", ROUND(E66 * F66, 2), 0) -> 66.06 | H66: Statutory 1% BOCW Welfare Cess. | I66: net of A
A67: Cost | B67: ="Total Cost of Batch (" & TEXT(D16, "0.00") & " " & F16 & "):" -> Total Cost of Batch (1.00 cum): | C67: - | D67: Z + Cess | E67: - | F67: - | G67: =G65 + G66 -> 6671.91 | H67: Total evaluated cost for the batch size in the Panel 1 header row | I67: -
A68: Rate | B68: ="Analyzed Unit Rate per 1.00 " & F16 & ":" -> Analyzed Unit Rate per 1.00 cum: | C68: - | D68: Cost / Batch Qty | E68: - | F68: - | G68: =ROUND(G67 / D16, 2) -> 6671.91 | H68: Calculated cost per standard unit of measurement | I68: -
A69: SAY | B69: ="OFFICIAL SAY RATE (Rs per " & F16 & "):" -> OFFICIAL SAY RATE (Rs per cum): | C69: - | D69: MROUND to Rs 0.05 | E69: - | F69: - | G69: =MROUND(G68, 0.05) -> 6671.9 | H69: OFFICIAL CPWD ROUNDED RATE FOR TENDER SCHEDULES & ESTIMATES. CPWD quotes Say rates to the nearest 5 paise - see the note directly below this row. | I69: -
A70: WHY THE SAY RATE IS ROUNDED TO 5 PAISE: CPWD DAR 2019 quotes every "Say" rate to the nearest Rs 0.05, not to two decimals - e.g. item 1.3 computes 104.89 and is printed as 104.90; item 1.4.1 computes 155.47 and is printed as 155.45; item 10.1 computes 86.04 and is printed as 86.05. This sheet therefore uses MROUND(rate, 0.05) so the analysed rate matches the book exactly instead of sitting a paisa away from it. Change the 0.05 only if your circle office issues a different rounding rule.
A72: 7. RUNNING CUSTOM NON-DSR ITEMS LIBRARY FOR THIS TRADE
A73: Log all completed custom rate analyses for this trade below. Items logged here maintain an internal project audit trail and can be referenced from other builder sheets.
A74: Item Code | B74: Item Nomenclature / Specification | C74: Unit | D74: Output Basis | E74: Direct Cost W (Rs) | F74: Markups Applied | G74: Unit Rate (Rs) | H74: Say Rate (Rs) | I74: A-Total (Rs)
