Workbook

Sheet Rates_Master
A1: Code | B1: Category | C1: Description | D1: Unit | E1: Basic Rate (Rs)
A2: 0114 | B2: Labour | C2: Beldar | D2: day | E2: 558
A3: 0115 | B3: Labour | C3: Coolie | D3: day | E3: 558
A4: 0101 | B4: Labour | C4: Bhisti | D4: day | E4: 617
A5: 0113 | B5: Sundries | C5: Chowkidar | D5: day | E5: 558
A6: 0003 | B6: Plant | C6: Hire charges of Diesel Road Roller | D6: day | E6: 3000
A7: 9999 | B7: Sundries | C7: Sundries | D7: L.S. | E7: 2

Sheet Global_Factors
A1: GF_1 | B1: desc | C1: 0.01 | D1: unit | E1: 0.01 | F1: 0.01
A2: GF_2 | B2: desc | C2: 0.01 | D2: unit | E2: 0.01 | F2: 0.01
A3: GF_3 | B3: desc | C3: 0.01 | D3: unit | E3: 0.01 | F3: 0.01
A4: GF_4 | B4: desc | C4: 0.01 | D4: unit | E4: 0.01 | F4: 0.01
A5: GF_5 | B5: desc | C5: 0.01 | D5: unit | E5: 0.01 | F5: 0.01
A6: GF_6 | B6: desc | C6: 0.01 | D6: unit | E6: 0.01 | F6: 0.01
A7: GF_7 | B7: desc | C7: 0.01 | D7: unit | E7: 0.01 | F7: 0.01
A8: GF_8 | B8: desc | C8: 0.01 | D8: unit | E8: 0.01 | F8: 0.01
A9: GF_9 | B9: desc | C9: 0.01 | D9: unit | E9: 0.01 | F9: 0.01
A10: GF_10 | B10: desc | C10: 0.01 | D10: unit | E10: 0.01 | F10: 0.01
A11: GF_11 | B11: desc | C11: 0.01 | D11: unit | E11: 0.01 | F11: 0.01
A12: GF_12 | B12: desc | C12: 0.01 | D12: unit | E12: 0.01 | F12: 0.01
... A19: GF_19 | B19: desc | C19: 0.01 | D19: unit | E19: 0.01 | F19: 0.01

Sheet 02_Earth_Work
A1: CPWD DAR 2019 — SUB-HEAD 02: EARTH WORK (CUSTOM ITEM BUILDER)
A2: LEGEND: | B2: INPUT - you type it | C2: OVERRIDE - optional | D2: LOOKUP - fetched | E2: DERIVED - calculated | F2: RESULT - subtotal | G2: SAY - final rate | H2: CPWD rule / note | I2: Not editable
A3: CPWD DAR Sub-head 02: Earthwork operations (surface excavation, trench excavation, filling, compaction). Operates without raw material inputs, applying labour crews and earthmoving machinery hire with standard 5-step compounding statutory markups.
A4: 1. RATE ANALYSIS CONFIGURATION & OPERATIONAL PROFILE (Select parameters in D6, D7, D8, D9 to drive rate analysis)
A5: Parameter | D5: Selected Value / Parameter Input | E5: Unit | F5: Cell Role | G5: CPWD DAR 2019 Engineering Specification & Practical Field Guidance Notes
A6: Primary Work Scope | D6: Surface Excavation (≤30 cm) | E6: — | F6: INPUT | G6: Core civil work category: Surface excavation, Foundation/trenching, Embankment, Backfilling, Site clearance, Timbering, or Anti-termite.
A7: Ground Strata / Material | D7: All kinds of soil | E7: — | F7: INPUT | G7: Strata classification: All kinds of soil, Ordinary rock, Hard rock (blasting permitted), or Hard rock (blasting prohibited).
A8: Execution Method & Depth Condition | D8: Manual labor (depth ≤1.5m) | E8: — | F8: INPUT | G8: Execution technique: Manual labor (≤1.5m), Mechanical (Hydraulic Excavator 0.9 cum), Extra depth 1.5-3.0m, or Extra depth 3.0-4.5m.
A9: Operation / Task Specification | D9: General surface cut (≤30 cm deep) | E9: — | F9: INPUT | G9: Specific activity variant or application subtype (e.g. open areas, pipe trenches, post holes, tree girth band, chemical barrier stage).
A10: Standard Output Batch Quantity | D10: 1 | E10: units | F10: LOOKUP | G10: Standard output batch volume or area defined in CPWD DAR 2019 (100 sqm, 10 cum, 1 m, 1 tree, 10 holes).
A11: Standard Output Measurement Unit | D11: 1 | E11: — | F11: LOOKUP | G11: Billing measurement unit for work output (cum, sqm, metre, tree, hole).
A12: Custom Project Rate Reference Code | D12: C-02.01 | E12: — | F12: INPUT | G12: Project-specific non-DSR reference code when saving custom rate variations.
A13: Official Work Specification Nomenclature: | D13: 1
A14: Published Reference Say Rate (Benchmark) | D14: 1 | E14: 1 | F14: LOOKUP | G14: Official CPWD DAR 2019 Volume 1 published rate for identical scope and strata.
A15: AUDIT VERIFICATION STATUS: | D15: 1 | E15: Cost Base: | F15: 1 | G15: Live variance check against published CPWD DAR 2019 Volume 1 Say Rate. Target variance: ₹ 0.00.
A17: 1B. PARAMETRIC OPERATIONAL SPECIFICATION PROFILE (5 CORE CIVIL WORK LEVERS)
A18: Operational Work Lever | D18: Active Execution Mechanism / Field Technique | E18: CPWD Standard Field Specification & Practical Engineering Scope Notes
A19: 1. Loosening / Digging Mode | D19: 1 | E19: Loosening of soil/rock crust to required formation level or trench invert.
A20: 2. Handling & Haulage Boundary | D20: 1 | E20: Haulage boundary: lead up to 50 m and lift up to 1.5 m from excavation face.
A21: 3. Layer Placement & Spreading | D21: 1 | E21: Depositing excavated earth in uniform layers ≤20 cm depth, breaking clods and shaping slopes.
A22: 4. Compaction Watering to OMC | D22: YES | E22: 1
A23: 5. Compaction Mechanism | D23: YES | E23: 1
A25: 2. ACTIVE RESOURCE BUILD-UP (Auto-populated from Table 5E Ground-Truth Norms; Equipment codes include fuel & crew)
A26: Line | B26: Resource Code | C26: Resource Name & Description | D26: Resource Category | E26: Unit | F26: Norm Input Qty | G26: Unit Rate (₹) | H26: Line Amount (₹) | I26: Include? / Apply | J26: Cost Share % | K26: Daily Productivity Norm | L26: Specific Effort | M26: Hourly Pace | N26: Field Guidance Note | O26: Engineering First-Principles & 8-Hour Shift Logic
A27: 1 | B27: =IFERROR(INDEX($G$105:$G$282, MATCH($D$6&"|"&$D$7&"|"&$D$8&"|"&$D$9&"|"&1, $P$105:$P$282, 0)), "") | C27: =IF(B27="","", IFERROR(INDEX(Rates_Master!$C:$C, MATCH(B27, Rates_Master!$A:$A, 0)), IFERROR(INDEX($H$105:$H$282, MATCH($D$6&"|"&$D$7&"|"&$D$8&"|"&$D$9&"|"&1, $P$105:$P$282, 0)), "Custom Resource"))) | D27: =IF(B27="","", IFERROR(INDEX(Rates_Master!$B:$B, MATCH(B27, Rates_Master!$A:$A, 0)), "Labour")) | E27: =IF(B27="","", IFERROR(INDEX(Rates_Master!$D:$D, MATCH(B27, Rates_Master!$A:$A, 0)), "day")) | F27: =IF(B27="","", IF(B27="0101", IF($D$22="NO", 0, IF(AND(ISNUMBER(K27), K27>0), ROUND(D$10/K27, 5), IFERROR(INDEX($I$105:$I$282, MATCH($D$6&"|"&$D$7&"|"&$D$8&"|"&$D$9&"|"&1, $P$105:$P$282, 0)), 0))), IF(OR(B27="0003", B27="0011", B27="0113"), IF($D$23="NO", 0, IF(AND(ISNUMBER(K27), K27>0), ROUND(D$10/K27, 5), IFERROR(INDEX($I$105:$I$282, MATCH($D$6&"|"&$D$7&"|"&$D$8&"|"&$D$9&"|"&1, $P$105:$P$282, 0)), 0))), IF(AND(ISNUMBER(K27), K27>0), ROUND(D$10/K27, 5), IFERROR(INDEX($I$105:$I$282, MATCH($D$6&"|"&$D$7&"|"&$D$8&"|"&$D$9&"|"&1, $P$105:$P$282, 0)), 0))))) | G27: =IF(B27="","", IFERROR(INDEX(Rates_Master!$E:$E, MATCH(B27, Rates_Master!$A:$A, 0)), IFERROR(INDEX($K$105:$K$282, MATCH($D$6&"|"&$D$7&"|"&$D$8&"|"&$D$9&"|"&1, $P$105:$P$282, 0)), 0))) | H27: =IF(OR(B27="", F27=""), 0, ROUND(F27 * G27, 2)) | I27: =IF(B27="","", IF(ISNUMBER(SEARCH("2.10", B27)), "A", "W")) | J27: =IF(H$41>0, ROUND(H27 / H$41 * 100, 1), 0) | K27: =IFERROR(INDEX($N$105:$N$282, MATCH($D$6&"|"&$D$7&"|"&$D$8&"|"&$D$9&"|"&1, $P$105:$P$282, 0)), "") | L27: =IF(AND(ISNUMBER(F27), F27>0, D$10>0), ROUND(F27 * 8 / D$10, 4), "") | M27: =IF(AND(ISNUMBER(F27), F27>0, D$10>0), ROUND(D$10 / (F27 * 8), 2), "") | N27: =IF(B27="","", "CPWD Standard Earthwork Production Resource") | O27: =IF(B27="","", IF(B27="0101", IF($D$22="NO", "OMITTED DEDUCTION (DAR Item 2.5): 0.40 Bhishti-day @ Rs 617 = Rs 246.80 direct. Compounded with GST 14.05% (Rs 34.68) + CPOH 15% (Rs 42.22) + Cess 1% (Rs 3.24) = Rs 326.94/10 cum -> -Rs 33.00/cum deduction.", "Watering by Bhishti to OMC: 25 cum/8-hr day (0.40 day/10 cum)."), IF(OR(B27="0003", B27="0011", B27="0113"), IF($D$23="NO", "OMITTED DEDUCTION (DAR Item 2.4): 0.008 Roller @ Rs 3000 (Rs 24.00) + 0.008 Chowkidar (Rs 4.46) + Sundries (Rs 3.64) = Rs 32.10 direct. Compounded with Water 1% (Rs 0.32) + GST 14.05% (Rs 4.55) + CPOH 15% (Rs 5.55) + Cess 1% (Rs 0.43) = Rs 42.95/10 cum -> -Rs 4.30/cum deduction.", "Power roller compaction: 1250 cum/8-hr day (0.008 day/10 cum)."), IFERROR(INDEX($O$105:$O$282, MATCH($D$6&"|"&$D$7&"|"&$D$8&"|"&$D$9&"|"&1, $P$105:$P$282, 0)), ""))))
A28: 2 | B28: =IFERROR(INDEX($G$105:$G$282, MATCH($D$6&"|"&$D$7&"|"&$D$8&"|"&$D$9&"|"&2, $P$105:$P$282, 0)), "") | C28: =IF(B28="","", IFERROR(INDEX(Rates_Master!$C:$C, MATCH(B28, Rates_Master!$A:$A, 0)), IFERROR(INDEX($H$105:$H$282, MATCH($D$6&"|"&$D$7&"|"&$D$8&"|"&$D$9&"|"&2, $P$105:$P$282, 0)), "Custom Resource"))) | D28: =IF(B28="","", IFERROR(INDEX(Rates_Master!$B:$B, MATCH(B28, Rates_Master!$A:$A, 0)), "Labour")) | E28: =IF(B28="","", IFERROR(INDEX(Rates_Master!$D:$D, MATCH(B28, Rates_Master!$A:$A, 0)), "day")) | F28: =IF(B28="","", IF(B28="0101", IF($D$22="NO", 0, IF(AND(ISNUMBER(K28), K28>0), ROUND(D$10/K28, 5), IFERROR(INDEX($I$105:$I$282, MATCH($D$6&"|"&$D$7&"|"&$D$8&"|"&$D$9&"|"&2, $P$105:$P$282, 0)), 0))), IF(OR(B28="0003", B28="0011", B28="0113"), IF($D$23="NO", 0, IF(AND(ISNUMBER(K28), K28>0), ROUND(D$10/K28, 5), IFERROR(INDEX($I$105:$I$282, MATCH($D$6&"|"&$D$7&"|"&$D$8&"|"&$D$9&"|"&2, $P$105:$P$282, 0)), 0))), IF(AND(ISNUMBER(K28), K28>0), ROUND(D$10/K28, 5), IFERROR(INDEX($I$105:$I$282, MATCH($D$6&"|"&$D$7&"|"&$D$8&"|"&$D$9&"|"&2, $P$105:$P$282, 0)), 0))))) | G28: =IF(B28="","", IFERROR(INDEX(Rates_Master!$E:$E, MATCH(B28, Rates_Master!$A:$A, 0)), IFERROR(INDEX($K$105:$K$282, MATCH($D$6&"|"&$D$7&"|"&$D$8&"|"&$D$9&"|"&2, $P$105:$P$282, 0)), 0))) | H28: =IF(OR(B28="", F28=""), 0, ROUND(F28 * G28, 2)) | I28: =IF(B28="","", IF(ISNUMBER(SEARCH("2.10", B28)), "A", "W")) | J28: =IF(H$41>0, ROUND(H28 / H$41 * 100, 1), 0) | K28: =IFERROR(INDEX($N$105:$N$282, MATCH($D$6&"|"&$D$7&"|"&$D$8&"|"&$D$9&"|"&2, $P$105:$P$282, 0)), "") | L28: =IF(AND(ISNUMBER(F28), F28>0, D$10>0), ROUND(F28 * 8 / D$10, 4), "") | M28: =IF(AND(ISNUMBER(F28), F28>0, D$10>0), ROUND(D$10 / (F28 * 8), 2), "") | N28: =IF(B28="","", "CPWD Standard Earthwork Production Resource") | O28: =IF(B28="","", IF(B28="0101", IF($D$22="NO", "OMITTED DEDUCTION (DAR Item 2.5): 0.40 Bhishti-day @ Rs 617 = Rs 246.80 direct. Compounded with GST 14.05% (Rs 34.68) + CPOH 15% (Rs 42.22) + Cess 1% (Rs 3.24) = Rs 326.94/10 cum -> -Rs 33.00/cum deduction.", "Watering by Bhishti to OMC: 25 cum/8-hr day (0.40 day/10 cum)."), IF(OR(B28="0003", B28="0011", B28="0113"), IF($D$23="NO", "OMITTED DEDUCTION (DAR Item 2.4): 0.008 Roller @ Rs 3000 (Rs 24.00) + 0.008 Chowkidar (Rs 4.46) + Sundries (Rs 3.64) = Rs 32.10 direct. Compounded with Water 1% (Rs 0.32) + GST 14.05% (Rs 4.55) + CPOH 15% (Rs 5.55) + Cess 1% (Rs 0.43) = Rs 42.95/10 cum -> -Rs 4.30/cum deduction.", "Power roller compaction: 1250 cum/8-hr day (0.008 day/10 cum)."), IFERROR(INDEX($O$105:$O$282, MATCH($D$6&"|"&$D$7&"|"&$D$8&"|"&$D$9&"|"&2, $P$105:$P$282, 0)), ""))))
A29: 3 | B29: =IFERROR(INDEX($G$105:$G$282, MATCH($D$6&"|"&$D$7&"|"&$D$8&"|"&$D$9&"|"&3, $P$105:$P$282, 0)), "") | C29: =IF(B29="","", IFERROR(INDEX(Rates_Master!$C:$C, MATCH(B29, Rates_Master!$A:$A, 0)), IFERROR(INDEX($H$105:$H$282, MATCH($D$6&"|"&$D$7&"|"&$D$8&"|"&$D$9&"|"&3, $P$105:$P$282, 0)), "Custom Resource"))) | D29: =IF(B29="","", IFERROR(INDEX(Rates_Master!$B:$B, MATCH(B29, Rates_Master!$A:$A, 0)), "Labour")) | E29: =IF(B29="","", IFERROR(INDEX(Rates_Master!$D:$D, MATCH(B29, Rates_Master!$A:$A, 0)), "day")) | F29: =IF(B29="","", IF(B29="0101", IF($D$22="NO", 0, IF(AND(ISNUMBER(K29), K29>0), ROUND(D$10/K29, 5), IFERROR(INDEX($I$105:$I$282, MATCH($D$6&"|"&$D$7&"|"&$D$8&"|"&$D$9&"|"&3, $P$105:$P$282, 0)), 0))), IF(OR(B29="0003", B29="0011", B29="0113"), IF($D$23="NO", 0, IF(AND(ISNUMBER(K29), K29>0), ROUND(D$10/K29, 5), IFERROR(INDEX($I$105:$I$282, MATCH($D$6&"|"&$D$7&"|"&$D$8&"|"&$D$9&"|"&3, $P$105:$P$282, 0)), 0))), IF(AND(ISNUMBER(K29), K29>0), ROUND(D$10/K29, 5), IFERROR(INDEX($I$105:$I$282, MATCH($D$6&"|"&$D$7&"|"&$D$8&"|"&$D$9&"|"&3, $P$105:$P$282, 0)), 0))))) | G29: =IF(B29="","", IFERROR(INDEX(Rates_Master!$E:$E, MATCH(B29, Rates_Master!$A:$A, 0)), IFERROR(INDEX($K$105:$K$282, MATCH($D$6&"|"&$D$7&"|"&$D$8&"|"&$D$9&"|"&3, $P$105:$P$282, 0)), 0))) | H29: =IF(OR(B29="", F29=""), 0, ROUND(F29 * G29, 2)) | I29: =IF(B29="","", IF(ISNUMBER(SEARCH("2.10", B29)), "A", "W")) | J29: =IF(H$41>0, ROUND(H29 / H$41 * 100, 1), 0) | K29: =IFERROR(INDEX($N$105:$N$282, MATCH($D$6&"|"&$D$7&"|"&$D$8&"|"&$D$9&"|"&3, $P$105:$P$282, 0)), "") | L29: =IF(AND(ISNUMBER(F29), F29>0, D$10>0), ROUND(F29 * 8 / D$10, 4), "") | M29: =IF(AND(ISNUMBER(F29), F29>0, D$10>0), ROUND(D$10 / (F29 * 8), 2), "") | N29: =IF(B29="","", "CPWD Standard Earthwork Production Resource") | O29: =IF(B29="","", IF(B29="0101", IF($D$22="NO", "OMITTED DEDUCTION (DAR Item 2.5): 0.40 Bhishti-day @ Rs 617 = Rs 246.80 direct. Compounded with GST 14.05% (Rs 34.68) + CPOH 15% (Rs 42.22) + Cess 1% (Rs 3.24) = Rs 326.94/10 cum -> -Rs 33.00/cum deduction.", "Watering by Bhishti to OMC: 25 cum/8-hr day (0.40 day/10 cum)."), IF(OR(B29="0003", B29="0011", B29="0113"), IF($D$23="NO", "OMITTED DEDUCTION (DAR Item 2.4): 0.008 Roller @ Rs 3000 (Rs 24.00) + 0.008 Chowkidar (Rs 4.46) + Sundries (Rs 3.64) = Rs 32.10 direct. Compounded with Water 1% (Rs 0.32) + GST 14.05% (Rs 4.55) + CPOH 15% (Rs 5.55) + Cess 1% (Rs 0.43) = Rs 42.95/10 cum -> -Rs 4.30/cum deduction.", "Power roller compaction: 1250 cum/8-hr day (0.008 day/10 cum)."), IFERROR(INDEX($O$105:$O$282, MATCH($D$6&"|"&$D$7&"|"&$D$8&"|"&$D$9&"|"&3, $P$105:$P$282, 0)), ""))))
A30: 4 | B30: =IFERROR(INDEX($G$105:$G$282, MATCH($D$6&"|"&$D$7&"|"&$D$8&"|"&$D$9&"|"&4, $P$105:$P$282, 0)), "") | C30: =IF(B30="","", IFERROR(INDEX(Rates_Master!$C:$C, MATCH(B30, Rates_Master!$A:$A, 0)), IFERROR(INDEX($H$105:$H$282, MATCH($D$6&"|"&$D$7&"|"&$D$8&"|"&$D$9&"|"&4, $P$105:$P$282, 0)), "Custom Resource"))) | D30: =IF(B30="","", IFERROR(INDEX(Rates_Master!$B:$B, MATCH(B30, Rates_Master!$A:$A, 0)), "Labour")) | E30: =IF(B30="","", IFERROR(INDEX(Rates_Master!$D:$D, MATCH(B30, Rates_Master!$A:$A, 0)), "day")) | F30: =IF(B30="","", IF(B30="0101", IF($D$22="NO", 0, IF(AND(ISNUMBER(K30), K30>0), ROUND(D$10/K30, 5), IFERROR(INDEX($I$105:$I$282, MATCH($D$6&"|"&$D$7&"|"&$D$8&"|"&$D$9&"|"&4, $P$105:$P$282, 0)), 0))), IF(OR(B30="0003", B30="0011", B30="0113"), IF($D$23="NO", 0, IF(AND(ISNUMBER(K30), K30>0), ROUND(D$10/K30, 5), IFERROR(INDEX($I$105:$I$282, MATCH($D$6&"|"&$D$7&"|"&$D$8&"|"&$D$9&"|"&4, $P$105:$P$282, 0)), 0))), IF(AND(ISNUMBER(K30), K30>0), ROUND(D$10/K30, 5), IFERROR(INDEX($I$105:$I$282, MATCH($D$6&"|"&$D$7&"|"&$D$8&"|"&$D$9&"|"&4, $P$105:$P$282, 0)), 0))))) | G30: =IF(B30="","", IFERROR(INDEX(Rates_Master!$E:$E, MATCH(B30, Rates_Master!$A:$A, 0)), IFERROR(INDEX($K$105:$K$282, MATCH($D$6&"|"&$D$7&"|"&$D$8&"|"&$D$9&"|"&4, $P$105:$P$282, 0)), 0))) | H30: =IF(OR(B30="", F30=""), 0, ROUND(F30 * G30, 2)) | I30: =IF(B30="","", IF(ISNUMBER(SEARCH("2.10", B30)), "A", "W")) | J30: =IF(H$41>0, ROUND(H30 / H$41 * 100, 1), 0) | K30: =IFERROR(INDEX($N$105:$N$282, MATCH($D$6&"|"&$D$7&"|"&$D$8&"|"&$D$9&"|"&4, $P$105:$P$282, 0)), "") | L30: =IF(AND(ISNUMBER(F30), F30>0, D$10>0), ROUND(F30 * 8 / D$10, 4), "") | M30: =IF(AND(ISNUMBER(F30), F30>0, D$10>0), ROUND(D$10 / (F30 * 8), 2), "") | N30: =IF(B30="","", "CPWD Standard Earthwork Production Resource") | O30: =IF(B30="","", IF(B30="0101", IF($D$22="NO", "OMITTED DEDUCTION (DAR Item 2.5): 0.40 Bhishti-day @ Rs 617 = Rs 246.80 direct. Compounded with GST 14.05% (Rs 34.68) + CPOH 15% (Rs 42.22) + Cess 1% (Rs 3.24) = Rs 326.94/10 cum -> -Rs 33.00/cum deduction.", "Watering by Bhishti to OMC: 25 cum/8-hr day (0.40 day/10 cum)."), IF(OR(B30="0003", B30="0011", B30="0113"), IF($D$23="NO", "OMITTED DEDUCTION (DAR Item 2.4): 0.008 Roller @ Rs 3000 (Rs 24.00) + 0.008 Chowkidar (Rs 4.46) + Sundries (Rs 3.64) = Rs 32.10 direct. Compounded with Water 1% (Rs 0.32) + GST 14.05% (Rs 4.55) + CPOH 15% (Rs 5.55) + Cess 1% (Rs 0.43) = Rs 42.95/10 cum -> -Rs 4.30/cum deduction.", "Power roller compaction: 1250 cum/8-hr day (0.008 day/10 cum)."), IFERROR(INDEX($O$105:$O$282, MATCH($D$6&"|"&$D$7&"|"&$D$8&"|"&$D$9&"|"&4, $P$105:$P$282, 0)), ""))))
A31: 5 | B31: =IFERROR(INDEX($G$105:$G$282, MATCH($D$6&"|"&$D$7&"|"&$D$8&"|"&$D$9&"|"&5, $P$105:$P$282, 0)), "") | C31: =IF(B31="","", IFERROR(INDEX(Rates_Master!$C:$C, MATCH(B31, Rates_Master!$A:$A, 0)), IFERROR(INDEX($H$105:$H$282, MATCH($D$6&"|"&$D$7&"|"&$D$8&"|"&$D$9&"|"&5, $P$105:$P$282, 0)), "Custom Resource"))) | D31: =IF(B31="","", IFERROR(INDEX(Rates_Master!$B:$B, MATCH(B31, Rates_Master!$A:$A, 0)), "Labour")) | E31: =IF(B31="","", IFERROR(INDEX(Rates_Master!$D:$D, MATCH(B31, Rates_Master!$A:$A, 0)), "day")) | F31: =IF(B31="","", IF(B31="0101", IF($D$22="NO", 0, IF(AND(ISNUMBER(K31), K31>0), ROUND(D$10/K31, 5), IFERROR(INDEX($I$105:$I$282, MATCH($D$6&"|"&$D$7&"|"&$D$8&"|"&$D$9&"|"&5, $P$105:$P$282, 0)), 0))), IF(OR(B31="0003", B31="0011", B31="0113"), IF($D$23="NO", 0, IF(AND(ISNUMBER(K31), K31>0), ROUND(D$10/K31, 5), IFERROR(INDEX($I$105:$I$282, MATCH($D$6&"|"&$D$7&"|"&$D$8&"|"&$D$9&"|"&5, $P$105:$P$282, 0)), 0))), IF(AND(ISNUMBER(K31), K31>0), ROUND(D$10/K31, 5), IFERROR(INDEX($I$105:$I$282, MATCH($D$6&"|"&$D$7&"|"&$D$8&"|"&$D$9&"|"&5, $P$105:$P$282, 0)), 0))))) | G31: =IF(B31="","", IFERROR(INDEX(Rates_Master!$E:$E, MATCH(B31, Rates_Master!$A:$A, 0)), IFERROR(INDEX($K$105:$K$282, MATCH($D$6&"|"&$D$7&"|"&$D$8&"|"&$D$9&"|"&5, $P$105:$P$282, 0)), 0))) | H31: =IF(OR(B31="", F31=""), 0, ROUND(F31 * G31, 2)) | I31: =IF(B31="","", IF(ISNUMBER(SEARCH("2.10", B31)), "A", "W")) | J31: =IF(H$41>0, ROUND(H31 / H$41 * 100, 1), 0) | K31: =IFERROR(INDEX($N$105:$N$282, MATCH($D$6&"|"&$D$7&"|"&$D$8&"|"&$D$9&"|"&5, $P$105:$P$282, 0)), "") | L31: =IF(AND(ISNUMBER(F31), F31>0, D$10>0), ROUND(F31 * 8 / D$10, 4), "") | M31: =IF(AND(ISNUMBER(F31), F31>0, D$10>0), ROUND(D$10 / (F31 * 8), 2), "") | N31: =IF(B31="","", "CPWD Standard Earthwork Production Resource") | O31: =IF(B31="","", IF(B31="0101", IF($D$22="NO", "OMITTED DEDUCTION (DAR Item 2.5): 0.40 Bhishti-day @ Rs 617 = Rs 246.80 direct. Compounded with GST 14.05% (Rs 34.68) + CPOH 15% (Rs 42.22) + Cess 1% (Rs 3.24) = Rs 326.94/10 cum -> -Rs 33.00/cum deduction.", "Watering by Bhishti to OMC: 25 cum/8-hr day (0.40 day/10 cum)."), IF(OR(B31="0003", B31="0011", B31="0113"), IF($D$23="NO", "OMITTED DEDUCTION (DAR Item 2.4): 0.008 Roller @ Rs 3000 (Rs 24.00) + 0.008 Chowkidar (Rs 4.46) + Sundries (Rs 3.64) = Rs 32.10 direct. Compounded with Water 1% (Rs 0.32) + GST 14.05% (Rs 4.55) + CPOH 15% (Rs 5.55) + Cess 1% (Rs 0.43) = Rs 42.95/10 cum -> -Rs 4.30/cum deduction.", "Power roller compaction: 1250 cum/8-hr day (0.008 day/10 cum)."), IFERROR(INDEX($O$105:$O$282, MATCH($D$6&"|"&$D$7&"|"&$D$8&"|"&$D$9&"|"&5, $P$105:$P$282, 0)), ""))))
A32: 6 | B32: =IFERROR(INDEX($G$105:$G$282, MATCH($D$6&"|"&$D$7&"|"&$D$8&"|"&$D$9&"|"&6, $P$105:$P$282, 0)), "") | C32: =IF(B32="","", IFERROR(INDEX(Rates_Master!$C:$C, MATCH(B32, Rates_Master!$A:$A, 0)), IFERROR(INDEX($H$105:$H$282, MATCH($D$6&"|"&$D$7&"|"&$D$8&"|"&$D$9&"|"&6, $P$105:$P$282, 0)), "Custom Resource"))) | D32: =IF(B32="","", IFERROR(INDEX(Rates_Master!$B:$B, MATCH(B32, Rates_Master!$A:$A, 0)), "Labour")) | E32: =IF(B32="","", IFERROR(INDEX(Rates_Master!$D:$D, MATCH(B32, Rates_Master!$A:$A, 0)), "day")) | F32: =IF(B32="","", IF(B32="0101", IF($D$22="NO", 0, IF(AND(ISNUMBER(K32), K32>0), ROUND(D$10/K32, 5), IFERROR(INDEX($I$105:$I$282, MATCH($D$6&"|"&$D$7&"|"&$D$8&"|"&$D$9&"|"&6, $P$105:$P$282, 0)), 0))), IF(OR(B32="0003", B32="0011", B32="0113"), IF($D$23="NO", 0, IF(AND(ISNUMBER(K32), K32>0), ROUND(D$10/K32, 5), IFERROR(INDEX($I$105:$I$282, MATCH($D$6&"|"&$D$7&"|"&$D$8&"|"&$D$9&"|"&6, $P$105:$P$282, 0)), 0))), IF(AND(ISNUMBER(K32), K32>0), ROUND(D$10/K32, 5), IFERROR(INDEX($I$105:$I$282, MATCH($D$6&"|"&$D$7&"|"&$D$8&"|"&$D$9&"|"&6, $P$105:$P$282, 0)), 0))))) | G32: =IF(B32="","", IFERROR(INDEX(Rates_Master!$E:$E, MATCH(B32, Rates_Master!$A:$A, 0)), IFERROR(INDEX($K$105:$K$282, MATCH($D$6&"|"&$D$7&"|"&$D$8&"|"&$D$9&"|"&6, $P$105:$P$282, 0)), 0))) | H32: =IF(OR(B32="", F32=""), 0, ROUND(F32 * G32, 2)) | I32: =IF(B32="","", IF(ISNUMBER(SEARCH("2.10", B32)), "A", "W")) | J32: =IF(H$41>0, ROUND(H32 / H$41 * 100, 1), 0) | K32: =IFERROR(INDEX($N$105:$N$282, MATCH($D$6&"|"&$D$7&"|"&$D$8&"|"&$D$9&"|"&6, $P$105:$P$282, 0)), "") | L32: =IF(AND(ISNUMBER(F32), F32>0, D$10>0), ROUND(F32 * 8 / D$10, 4), "") | M32: =IF(AND(ISNUMBER(F32), F32>0, D$10>0), ROUND(D$10 / (F32 * 8), 2), "") | N32: =IF(B32="","", "CPWD Standard Earthwork Production Resource") | O32: =IF(B32="","", IF(B32="0101", IF($D$22="NO", "OMITTED DEDUCTION (DAR Item 2.5): 0.40 Bhishti-day @ Rs 617 = Rs 246.80 direct. Compounded with GST 14.05% (Rs 34.68) + CPOH 15% (Rs 42.22) + Cess 1% (Rs 3.24) = Rs 326.94/10 cum -> -Rs 33.00/cum deduction.", "Watering by Bhishti to OMC: 25 cum/8-hr day (0.40 day/10 cum)."), IF(OR(B32="0003", B32="0011", B32="0113"), IF($D$23="NO", "OMITTED DEDUCTION (DAR Item 2.4): 0.008 Roller @ Rs 3000 (Rs 24.00) + 0.008 Chowkidar (Rs 4.46) + Sundries (Rs 3.64) = Rs 32.10 direct. Compounded with Water 1% (Rs 0.32) + GST 14.05% (Rs 4.55) + CPOH 15% (Rs 5.55) + Cess 1% (Rs 0.43) = Rs 42.95/10 cum -> -Rs 4.30/cum deduction.", "Power roller compaction: 1250 cum/8-hr day (0.008 day/10 cum)."), IFERROR(INDEX($O$105:$O$282, MATCH($D$6&"|"&$D$7&"|"&$D$8&"|"&$D$9&"|"&6, $P$105:$P$282, 0)), ""))))
A33: 7 | B33: =IFERROR(INDEX($G$105:$G$282, MATCH($D$6&"|"&$D$7&"|"&$D$8&"|"&$D$9&"|"&7, $P$105:$P$282, 0)), "") | C33: =IF(B33="","", IFERROR(INDEX(Rates_Master!$C:$C, MATCH(B33, Rates_Master!$A:$A, 0)), IFERROR(INDEX($H$105:$H$282, MATCH($D$6&"|"&$D$7&"|"&$D$8&"|"&$D$9&"|"&7, $P$105:$P$282, 0)), "Custom Resource"))) | D33: =IF(B33="","", IFERROR(INDEX(Rates_Master!$B:$B, MATCH(B33, Rates_Master!$A:$A, 0)), "Labour")) | E33: =IF(B33="","", IFERROR(INDEX(Rates_Master!$D:$D, MATCH(B33, Rates_Master!$A:$A, 0)), "day")) | F33: =IF(B33="","", IF(B33="0101", IF($D$22="NO", 0, IF(AND(ISNUMBER(K33), K33>0), ROUND(D$10/K33, 5), IFERROR(INDEX($I$105:$I$282, MATCH($D$6&"|"&$D$7&"|"&$D$8&"|"&$D$9&"|"&7, $P$105:$P$282, 0)), 0))), IF(OR(B33="0003", B33="0011", B33="0113"), IF($D$23="NO", 0, IF(AND(ISNUMBER(K33), K33>0), ROUND(D$10/K33, 5), IFERROR(INDEX($I$105:$I$282, MATCH($D$6&"|"&$D$7&"|"&$D$8&"|"&$D$9&"|"&7, $P$105:$P$282, 0)), 0))), IF(AND(ISNUMBER(K33), K33>0), ROUND(D$10/K33, 5), IFERROR(INDEX($I$105:$I$282, MATCH($D$6&"|"&$D$7&"|"&$D$8&"|"&$D$9&"|"&7, $P$105:$P$282, 0)), 0))))) | G33: =IF(B33="","", IFERROR(INDEX(Rates_Master!$E:$E, MATCH(B33, Rates_Master!$A:$A, 0)), IFERROR(INDEX($K$105:$K$282, MATCH($D$6&"|"&$D$7&"|"&$D$8&"|"&$D$9&"|"&7, $P$105:$P$282, 0)), 0))) | H33: =IF(OR(B33="", F33=""), 0, ROUND(F33 * G33, 2)) | I33: =IF(B33="","", IF(ISNUMBER(SEARCH("2.10", B33)), "A", "W")) | J33: =IF(H$41>0, ROUND(H33 / H$41 * 100, 1), 0) | K33: =IFERROR(INDEX($N$105:$N$282, MATCH($D$6&"|"&$D$7&"|"&$D$8&"|"&$D$9&"|"&7, $P$105:$P$282, 0)), "") | L33: =IF(AND(ISNUMBER(F33), F33>0, D$10>0), ROUND(F33 * 8 / D$10, 4), "") | M33: =IF(AND(ISNUMBER(F33), F33>0, D$10>0), ROUND(D$10 / (F33 * 8), 2), "") | N33: =IF(B33="","", "CPWD Standard Earthwork Production Resource") | O33: =IF(B33="","", IF(B33="0101", IF($D$22="NO", "OMITTED DEDUCTION (DAR Item 2.5): 0.40 Bhishti-day @ Rs 617 = Rs 246.80 direct. Compounded with GST 14.05% (Rs 34.68) + CPOH 15% (Rs 42.22) + Cess 1% (Rs 3.24) = Rs 326.94/10 cum -> -Rs 33.00/cum deduction.", "Watering by Bhishti to OMC: 25 cum/8-hr day (0.40 day/10 cum)."), IF(OR(B33="0003", B33="0011", B33="0113"), IF($D$23="NO", "OMITTED DEDUCTION (DAR Item 2.4): 0.008 Roller @ Rs 3000 (Rs 24.00) + 0.008 Chowkidar (Rs 4.46) + Sundries (Rs 3.64) = Rs 32.10 direct. Compounded with Water 1% (Rs 0.32) + GST 14.05% (Rs 4.55) + CPOH 15% (Rs 5.55) + Cess 1% (Rs 0.43) = Rs 42.95/10 cum -> -Rs 4.30/cum deduction.", "Power roller compaction: 1250 cum/8-hr day (0.008 day/10 cum)."), IFERROR(INDEX($O$105:$O$282, MATCH($D$6&"|"&$D$7&"|"&$D$8&"|"&$D$9&"|"&7, $P$105:$P$282, 0)), ""))))
A34: 8 | B34: =IFERROR(INDEX($G$105:$G$282, MATCH($D$6&"|"&$D$7&"|"&$D$8&"|"&$D$9&"|"&8, $P$105:$P$282, 0)), "") | C34: =IF(B34="","", IFERROR(INDEX(Rates_Master!$C:$C, MATCH(B34, Rates_Master!$A:$A, 0)), IFERROR(INDEX($H$105:$H$282, MATCH($D$6&"|"&$D$7&"|"&$D$8&"|"&$D$9&"|"&8, $P$105:$P$282, 0)), "Custom Resource"))) | D34: =IF(B34="","", IFERROR(INDEX(Rates_Master!$B:$B, MATCH(B34, Rates_Master!$A:$A, 0)), "Labour")) | E34: =IF(B34="","", IFERROR(INDEX(Rates_Master!$D:$D, MATCH(B34, Rates_Master!$A:$A, 0)), "day")) | F34: =IF(B34="","", IF(B34="0101", IF($D$22="NO", 0, IF(AND(ISNUMBER(K34), K34>0), ROUND(D$10/K34, 5), IFERROR(INDEX($I$105:$I$282, MATCH($D$6&"|"&$D$7&"|"&$D$8&"|"&$D$9&"|"&8, $P$105:$P$282, 0)), 0))), IF(OR(B34="0003", B34="0011", B34="0113"), IF($D$23="NO", 0, IF(AND(ISNUMBER(K34), K34>0), ROUND(D$10/K34, 5), IFERROR(INDEX($I$105:$I$282, MATCH($D$6&"|"&$D$7&"|"&$D$8&"|"&$D$9&"|"&8, $P$105:$P$282, 0)), 0))), IF(AND(ISNUMBER(K34), K34>0), ROUND(D$10/K34, 5), IFERROR(INDEX($I$105:$I$282, MATCH($D$6&"|"&$D$7&"|"&$D$8&"|"&$D$9&"|"&8, $P$105:$P$282, 0)), 0))))) | G34: =IF(B34="","", IFERROR(INDEX(Rates_Master!$E:$E, MATCH(B34, Rates_Master!$A:$A, 0)), IFERROR(INDEX($K$105:$K$282, MATCH($D$6&"|"&$D$7&"|"&$D$8&"|"&$D$9&"|"&8, $P$105:$P$282, 0)), 0))) | H34: =IF(OR(B34="", F34=""), 0, ROUND(F34 * G34, 2)) | I34: =IF(B34="","", IF(ISNUMBER(SEARCH("2.10", B34)), "A", "W")) | J34: =IF(H$41>0, ROUND(H34 / H$41 * 100, 1), 0) | K34: =IFERROR(INDEX($N$105:$N$282, MATCH($D$6&"|"&$D$7&"|"&$D$8&"|"&$D$9&"|"&8, $P$105:$P$282, 0)), "") | L34: =IF(AND(ISNUMBER(F34), F34>0, D$10>0), ROUND(F34 * 8 / D$10, 4), "") | M34: =IF(AND(ISNUMBER(F34), F34>0, D$10>0), ROUND(D$10 / (F34 * 8), 2), "") | N34: =IF(B34="","", "CPWD Standard Earthwork Production Resource") | O34: =IF(B34="","", IF(B34="0101", IF($D$22="NO", "OMITTED DEDUCTION (DAR Item 2.5): 0.40 Bhishti-day @ Rs 617 = Rs 246.80 direct. Compounded with GST 14.05% (Rs 34.68) + CPOH 15% (Rs 42.22) + Cess 1% (Rs 3.24) = Rs 326.94/10 cum -> -Rs 33.00/cum deduction.", "Watering by Bhishti to OMC: 25 cum/8-hr day (0.40 day/10 cum)."), IF(OR(B34="0003", B34="0011", B34="0113"), IF($D$23="NO", "OMITTED DEDUCTION (DAR Item 2.4): 0.008 Roller @ Rs 3000 (Rs 24.00) + 0.008 Chowkidar (Rs 4.46) + Sundries (Rs 3.64) = Rs 32.10 direct. Compounded with Water 1% (Rs 0.32) + GST 14.05% (Rs 4.55) + CPOH 15% (Rs 5.55) + Cess 1% (Rs 0.43) = Rs 42.95/10 cum -> -Rs 4.30/cum deduction.", "Power roller compaction: 1250 cum/8-hr day (0.008 day/10 cum)."), IFERROR(INDEX($O$105:$O$282, MATCH($D$6&"|"&$D$7&"|"&$D$8&"|"&$D$9&"|"&8, $P$105:$P$282, 0)), ""))))
A35: 9 | B35: =IFERROR(INDEX($G$105:$G$282, MATCH($D$6&"|"&$D$7&"|"&$D$8&"|"&$D$9&"|"&9, $P$105:$P$282, 0)), "") | C35: =IF(B35="","", IFERROR(INDEX(Rates_Master!$C:$C, MATCH(B35, Rates_Master!$A:$A, 0)), IFERROR(INDEX($H$105:$H$282, MATCH($D$6&"|"&$D$7&"|"&$D$8&"|"&$D$9&"|"&9, $P$105:$P$282, 0)), "Custom Resource"))) | D35: =IF(B35="","", IFERROR(INDEX(Rates_Master!$B:$B, MATCH(B35, Rates_Master!$A:$A, 0)), "Labour")) | E35: =IF(B35="","", IFERROR(INDEX(Rates_Master!$D:$D, MATCH(B35, Rates_Master!$A:$A, 0)), "day")) | F35: =IF(B35="","", IF(B35="0101", IF($D$22="NO", 0, IF(AND(ISNUMBER(K35), K35>0), ROUND(D$10/K35, 5), IFERROR(INDEX($I$105:$I$282, MATCH($D$6&"|"&$D$7&"|"&$D$8&"|"&$D$9&"|"&9, $P$105:$P$282, 0)), 0))), IF(OR(B35="0003", B35="0011", B35="0113"), IF($D$23="NO", 0, IF(AND(ISNUMBER(K35), K35>0), ROUND(D$10/K35, 5), IFERROR(INDEX($I$105:$I$282, MATCH($D$6&"|"&$D$7&"|"&$D$8&"|"&$D$9&"|"&9, $P$105:$P$282, 0)), 0))), IF(AND(ISNUMBER(K35), K35>0), ROUND(D$10/K35, 5), IFERROR(INDEX($I$105:$I$282, MATCH($D$6&"|"&$D$7&"|"&$D$8&"|"&$D$9&"|"&9, $P$105:$P$282, 0)), 0))))) | G35: =IF(B35="","", IFERROR(INDEX(Rates_Master!$E:$E, MATCH(B35, Rates_Master!$A:$A, 0)), IFERROR(INDEX($K$105:$K$282, MATCH($D$6&"|"&$D$7&"|"&$D$8&"|"&$D$9&"|"&9, $P$105:$P$282, 0)), 0))) | H35: =IF(OR(B35="", F35=""), 0, ROUND(F35 * G35, 2)) | I35: =IF(B35="","", IF(ISNUMBER(SEARCH("2.10", B35)), "A", "W")) | J35: =IF(H$41>0, ROUND(H35 / H$41 * 100, 1), 0) | K35: =IFERROR(INDEX($N$105:$N$282, MATCH($D$6&"|"&$D$7&"|"&$D$8&"|"&$D$9&"|"&9, $P$105:$P$282, 0)), "") | L35: =IF(AND(ISNUMBER(F35), F35>0, D$10>0), ROUND(F35 * 8 / D$10, 4), "") | M35: =IF(AND(ISNUMBER(F35), F35>0, D$10>0), ROUND(D$10 / (F35 * 8), 2), "") | N35: =IF(B35="","", "CPWD Standard Earthwork Production Resource") | O35: =IF(B35="","", IF(B35="0101", IF($D$22="NO", "OMITTED DEDUCTION (DAR Item 2.5): 0.40 Bhishti-day @ Rs 617 = Rs 246.80 direct. Compounded with GST 14.05% (Rs 34.68) + CPOH 15% (Rs 42.22) + Cess 1% (Rs 3.24) = Rs 326.94/10 cum -> -Rs 33.00/cum deduction.", "Watering by Bhishti to OMC: 25 cum/8-hr day (0.40 day/10 cum)."), IF(OR(B35="0003", B35="0011", B35="0113"), IF($D$23="NO", "OMITTED DEDUCTION (DAR Item 2.4): 0.008 Roller @ Rs 3000 (Rs 24.00) + 0.008 Chowkidar (Rs 4.46) + Sundries (Rs 3.64) = Rs 32.10 direct. Compounded with Water 1% (Rs 0.32) + GST 14.05% (Rs 4.55) + CPOH 15% (Rs 5.55) + Cess 1% (Rs 0.43) = Rs 42.95/10 cum -> -Rs 4.30/cum deduction.", "Power roller compaction: 1250 cum/8-hr day (0.008 day/10 cum)."), IFERROR(INDEX($O$105:$O$282, MATCH($D$6&"|"&$D$7&"|"&$D$8&"|"&$D$9&"|"&9, $P$105:$P$282, 0)), ""))))
A36: 10 | B36: =IFERROR(INDEX($G$105:$G$282, MATCH($D$6&"|"&$D$7&"|"&$D$8&"|"&$D$9&"|"&10, $P$105:$P$282, 0)), "") | C36: =IF(B36="","", IFERROR(INDEX(Rates_Master!$C:$C, MATCH(B36, Rates_Master!$A:$A, 0)), IFERROR(INDEX($H$105:$H$282, MATCH($D$6&"|"&$D$7&"|"&$D$8&"|"&$D$9&"|"&10, $P$105:$P$282, 0)), "Custom Resource"))) | D36: =IF(B36="","", IFERROR(INDEX(Rates_Master!$B:$B, MATCH(B36, Rates_Master!$A:$A, 0)), "Labour")) | E36: =IF(B36="","", IFERROR(INDEX(Rates_Master!$D:$D, MATCH(B36, Rates_Master!$A:$A, 0)), "day")) | F36: =IF(B36="","", IF(B36="0101", IF($D$22="NO", 0, IF(AND(ISNUMBER(K36), K36>0), ROUND(D$10/K36, 5), IFERROR(INDEX($I$105:$I$282, MATCH($D$6&"|"&$D$7&"|"&$D$8&"|"&$D$9&"|"&10, $P$105:$P$282, 0)), 0))), IF(OR(B36="0003", B36="0011", B36="0113"), IF($D$23="NO", 0, IF(AND(ISNUMBER(K36), K36>0), ROUND(D$10/K36, 5), IFERROR(INDEX($I$105:$I$282, MATCH($D$6&"|"&$D$7&"|"&$D$8&"|"&$D$9&"|"&10, $P$105:$P$282, 0)), 0))), IF(AND(ISNUMBER(K36), K36>0), ROUND(D$10/K36, 5), IFERROR(INDEX($I$105:$I$282, MATCH($D$6&"|"&$D$7&"|"&$D$8&"|"&$D$9&"|"&10, $P$105:$P$282, 0)), 0))))) | G36: =IF(B36="","", IFERROR(INDEX(Rates_Master!$E:$E, MATCH(B36, Rates_Master!$A:$A, 0)), IFERROR(INDEX($K$105:$K$282, MATCH($D$6&"|"&$D$7&"|"&$D$8&"|"&$D$9&"|"&10, $P$105:$P$282, 0)), 0))) | H36: =IF(OR(B36="", F36=""), 0, ROUND(F36 * G36, 2)) | I36: =IF(B36="","", IF(ISNUMBER(SEARCH("2.10", B36)), "A", "W")) | J36: =IF(H$41>0, ROUND(H36 / H$41 * 100, 1), 0) | K36: =IFERROR(INDEX($N$105:$N$282, MATCH($D$6&"|"&$D$7&"|"&$D$8&"|"&$D$9&"|"&10, $P$105:$P$282, 0)), "") | L36: =IF(AND(ISNUMBER(F36), F36>0, D$10>0), ROUND(F36 * 8 / D$10, 4), "") | M36: =IF(AND(ISNUMBER(F36), F36>0, D$10>0), ROUND(D$10 / (F36 * 8), 2), "") | N36: =IF(B36="","", "CPWD Standard Earthwork Production Resource") | O36: =IF(B36="","", IF(B36="0101", IF($D$22="NO", "OMITTED DEDUCTION (DAR Item 2.5): 0.40 Bhishti-day @ Rs 617 = Rs 246.80 direct. Compounded with GST 14.05% (Rs 34.68) + CPOH 15% (Rs 42.22) + Cess 1% (Rs 3.24) = Rs 326.94/10 cum -> -Rs 33.00/cum deduction.", "Watering by Bhishti to OMC: 25 cum/8-hr day (0.40 day/10 cum)."), IF(OR(B36="0003", B36="0011", B36="0113"), IF($D$23="NO", "OMITTED DEDUCTION (DAR Item 2.4): 0.008 Roller @ Rs 3000 (Rs 24.00) + 0.008 Chowkidar (Rs 4.46) + Sundries (Rs 3.64) = Rs 32.10 direct. Compounded with Water 1% (Rs 0.32) + GST 14.05% (Rs 4.55) + CPOH 15% (Rs 5.55) + Cess 1% (Rs 0.43) = Rs 42.95/10 cum -> -Rs 4.30/cum deduction.", "Power roller compaction: 1250 cum/8-hr day (0.008 day/10 cum)."), IFERROR(INDEX($O$105:$O$282, MATCH($D$6&"|"&$D$7&"|"&$D$8&"|"&$D$9&"|"&10, $P$105:$P$282, 0)), ""))))
A37: 11 | B37: =IFERROR(INDEX($G$105:$G$282, MATCH($D$6&"|"&$D$7&"|"&$D$8&"|"&$D$9&"|"&11, $P$105:$P$282, 0)), "") | C37: =IF(B37="","", IFERROR(INDEX(Rates_Master!$C:$C, MATCH(B37, Rates_Master!$A:$A, 0)), IFERROR(INDEX($H$105:$H$282, MATCH($D$6&"|"&$D$7&"|"&$D$8&"|"&$D$9&"|"&11, $P$105:$P$282, 0)), "Custom Resource"))) | D37: =IF(B37="","", IFERROR(INDEX(Rates_Master!$B:$B, MATCH(B37, Rates_Master!$A:$A, 0)), "Labour")) | E37: =IF(B37="","", IFERROR(INDEX(Rates_Master!$D:$D, MATCH(B37, Rates_Master!$A:$A, 0)), "day")) | F37: =IF(B37="","", IF(B37="0101", IF($D$22="NO", 0, IF(AND(ISNUMBER(K37), K37>0), ROUND(D$10/K37, 5), IFERROR(INDEX($I$105:$I$282, MATCH($D$6&"|"&$D$7&"|"&$D$8&"|"&$D$9&"|"&11, $P$105:$P$282, 0)), 0))), IF(OR(B37="0003", B37="0011", B37="0113"), IF($D$23="NO", 0, IF(AND(ISNUMBER(K37), K37>0), ROUND(D$10/K37, 5), IFERROR(INDEX($I$105:$I$282, MATCH($D$6&"|"&$D$7&"|"&$D$8&"|"&$D$9&"|"&11, $P$105:$P$282, 0)), 0))), IF(AND(ISNUMBER(K37), K37>0), ROUND(D$10/K37, 5), IFERROR(INDEX($I$105:$I$282, MATCH($D$6&"|"&$D$7&"|"&$D$8&"|"&$D$9&"|"&11, $P$105:$P$282, 0)), 0))))) | G37: =IF(B37="","", IFERROR(INDEX(Rates_Master!$E:$E, MATCH(B37, Rates_Master!$A:$A, 0)), IFERROR(INDEX($K$105:$K$282, MATCH($D$6&"|"&$D$7&"|"&$D$8&"|"&$D$9&"|"&11, $P$105:$P$282, 0)), 0))) | H37: =IF(OR(B37="", F37=""), 0, ROUND(F37 * G37, 2)) | I37: =IF(B37="","", IF(ISNUMBER(SEARCH("2.10", B37)), "A", "W")) | J37: =IF(H$41>0, ROUND(H37 / H$41 * 100, 1), 0) | K37: =IFERROR(INDEX($N$105:$N$282, MATCH($D$6&"|"&$D$7&"|"&$D$8&"|"&$D$9&"|"&11, $P$105:$P$282, 0)), "") | L37: =IF(AND(ISNUMBER(F37), F37>0, D$10>0), ROUND(F37 * 8 / D$10, 4), "") | M37: =IF(AND(ISNUMBER(F37), F37>0, D$10>0), ROUND(D$10 / (F37 * 8), 2), "") | N37: =IF(B37="","", "CPWD Standard Earthwork Production Resource") | O37: =IF(B37="","", IF(B37="0101", IF($D$22="NO", "OMITTED DEDUCTION (DAR Item 2.5): 0.40 Bhishti-day @ Rs 617 = Rs 246.80 direct. Compounded with GST 14.05% (Rs 34.68) + CPOH 15% (Rs 42.22) + Cess 1% (Rs 3.24) = Rs 326.94/10 cum -> -Rs 33.00/cum deduction.", "Watering by Bhishti to OMC: 25 cum/8-hr day (0.40 day/10 cum)."), IF(OR(B37="0003", B37="0011", B37="0113"), IF($D$23="NO", "OMITTED DEDUCTION (DAR Item 2.4): 0.008 Roller @ Rs 3000 (Rs 24.00) + 0.008 Chowkidar (Rs 4.46) + Sundries (Rs 3.64) = Rs 32.10 direct. Compounded with Water 1% (Rs 0.32) + GST 14.05% (Rs 4.55) + CPOH 15% (Rs 5.55) + Cess 1% (Rs 0.43) = Rs 42.95/10 cum -> -Rs 4.30/cum deduction.", "Power roller compaction: 1250 cum/8-hr day (0.008 day/10 cum)."), IFERROR(INDEX($O$105:$O$282, MATCH($D$6&"|"&$D$7&"|"&$D$8&"|"&$D$9&"|"&11, $P$105:$P$282, 0)), ""))))
A38: 12 | B38: =IFERROR(INDEX($G$105:$G$282, MATCH($D$6&"|"&$D$7&"|"&$D$8&"|"&$D$9&"|"&12, $P$105:$P$282, 0)), "") | C38: =IF(B38="","", IFERROR(INDEX(Rates_Master!$C:$C, MATCH(B38, Rates_Master!$A:$A, 0)), IFERROR(INDEX($H$105:$H$282, MATCH($D$6&"|"&$D$7&"|"&$D$8&"|"&$D$9&"|"&12, $P$105:$P$282, 0)), "Custom Resource"))) | D38: =IF(B38="","", IFERROR(INDEX(Rates_Master!$B:$B, MATCH(B38, Rates_Master!$A:$A, 0)), "Labour")) | E38: =IF(B38="","", IFERROR(INDEX(Rates_Master!$D:$D, MATCH(B38, Rates_Master!$A:$A, 0)), "day")) | F38: =IF(B38="","", IF(B38="0101", IF($D$22="NO", 0, IF(AND(ISNUMBER(K38), K38>0), ROUND(D$10/K38, 5), IFERROR(INDEX($I$105:$I$282, MATCH($D$6&"|"&$D$7&"|"&$D$8&"|"&$D$9&"|"&12, $P$105:$P$282, 0)), 0))), IF(OR(B38="0003", B38="0011", B38="0113"), IF($D$23="NO", 0, IF(AND(ISNUMBER(K38), K38>0), ROUND(D$10/K38, 5), IFERROR(INDEX($I$105:$I$282, MATCH($D$6&"|"&$D$7&"|"&$D$8&"|"&$D$9&"|"&12, $P$105:$P$282, 0)), 0))), IF(AND(ISNUMBER(K38), K38>0), ROUND(D$10/K38, 5), IFERROR(INDEX($I$105:$I$282, MATCH($D$6&"|"&$D$7&"|"&$D$8&"|"&$D$9&"|"&12, $P$105:$P$282, 0)), 0))))) | G38: =IF(B38="","", IFERROR(INDEX(Rates_Master!$E:$E, MATCH(B38, Rates_Master!$A:$A, 0)), IFERROR(INDEX($K$105:$K$282, MATCH($D$6&"|"&$D$7&"|"&$D$8&"|"&$D$9&"|"&12, $P$105:$P$282, 0)), 0))) | H38: =IF(OR(B38="", F38=""), 0, ROUND(F38 * G38, 2)) | I38: =IF(B38="","", IF(ISNUMBER(SEARCH("2.10", B38)), "A", "W")) | J38: =IF(H$41>0, ROUND(H38 / H$41 * 100, 1), 0) | K38: =IFERROR(INDEX($N$105:$N$282, MATCH($D$6&"|"&$D$7&"|"&$D$8&"|"&$D$9&"|"&12, $P$105:$P$282, 0)), "") | L38: =IF(AND(ISNUMBER(F38), F38>0, D$10>0), ROUND(F38 * 8 / D$10, 4), "") | M38: =IF(AND(ISNUMBER(F38), F38>0, D$10>0), ROUND(D$10 / (F38 * 8), 2), "") | N38: =IF(B38="","", "CPWD Standard Earthwork Production Resource") | O38: =IF(B38="","", IF(B38="0101", IF($D$22="NO", "OMITTED DEDUCTION (DAR Item 2.5): 0.40 Bhishti-day @ Rs 617 = Rs 246.80 direct. Compounded with GST 14.05% (Rs 34.68) + CPOH 15% (Rs 42.22) + Cess 1% (Rs 3.24) = Rs 326.94/10 cum -> -Rs 33.00/cum deduction.", "Watering by Bhishti to OMC: 25 cum/8-hr day (0.40 day/10 cum)."), IF(OR(B38="0003", B38="0011", B38="0113"), IF($D$23="NO", "OMITTED DEDUCTION (DAR Item 2.4): 0.008 Roller @ Rs 3000 (Rs 24.00) + 0.008 Chowkidar (Rs 4.46) + Sundries (Rs 3.64) = Rs 32.10 direct. Compounded with Water 1% (Rs 0.32) + GST 14.05% (Rs 4.55) + CPOH 15% (Rs 5.55) + Cess 1% (Rs 0.43) = Rs 42.95/10 cum -> -Rs 4.30/cum deduction.", "Power roller compaction: 1250 cum/8-hr day (0.008 day/10 cum)."), IFERROR(INDEX($O$105:$O$282, MATCH($D$6&"|"&$D$7&"|"&$D$8&"|"&$D$9&"|"&12, $P$105:$P$282, 0)), ""))))
A39: 13 | B39: =IFERROR(INDEX($G$105:$G$282, MATCH($D$6&"|"&$D$7&"|"&$D$8&"|"&$D$9&"|"&13, $P$105:$P$282, 0)), "") | C39: =IF(B39="","", IFERROR(INDEX(Rates_Master!$C:$C, MATCH(B39, Rates_Master!$A:$A, 0)), IFERROR(INDEX($H$105:$H$282, MATCH($D$6&"|"&$D$7&"|"&$D$8&"|"&$D$9&"|"&13, $P$105:$P$282, 0)), "Custom Resource"))) | D39: =IF(B39="","", IFERROR(INDEX(Rates_Master!$B:$B, MATCH(B39, Rates_Master!$A:$A, 0)), "Labour")) | E39: =IF(B39="","", IFERROR(INDEX(Rates_Master!$D:$D, MATCH(B39, Rates_Master!$A:$A, 0)), "day")) | F39: =IF(B39="","", IF(B39="0101", IF($D$22="NO", 0, IF(AND(ISNUMBER(K39), K39>0), ROUND(D$10/K39, 5), IFERROR(INDEX($I$105:$I$282, MATCH($D$6&"|"&$D$7&"|"&$D$8&"|"&$D$9&"|"&13, $P$105:$P$282, 0)), 0))), IF(OR(B39="0003", B39="0011", B39="0113"), IF($D$23="NO", 0, IF(AND(ISNUMBER(K39), K39>0), ROUND(D$10/K39, 5), IFERROR(INDEX($I$105:$I$282, MATCH($D$6&"|"&$D$7&"|"&$D$8&"|"&$D$9&"|"&13, $P$105:$P$282, 0)), 0))), IF(AND(ISNUMBER(K39), K39>0), ROUND(D$10/K39, 5), IFERROR(INDEX($I$105:$I$282, MATCH($D$6&"|"&$D$7&"|"&$D$8&"|"&$D$9&"|"&13, $P$105:$P$282, 0)), 0))))) | G39: =IF(B39="","", IFERROR(INDEX(Rates_Master!$E:$E, MATCH(B39, Rates_Master!$A:$A, 0)), IFERROR(INDEX($K$105:$K$282, MATCH($D$6&"|"&$D$7&"|"&$D$8&"|"&$D$9&"|"&13, $P$105:$P$282, 0)), 0))) | H39: =IF(OR(B39="", F39=""), 0, ROUND(F39 * G39, 2)) | I39: =IF(B39="","", IF(ISNUMBER(SEARCH("2.10", B39)), "A", "W")) | J39: =IF(H$41>0, ROUND(H39 / H$41 * 100, 1), 0) | K39: =IFERROR(INDEX($N$105:$N$282, MATCH($D$6&"|"&$D$7&"|"&$D$8&"|"&$D$9&"|"&13, $P$105:$P$282, 0)), "") | L39: =IF(AND(ISNUMBER(F39), F39>0, D$10>0), ROUND(F39 * 8 / D$10, 4), "") | M39: =IF(AND(ISNUMBER(F39), F39>0, D$10>0), ROUND(D$10 / (F39 * 8), 2), "") | N39: =IF(B39="","", "CPWD Standard Earthwork Production Resource") | O39: =IF(B39="","", IF(B39="0101", IF($D$22="NO", "OMITTED DEDUCTION (DAR Item 2.5): 0.40 Bhishti-day @ Rs 617 = Rs 246.80 direct. Compounded with GST 14.05% (Rs 34.68) + CPOH 15% (Rs 42.22) + Cess 1% (Rs 3.24) = Rs 326.94/10 cum -> -Rs 33.00/cum deduction.", "Watering by Bhishti to OMC: 25 cum/8-hr day (0.40 day/10 cum)."), IF(OR(B39="0003", B39="0011", B39="0113"), IF($D$23="NO", "OMITTED DEDUCTION (DAR Item 2.4): 0.008 Roller @ Rs 3000 (Rs 24.00) + 0.008 Chowkidar (Rs 4.46) + Sundries (Rs 3.64) = Rs 32.10 direct. Compounded with Water 1% (Rs 0.32) + GST 14.05% (Rs 4.55) + CPOH 15% (Rs 5.55) + Cess 1% (Rs 0.43) = Rs 42.95/10 cum -> -Rs 4.30/cum deduction.", "Power roller compaction: 1250 cum/8-hr day (0.008 day/10 cum)."), IFERROR(INDEX($O$105:$O$282, MATCH($D$6&"|"&$D$7&"|"&$D$8&"|"&$D$9&"|"&13, $P$105:$P$282, 0)), ""))))
A40: 14 | B40: =IFERROR(INDEX($G$105:$G$282, MATCH($D$6&"|"&$D$7&"|"&$D$8&"|"&$D$9&"|"&14, $P$105:$P$282, 0)), "") | C40: =IF(B40="","", IFERROR(INDEX(Rates_Master!$C:$C, MATCH(B40, Rates_Master!$A:$A, 0)), IFERROR(INDEX($H$105:$H$282, MATCH($D$6&"|"&$D$7&"|"&$D$8&"|"&$D$9&"|"&14, $P$105:$P$282, 0)), "Custom Resource"))) | D40: =IF(B40="","", IFERROR(INDEX(Rates_Master!$B:$B, MATCH(B40, Rates_Master!$A:$A, 0)), "Labour")) | E40: =IF(B40="","", IFERROR(INDEX(Rates_Master!$D:$D, MATCH(B40, Rates_Master!$A:$A, 0)), "day")) | F40: =IF(B40="","", IF(B40="0101", IF($D$22="NO", 0, IF(AND(ISNUMBER(K40), K40>0), ROUND(D$10/K40, 5), IFERROR(INDEX($I$105:$I$282, MATCH($D$6&"|"&$D$7&"|"&$D$8&"|"&$D$9&"|"&14, $P$105:$P$282, 0)), 0))), IF(OR(B40="0003", B40="0011", B40="0113"), IF($D$23="NO", 0, IF(AND(ISNUMBER(K40), K40>0), ROUND(D$10/K40, 5), IFERROR(INDEX($I$105:$I$282, MATCH($D$6&"|"&$D$7&"|"&$D$8&"|"&$D$9&"|"&14, $P$105:$P$282, 0)), 0))), IF(AND(ISNUMBER(K40), K40>0), ROUND(D$10/K40, 5), IFERROR(INDEX($I$105:$I$282, MATCH($D$6&"|"&$D$7&"|"&$D$8&"|"&$D$9&"|"&14, $P$105:$P$282, 0)), 0))))) | G40: =IF(B40="","", IFERROR(INDEX(Rates_Master!$E:$E, MATCH(B40, Rates_Master!$A:$A, 0)), IFERROR(INDEX($K$105:$K$282, MATCH($D$6&"|"&$D$7&"|"&$D$8&"|"&$D$9&"|"&14, $P$105:$P$282, 0)), 0))) | H40: =IF(OR(B40="", F40=""), 0, ROUND(F40 * G40, 2)) | I40: =IF(B40="","", IF(ISNUMBER(SEARCH("2.10", B40)), "A", "W")) | J40: =IF(H$41>0, ROUND(H40 / H$41 * 100, 1), 0) | K40: =IFERROR(INDEX($N$105:$N$282, MATCH($D$6&"|"&$D$7&"|"&$D$8&"|"&$D$9&"|"&14, $P$105:$P$282, 0)), "") | L40: =IF(AND(ISNUMBER(F40), F40>0, D$10>0), ROUND(F40 * 8 / D$10, 4), "") | M40: =IF(AND(ISNUMBER(F40), F40>0, D$10>0), ROUND(D$10 / (F40 * 8), 2), "") | N40: =IF(B40="","", "CPWD Standard Earthwork Production Resource") | O40: =IF(B40="","", IF(B40="0101", IF($D$22="NO", "OMITTED DEDUCTION (DAR Item 2.5): 0.40 Bhishti-day @ Rs 617 = Rs 246.80 direct. Compounded with GST 14.05% (Rs 34.68) + CPOH 15% (Rs 42.22) + Cess 1% (Rs 3.24) = Rs 326.94/10 cum -> -Rs 33.00/cum deduction.", "Watering by Bhishti to OMC: 25 cum/8-hr day (0.40 day/10 cum)."), IF(OR(B40="0003", B40="0011", B40="0113"), IF($D$23="NO", "OMITTED DEDUCTION (DAR Item 2.4): 0.008 Roller @ Rs 3000 (Rs 24.00) + 0.008 Chowkidar (Rs 4.46) + Sundries (Rs 3.64) = Rs 32.10 direct. Compounded with Water 1% (Rs 0.32) + GST 14.05% (Rs 4.55) + CPOH 15% (Rs 5.55) + Cess 1% (Rs 0.43) = Rs 42.95/10 cum -> -Rs 4.30/cum deduction.", "Power roller compaction: 1250 cum/8-hr day (0.008 day/10 cum)."), IFERROR(INDEX($O$105:$O$282, MATCH($D$6&"|"&$D$7&"|"&$D$8&"|"&$D$9&"|"&14, $P$105:$P$282, 0)), ""))))
A41: Direct Production Cost W = Σ Amount (all active resource lines): | H41: 1 | I41: W | J41: Base for statutory markup calculations before exclusion of pre-marked reference items.
A42: A-tagged Total (pre-marked composite reference items excluded from markups): | H42: 1 | I42: A | J42: Uses robust SUMIF to guarantee error-free evaluation even with empty slots.
A44: 3. STATUTORY MARKUPS & FINAL RATE DERIVATION (CPWD DAR Standard Compounded Markup Chain)
A45: Step | B45: Component / Markup Description | C45: Apply? | D45: Basis Applied | E45: Base Amount (₹) | F45: Factor / % | G45: Added (₹) | H45: Running Total (₹) | I45: Cell Role | J45: CPWD Statutory Guidance Rule & Practical Field Note
A46: W | B46: Direct Production Cost W (all resources) | C46: — | D46: Direct Sum | E46: 1 | F46: — | G46: 1 | H46: 1 | I46: DERIVED | J46: Sum of all direct labour, machinery and sundries from Section 2.
A47: X1 | B47: Add: Water Charges (1% on W-A) | C47: YES | D47: On (W - A) | E47: 1 | F47: 1 | G47: 1 | H47: 1 | I47: INPUT | J47: CPWD standard: 1% for site compaction watering, trench dampening and dust control. Live-linked to Factor_Water.
A48: X | B48: Subtotal X (W + Water Charges) | C48: — | D48: W + Water | E48: 1 | F48: — | G48: 1 | H48: 1 | I48: DERIVED | J48: Compounded base passed to Works Contract GST calculation.
A49: Y1 | B49: Add: GST on Works Contract (14.05% on X-A) | C49: YES | D49: On (X - A) | E49: 1 | F49: 1 | G49: 1 | H49: 1 | I49: INPUT | J49: CPWD DAR statutory works contract tax factor (0.1405). Live-linked to Factor_GST on Global_Factors.
A50: Y | B50: Subtotal Y (X + GST) | C50: — | D50: X + GST | E50: 1 | F50: — | G50: 1 | H50: 1 | I50: DERIVED | J50: Compounded base passed to Contractor Profit & Overheads calculation.
A51: Z1 | B51: Add: Contractor Profit & Overheads (15% CPOH on Y-A) | C51: YES | D51: On (Y - A) | E51: 1 | F51: 1 | G51: 1 | H51: 1 | I51: INPUT | J51: Standard 15% allowance for contractor overheads, plant depreciation and profit. Live-linked to Factor_CPOH.
A52: Z | B52: Subtotal Z (Y + CPOH) | C52: — | D52: Y + CPOH | E52: 1 | F52: — | G52: 1 | H52: 1 | I52: DERIVED | J52: Compounded base passed to Building and Other Construction Workers Welfare Cess calculation.
A53: Z2 | B53: Add: Building and Other Construction Workers Welfare Cess (1% on Z) | C53: YES | D53: On Z | E53: 1 | F53: 1 | G53: 1 | H53: 1 | I53: INPUT | J53: Statutory 1% BOCW Welfare Cess levied on overall cost including CPOH. Live-linked to Factor_Cess.
A54: Cost | B54: 1 | C54: — | D54: Standard Output Batch | E54: 1 | F54: — | G54: 1 | H54: 1 | I54: RESULT | J54: Fully compounded cost for the standard DAR batch quantity before unit-rate derivation.
A55: Rate | B55: 1 | C55: — | D55: 1 | E55: 1 | F55: — | G55: 1 | H55: 1 | I55: DERIVED | J55: Exact rate per unit output (Cost / Batch Qty) carried into statutory rounding.
A56: SAY | B56: 1 | C56: — | D56: MROUND 0.05 | E56: 1 | F56: — | G56: 1 | H56: 1 | I56: SAY | J56: Final published billing rate rounded to the nearest 5 paise in accordance with CPWD DAR Section 0 conventions.
A57: REF | B57: 1 | C57: — | D57: Benchmark | E57: 1 | F57: — | G57: 1 | H57: 1 | I57: LOOKUP | J57: Official CPWD DAR 2019 Volume 1 published rate for verification.
A58: DIFF | B58: Audit Variance (Analysed Say - Published Say): | C58: — | D58: Say - Ref | E58: 1 | F58: — | G58: 1 | H58: 1 | I58: RESULT | J58: Discrepancy audit against published benchmark. Target = ₹ 0.00.
A60: 4. FIRST-PRINCIPLES LABOUR & MACHINERY PRODUCTIVITY BENCHMARK MATRIX (8-Hour Working Shift Basis)
A61: FIRST-PRINCIPLES DERIVATION MECHANICS: Shows how physical labour and equipment operations in an 8-hour shift translate into CPWD norm factors. Standard Gang (G) × Task Duration (H) = Total Man-Hours (MH) → Day Coeff (D) = MH / 8.00 h → Daily Output (P) = Batch Q / D → Specific Effort (SE) = MH / Q → Hourly Pace = P / 8.00. Every calculation cell is a live Excel formula. No CPWD code numbering; Resource Code is placed in its own dedicated column (Col C).
A62: Civil Work Scope / Operation | B62: Operation / Sub-Task | C62: Resource Code | D62: Resource Trade / Fleet Role | E62: Batch Qty (Q) | F62: Unit | G62: Gang Size (G) | H62: Duration (H hrs) | I62: Total Man-Hours (MH) | J62: Shift (h) | K62: Day Coeff (D) | L62: Daily Output (P) | M62: Unit Effort (SE) | N62: Hourly Pace | O62: Engineering Task Breakdown & First-Principles 8-Hour Logic
A63: Surface excavation <= 30cm depth (100 sqm) | B63: Pickaxe & phowrah loosening hard crust | C63: 0114 | D63: Beldar (Semi-Skilled / Operational Earthwork) | E63: 100 | F63: sqm | G63: 4 | H63: 13.6 | I63: 1 | J63: 8 | K63: 1 | L63: 1 | M63: 1 | N63: 1 | O63: Pickaxe loosening of hard dry soil crust up to 30 cm depth. 1 Beldar loosens 14.71 sqm per 8-hr shift (1.84 sqm/hr). Total 54.40 man-hrs.
A64: Surface excavation <= 30cm depth (100 sqm) | B64: Basket loading, haulage & 50m disposal | C64: 0115 | D64: Coolie (Unskilled / Haulage & Spoil Handling) | E64: 100 | F64: sqm | G64: 4 | H64: 11.2 | I64: 1 | J64: 8 | K64: 1 | L64: 1 | M64: 1 | N64: 1 | O64: Shoveling into iron tagaris, basket haulage and dumping up to 50 m lead and 1.5 m lift. 1 Coolie moves 17.86 sqm per 8-hr shift.
A65: Rough excav, banking, water & roll (10 cum) | B65: Rough soil digging & heavy clod breaking | C65: 0114 | D65: Beldar (Semi-Skilled / Operational Earthwork) | E65: 10 | F65: cum | G65: 4 | H65: 11.8 | I65: 1 | J65: 8 | K65: 1 | L65: 1 | M65: 1 | N65: 1 | O65: Rough digging in soil + breaking heavy clods + dressing embankment slope profile. 1 Beldar yields 1.695 cum per 8-hr shift.
A66: Rough excav, banking, water & roll (10 cum) | B66: Basket haulage 50m & 20cm layer spread | C66: 0115 | D66: Coolie (Unskilled / Haulage & Spoil Handling) | E66: 10 | F66: cum | G66: 3 | H66: 9.6 | I66: 1 | J66: 8 | K66: 1 | L66: 1 | M66: 1 | N66: 1 | O66: Basket haulage within 50 m lead, tipping and uniform spreading in layers not exceeding 20 cm depth.
A67: Rough excav, banking, water & roll (10 cum) | B67: OMC compaction layer watering | C67: 0101 | D67: Bhishti (Compaction Layer Watering to OMC) | E67: 10 | F67: cum | G67: 1 | H67: 3.2 | I67: 1 | J67: 8 | K67: 1 | L67: 1 | M67: 1 | N67: 1 | O67: Spraying water over loose 20 cm layers from mashak/hose to optimum moisture content (OMC) before rolling. 25 cum per 8-hr day.
A68: Rough excav, banking, water & roll (10 cum) | B68: 8-10t power roller 6 passes on 20cm layer | C68: 0011 | D68: Road Roller 8-10t Diesel Power (incl Fuel & Crew) | E68: 10 | F68: cum | G68: 1 | H68: 0.064 | I68: 1 | J68: 8 | K68: 1 | L68: 1 | M68: 1 | N68: 1 | O68: Compacting loose 20 cm layers: 6 passes with 8-10t roller covering 1.8 m width at 2.5 km/h = 156.25 cum/hr (1250 cum per 8-hr shift).
A69: Rough excavation only (10 cum) | B69: Rough soil digging & loosening | C69: 0114 | D69: Beldar (Semi-Skilled / Operational Earthwork) | E69: 10 | F69: cum | G69: 2 | H69: 14.8 | I69: 1 | J69: 8 | K69: 1 | L69: 1 | M69: 1 | N69: 1 | O69: Pure rough soil digging and loosening without banking or clod pulverization: 29.60 man-hrs / 10 cum (3.70 bd). Daily output: 2.703 cum per 8-hr shift.
A70: Embankment banking excl digging (10 cum) | B70: Breaking clods & shaping slope profile | C70: 0114 | D70: Beldar (Semi-Skilled / Operational Earthwork) | E70: 10 | F70: cum | G70: 2 | H70: 8.8 | I70: 1 | J70: 8 | K70: 1 | L70: 1 | M70: 1 | N70: 1 | O70: Pulverizing clods, leveling into 20 cm layers and shaping embankment slope profiles: 17.60 man-hrs / 10 cum (2.20 bd). Daily output: 4.545 cum per 8-hr shift. (Full cycle = 3.70 dig + 2.20 bank = 5.90 bd).
A71: Embankment banking excl digging (10 cum) | B71: Haulage & layer spreading | C71: 0115 | D71: Coolie (Unskilled / Haulage & Spoil Handling) | E71: 10 | F71: cum | G71: 3 | H71: 9.6 | I71: 1 | J71: 8 | K71: 1 | L71: 1 | M71: 1 | N71: 1 | O71: Haulage within 50m lead and spreading in layers not exceeding 20cm.
A72: Embankment banking excl digging (10 cum) | B72: OMC compaction layer watering | C72: 0101 | D72: Bhishti (Compaction Layer Watering to OMC) | E72: 10 | F72: cum | G72: 1 | H72: 3.2 | I72: 1 | J72: 8 | K72: 1 | L72: 1 | M72: 1 | N72: 1 | O72: Compaction watering: 25 cum conditioned per 8-hr shift.
A73: Embankment banking excl digging (10 cum) | B73: 8-10t power rolling 6 passes | C73: 0011 | D73: Road Roller 8-10t Diesel Power (incl Fuel & Crew) | E73: 10 | F73: cum | G73: 1 | H73: 0.064 | I73: 1 | J73: 8 | K73: 1 | L73: 1 | M73: 1 | N73: 1 | O73: Layer consolidation: 1250 cum per 8-hr shift (0.008 machine-day per 10 cum).
A74: Deduct not rolling embankment (10 cum) | B74: Omission of 8-10t power rolling | C74: 0011 | D74: Road Roller 8-10t Diesel Power (incl Fuel & Crew) | E74: 10 | F74: cum | G74: -1 | H74: 0.064 | I74: 1 | J74: 8 | K74: 1 | L74: 1 | M74: 1 | N74: 1 | O74: Reverses the 8-10t road roller compaction allowance where embankment rolling is omitted: -0.008 roller-day.
... A89: Clearing jungle & rank vegetation (100 sqm) | B89: Stacking & disposal outside 50m periphery | C89: 0115 | D89: Coolie (Unskilled / Haulage & Spoil Handling) | E89: 100 | F89: sqm | G89: 1 | H89: 1.6 | I89: 1 | J89: 8 | K89: 1 | L89: 1 | M89: 1 | N89: 1 | O89: Stacking cut brushwood and carrying all unserviceable debris outside 50 m perimeter (500 sqm/day).
A90: 5. RUNNING CUSTOM NON-DSR ITEMS LIBRARY FOR EARTH WORK
A91: Log custom non-DSR earthwork rate analyses below. Results generated above can be archived here for tender schedules.
A92: Custom Code | B92: Item Nomenclature / Scope | C92: Unit | D92: Batch | E92: Mode | F92: CPOH Base | G92: Direct Cost W (₹) | H92: Unit Rate (₹) | I92: Say Rate (₹) | J92: Status | K92: Technical Basis & Remarks
A93: C-02.01 | B93: Earth work surface excavation in soil ≤30cm depth (DAR baseline) | C93: sqm | D93: 100 | E93: DIRECT | F93: W | G93: 6919.2 | H93: 92.55 | I93: 92.55 | J93: COMPLETE | K93: Standard DAR surface excavation benchmark
A94: C-02.02 | B94: Earth work rough excavation, banking, watering & rolling (DAR baseline) | C94: cum | D94: 10 | E94: DIRECT | F94: W | G94: 5581.72 | H94: 746.8 | I94: 746.8 | J94: COMPLETE | K94: Standard DAR embankment benchmark
A95: C-02.03 | B95: Hydraulic excavator 0.9 cum area excavation (DAR baseline) | C95: cum | D95: 10 | E95: DIRECT | F95: W | G95: 1358 | H95: 181.85 | I95: 181.85 | J95: COMPLETE | K95: Standard DAR excavator benchmark
A96: C-02.04 | B96: (Available for custom earthwork specification) | C96: cum | D96: 10 | E96: DIRECT | F96: W | J96: DRAFT | K96: Custom item slot
A97: C-02.05 | B97: (Available for custom earthwork specification) | C97: cum | D97: 10 | E97: DIRECT | F97: W | J97: DRAFT | K97: Custom item slot
A98: C-02.06 | B98: (Available for custom earthwork specification) | C98: sqm | D98: 100 | E98: DIRECT | F98: W | J98: DRAFT | K98: Custom item slot
A99: C-02.07 | B99: (Available for custom earthwork specification) | C99: cum | D99: 10 | E99: DIRECT | F99: W | J99: DRAFT | K99: Custom item slot
A100: C-02.08 | B100: (Available for custom earthwork specification) | C100: m | D100: 100 | E100: DIRECT | F100: W | J100: DRAFT | K100: Custom item slot
A102: TABLE 5E — GROUND-TRUTH RESOURCE NORMS & ACTIVITY SPECIFICATION CATALOG (178 Verified Records)
A103: Ground-truth reference norms transcribed from official CPWD DAR 2019 Volume 1 (Sub-Head 02: Earth Work, PDF pages 88-140). Organized into 15 high-value engineering columns. Cost Contribution (%) identifies equipment- vs. labor-heavy activities. All rate analysis builds directly from this database.
A104: Primary Work Scope | B104: Ground Strata / Material | C104: Execution Method & Depth Condition | D104: Operation / Task Specification | E104: Standard Batch Output | F104: Resource Category | G104: Resource Code | H104: Resource Description & Role | I104: Norm Input Qty | J104: Resource Unit | K104: Unit Rate (₹) | L104: Line Amount (₹) | M104: Cost Share % | N104: Productivity & Daily Output Norm | O104: Engineering First-Principles & CPWD 8-Hour Shift Logic | AA104: Master Activity Full Key | AB104: Master Fallback Key | AC104: Batch Qty | AD104: Batch Unit | AE104: Published Say Rate (₹) | AF104: Official Nomenclature | AG104: Loosening Lever | AH104: Handling Lever | AI104: Spreading Lever | AJ104: Watering Lever | AK104: Compaction Lever | AL104: Task / Operation Specification Options (D9 Dropdown Source)
A105: Surface Excavation (≤30 cm) | B105: All kinds of soil | C105: Manual labor (depth ≤1.5m) | D105: General surface cut (≤30 cm deep) | E105: 100 sqm | F105: Labour (Semi-Skilled / Operational) | G105: 0114 | H105: Beldar | I105: 6.8 | J105: day | K105: 558 | L105: 3794.4 | M105: 54.8 | N105: 14.705882 | O105: 4 men × 13.60 h = 54.40 man-hrs ÷ 8 = 6.80 bd. Pickaxe crust loosening: 14.71 sqm/8-hr day (0.544 hr/sqm, 32.6 min/sqm pace). | P105: Surface Excavation (≤30 cm)|All kinds of soil|Manual labor (depth ≤1.5m)|General surface cut (≤30 cm deep)|1 | Q105: 1 | R105: 100 | S105: sqm | T105: 92.55 | U105: Manual Pickaxe / Beldar | V105: Manual Basket (≤50m lead, ≤1.5m lift) | W105: Dressing & grading surface | X105: None | Y105: None | AA105: Surface Excavation (≤30 cm)|All kinds of soil|Manual labor (depth ≤1.5m)|General surface cut (≤30 cm deep) | AB105: Surface Excavation (≤30 cm)|All kinds of soil|Manual labor (depth ≤1.5m) | AC105: 100 | AD105: sqm | AE105: 92.55 | AF105: Earth work in surface excavation not exceeding 30 cm in depth but exceeding 1.5 m in width as well as 10 sqm on plan including getting out and disposal of excavated earth upto 50 m and lift upto 1.5 m, as directed by Engineer-in- Charge:: All kinds of soil Details of cost for 100 Sqm LABOUR | AG105: Manual Pickaxe / Beldar | AH105: Manual Basket (≤50m lead, ≤1.5m lift) | AI105: Dressing & grading surface | AJ105: None | AK105: None | AL105: Banking & rolling only (excavation excluded)
A106: Surface Excavation (≤30 cm) | B106: All kinds of soil | C106: Manual labor (depth ≤1.5m) | D106: General surface cut (≤30 cm deep) | E106: 100 sqm | F106: Labour (Unskilled / Haulage) | G106: 0115 | H106: Coolie | I106: 5.6 | J106: day | K106: 558 | L106: 3124.8 | M106: 45.2 | N106: 17.857143 | O106: 4 men × 11.20 h = 44.80 man-hrs ÷ 8 = 5.60 cd. Basket haulage & 50m disposal: 17.86 sqm/8-hr day (0.448 hr/sqm, 26.9 min/sqm pace). | P106: Surface Excavation (≤30 cm)|All kinds of soil|Manual labor (depth ≤1.5m)|General surface cut (≤30 cm deep)|2 | Q106: 2 | R106: 100 | S106: sqm | T106: 92.55 | U106: Manual Pickaxe / Beldar | V106: Manual Basket (≤50m lead, ≤1.5m lift) | W106: Dressing & grading surface | X106: None | Y106: None | AA106: Foundation & Pipeline Trenching|All kinds of soil|Manual labor (depth ≤1.5m)|Pipe / Cable trenches (dia ≤ 80 mm) | AB106: Foundation & Pipeline Trenching|All kinds of soil|Manual labor (depth ≤1.5m) | AC106: 1 | AD106: m | AE106: 223 | AF106: CPWD DAR Item 2.10.1.1 - Earth Work | AG106: Narrow trench spade / pickaxe | AH106: Basket Coolie along trench edge | AI106: Trench bank disposal | AJ106: None | AK106: None | AL106: Clearing grass & removal of rubbish
A107: Embankment Banking & Dressing | B107: All kinds of soil | C107: Manual labor (depth ≤1.5m) | D107: Full cycle: rough excavation + banking + roll | E107: 10 cum | F107: Labour (Semi-Skilled / Operational) | G107: 0114 | H107: Beldar | I107: 5.9 | J107: day | K107: 558 | L107: 3292.2 | M107: 59 | N107: 1.6949153 | O107: 4 men × 11.80 h = 47.20 man-hrs ÷ 8 = 5.90 bd. Digging (3.70 bd) + clod breaking & slope dressing (2.20 bd) = 5.90 bd. Daily output: 1.695 cum/8-hr day. | P107: Embankment Banking & Dressing|All kinds of soil|Manual labor (depth ≤1.5m)|Full cycle: rough excavation + banking + roll|1 | Q107: 1 | R107: 10 | S107: cum | T107: 746.8 | U107: Rough excavation by Beldar | V107: Basket Coolie (50m lead / 1.5m lift) | W107: Spreading in 20cm layers & breaking clods | X107: Watering to OMC by Bhishti | Y107: 8-10t Power Roller (every 3rd & top layer) | AA107: Foundation & Pipeline Trenching|All kinds of soil|Manual labor (depth ≤1.5m)|Pipe / Cable trenches (dia 80-300 mm) | AB107: Foundation & Pipeline Trenching|All kinds of soil|Manual labor (depth ≤1.5m) | AC107: 1 | AD107: m | AE107: 364.2 | AF107: CPWD DAR Item 2.10.1.2 - Earth Work | AG107: Narrow trench spade / pickaxe | AH107: Basket Coolie along trench edge | AI107: Trench bank disposal | AJ107: None | AK107: None | AL107: Clearing jungle & rank vegetation uprooting
A108: Embankment Banking & Dressing | B108: All kinds of soil | C108: Manual labor (depth ≤1.5m) | D108: Full cycle: rough excavation + banking + roll | E108: 10 cum | F108: Labour (Unskilled / Haulage) | G108: 0115 | H108: Coolie | I108: 3.6 | J108: day | K108: 558 | L108: 2008.8 | M108: 36 | N108: 2.7777778 | O108: 3 men × 9.60 h = 28.80 man-hrs ÷ 8 = 3.60 cd. 50m haulage & 20cm layer spreading: 1 Coolie moves 2.778 cum/8-hr day (2.88 hr/cum). | P108: Embankment Banking & Dressing|All kinds of soil|Manual labor (depth ≤1.5m)|Full cycle: rough excavation + banking + roll|2 | Q108: 2 | R108: 10 | S108: cum | T108: 746.8 | U108: Rough excavation by Beldar | V108: Basket Coolie (50m lead / 1.5m lift) | W108: Spreading in 20cm layers & breaking clods | X108: Watering to OMC by Bhishti | Y108: 8-10t Power Roller (every 3rd & top layer) | AA108: Foundation & Pipeline Trenching|All kinds of soil|Manual labor (depth ≤1.5m)|Pipe / Cable trenches (dia > 300 mm) | AB108: Foundation & Pipeline Trenching|All kinds of soil|Manual labor (depth ≤1.5m) | AC108: 1 | AD108: m | AE108: 568.8 | AF108: CPWD DAR Item 2.10.1.3 - Earth Work | AG108: Pickaxe & shovel Beldar | AH108: Basket Coolie along trench edge | AI108: Trench bank disposal | AJ108: None | AK108: None | AL108: Close timbering depth 1.5m-3.0m (90 sqm face)
A109: Embankment Banking & Dressing | B109: All kinds of soil | C109: Manual labor (depth ≤1.5m) | D109: Full cycle: rough excavation + banking + roll | E109: 10 cum | F109: Labour (Operational / Bhishti) | G109: 0101 | H109: Bhisti | I109: 0.4 | J109: day | K109: 617 | L109: 246.8 | M109: 4.4 | N109: 25 | O109: 1 man × 3.20 h = 3.20 man-hrs ÷ 8 = 0.40 bhisti-day. OMC compaction watering: 25 cum/8-hr day (0.32 hr/cum). | P109: Embankment Banking & Dressing|All kinds of soil|Manual labor (depth ≤1.5m)|Full cycle: rough excavation + banking + roll|3 | Q109: 3 | R109: 10 | S109: cum | T109: 746.8 | U109: Rough excavation by Beldar | V109: Basket Coolie (50m lead / 1.5m lift) | W109: Spreading in 20cm layers & breaking clods | X109: Watering to OMC by Bhishti | Y109: 8-10t Power Roller (every 3rd & top layer) | AA109: Foundation & Pipeline Trenching|All kinds of soil|Extra depth >1.5m to 3.0m|Extra for pipe trench depth 1.5m to 3.0m | AB109: Foundation & Pipeline Trenching|All kinds of soil|Extra depth >1.5m to 3.0m | AC109: 1 | AD109: m | AE109: 127 | AF109: Extra for excavating trenches for pipes, cables etc. in all kinds of soil for depth exceeding 1.5 m, but not exceeding 3 m. (Rate is over corresponding basic item for depth upto 1.5 metre). Details of cost for 300m length of pipe of an average dia. say 200mm (rate in percentage), Slope assumed 1 in 200. 100x0.60x1.75 = 105.00 cum, 200x 0.60x2.00 = 240.00 cum. Total = 345.00 cum. Collars 5%= 17.25 cum. Total = 362.25 cum. | AG109: Deep trench pickaxe | AH109: Double handling stage lift | AI109: Trench bank disposal | AJ109: None | AK109: None | AL109: Close timbering depth 3.0m-4.5m (90 sqm face)
A110: Embankment Banking & Dressing | B110: All kinds of soil | C110: Manual labor (depth ≤1.5m) | D110: Full cycle: rough excavation + banking + roll | E110: 10 cum | F110: Sundries & Allowances | G110: 0113 | H110: Chowkidar | I110: 0.008 | J110: day | K110: 558 | L110: 4.46 | M110: 0.1 | N110: 1250 | O110: 1 machine × 0.064 h (3.84 min) ÷ 8 = 0.008 roller-day. 6 passes at 2.5 km/h on 1.8m roll: 156.25 cum/hr (1250 cum/8-hr shift). | P110: Embankment Banking & Dressing|All kinds of soil|Manual labor (depth ≤1.5m)|Full cycle: rough excavation + banking + roll|4 | Q110: 4 | R110: 10 | S110: cum | T110: 746.8 | U110: Rough excavation by Beldar | V110: Basket Coolie (50m lead / 1.5m lift) | W110: Spreading in 20cm layers & breaking clods | X110: Watering to OMC by Bhishti | Y110: 8-10t Power Roller (every 3rd & top layer) | AA110: Foundation & Pipeline Trenching|All kinds of soil|Extra depth >3.0m to 4.5m|Extra for pipe trench depth 3.0m to 4.5m | AB110: Foundation & Pipeline Trenching|All kinds of soil|Extra depth >3.0m to 4.5m | AC110: 1 | AD110: m | AE110: 315.05 | AF110: Extra for excavating trenches for pipes, cables, etc, in all kinds of soil for depth exceeding 3 m in depth, but not exceeding 4.5 m. (Rate is over corresponding basic item for depth upto 1.5 metre.) Details of cost for a 100m length of a pipe of an average dia. say 200mm Slope assumed 1 in 200. Earth work and filling- 1x100x0.60x2 = 120 cum Collars 5% = 6 cum. Total = 126 cum. | AG110: Deep trench pickaxe | AH110: Triple stage hoist / lift | AI110: Trench bank disposal | AJ110: None | AK110: None | AL110: Close timbering depth ≤1.5m (90 sqm face)
A111: Embankment Banking & Dressing | B111: All kinds of soil | C111: Manual labor (depth ≤1.5m) | D111: Full cycle: rough excavation + banking + roll | E111: 10 cum | F111: Plant & Machinery | G111: 0003 | H111: Hire – Diesel Road Roller 8-10t | I111: 0.008 | J111: day | K111: 3000 | L111: 24 | M111: 0.4 | N111: 1250 | O111: 1 machine × 0.064 h (3.84 min) ÷ 8 = 0.008 roller-day. 6 passes with 8-10t roller: 1250 cum/8-hr shift. | P111: Embankment Banking & Dressing|All kinds of soil|Manual labor (depth ≤1.5m)|Full cycle: rough excavation + banking + roll|5 | Q111: 5 | R111: 10 | S111: cum | T111: 746.8 | U111: Rough excavation by Beldar | V111: Basket Coolie (50m lead / 1.5m lift) | W111: Spreading in 20cm layers & breaking clods | X111: Watering to OMC by Bhishti | Y111: 8-10t Power Roller (every 3rd & top layer) | AA111: Foundation & Pipeline Trenching|Ordinary rock|Manual labor (depth ≤1.5m)|Pipe trenches in ordinary rock (≤80mm) | AB111: Foundation & Pipeline Trenching|Ordinary rock|Manual labor (depth ≤1.5m) | AC111: 1 | AD111: m | AE111: 323.85 | AF111: CPWD DAR Item 2.13.1.1 - Earth Work | AG111: Crowbar & sledge hammer | AH111: Basket Coolie along trench edge | AI111: Trench bank disposal | AJ111: None | AK111: None | AL111: DEDUCT: Omission of 8-10t power rolling
A112: Embankment Banking & Dressing | B112: All kinds of soil | C112: Manual labor (depth ≤1.5m) | D112: Full cycle: rough excavation + banking + roll | E112: 10 cum | F112: Sundries & Allowances | G112: 9999 | H112: Sundries | I112: 2.73 | J112: L.S. | K112: 2 | L112: 5.46 | M112: 0.1 | O112: Direct production cost W base allowance. | P112: Embankment Banking & Dressing|All kinds of soil|Manual labor (depth ≤1.5m)|Full cycle: rough excavation + banking + roll|6 | Q112: 6 | R112: 10 | S112: cum | T112: 746.8 | U112: Rough excavation by Beldar | V112: Basket Coolie (50m lead / 1.5m lift) | W112: Spreading in 20cm layers & breaking clods | X112: Watering to OMC by Bhishti | Y112: 8-10t Power Roller (every 3rd & top layer) | AA112: Timbering & Shoring|All kinds of soil|Manual labor (depth ≤1.5m)|Close timbering depth ≤1.5m (90 sqm face) | AB112: Timbering & Shoring|All kinds of soil|Manual labor (depth ≤1.5m) | AC112: 90 | AD112: sqm | AE112: 129.95 | AF112: Close timbering in trenches including strutting, shoring and packing cavities (wherever required) complete. (Measurements to be taken of the face area timbered).: Depth not exceeding 1.5 m Details of cost for a trench 30m long and 1.5m deep area 2x30x1.50=90 sqm MATERIAL The Material can be used four times on the same work and after use of material credit is given @ 75% of cost Poling boards of | AG112: Sal wood runners, open/close poling boards | AH112: Lowering into trench & positioning | AI112: Strutting with adjustable screw jacks / timber | AJ112: None | AK112: Tight wedge wedging against trench sides | AL112: DEDUCT: Omission of OMC compaction watering
A113: Embankment Banking & Dressing | B113: All kinds of soil | C113: Manual labor (depth ≤1.5m) | D113: Banking & rolling only (excavation excluded) | E113: 10 cum | F113: Labour (Semi-Skilled / Operational) | G113: 0114 | H113: Beldar | I113: 2.2 | J113: day | K113: 558 | L113: 1227.6 | M113: 34.9 | N113: 4.5454545 | O113: 2 men × 8.80 h = 17.60 man-hrs ÷ 8 = 2.20 bd. Clod breaking, layer placement & section profiling: 4.545 cum/8-hr day. (Excavation digging 3.70 bd excluded: 5.90 - 3.70 = 2.20 bd). | P113: Embankment Banking & Dressing|All kinds of soil|Manual labor (depth ≤1.5m)|Banking & rolling only (excavation excluded)|1 | Q113: 1 | R113: 10 | S113: cum | T113: 470.55 | U113: Earth already excavated (excluded) | V113: Basket Coolie lead 50m / lift 1.5m | W113: Spreading in 20cm layers & breaking clods | X113: Watering to OMC by Bhishti | Y113: 8-10t Power Roller (every 3rd & top layer) | AA113: Timbering & Shoring|All kinds of soil|Extra depth >1.5m to 3.0m|Close timbering depth 1.5m-3.0m (90 sqm face) | AB113: Timbering & Shoring|All kinds of soil|Extra depth >1.5m to 3.0m | AC113: 90 | AD113: sqm | AE113: 141.2 | AF113: Close timbering in trenches including strutting, shoring and packing cavities (wherever required) complete. (Measurements to be taken of the face area timbered).: Depth exceeding 1.5 m but not exceeding 3 m Details of cost for a trench 30m long and 1.5m deep Area 2x30x1.50=90 sqm MATERIAL The Material can be used four times on the same work and after use of material credit is given @ 75% of cost Poling boards of | AG113: Sal wood runners, open/close poling boards | AH113: Lowering into trench & positioning | AI113: Strutting with adjustable screw jacks / timber | AJ113: None | AK113: Tight wedge wedging against trench sides | AL113: Excavating post holes 0.1-0.5 cum in hard rock blast
A114: Embankment Banking & Dressing | B114: All kinds of soil | C114: Manual labor (depth ≤1.5m) | D114: Banking & rolling only (excavation excluded) | E114: 10 cum | F114: Labour (Unskilled / Haulage) | G114: 0115 | H114: Coolie | I114: 3.6 | J114: day | K114: 558 | L114: 2008.8 | M114: 57.1 | N114: 2.7777778 | O114: 3 men × 9.60 h = 28.80 man-hrs ÷ 8 = 3.60 cd. Haulage & 20cm layer spreading: 2.778 cum/8-hr day. | P114: Embankment Banking & Dressing|All kinds of soil|Manual labor (depth ≤1.5m)|Banking & rolling only (excavation excluded)|2 | Q114: 2 | R114: 10 | S114: cum | T114: 470.55 | U114: Earth already excavated (excluded) | V114: Basket Coolie lead 50m / lift 1.5m | W114: Spreading in 20cm layers & breaking clods | X114: Watering to OMC by Bhishti | Y114: 8-10t Power Roller (every 3rd & top layer) | AA114: Timbering & Shoring|All kinds of soil|Extra depth >3.0m to 4.5m|Close timbering depth 3.0m-4.5m (90 sqm face) | AB114: Timbering & Shoring|All kinds of soil|Extra depth >3.0m to 4.5m | AC114: 90 | AD114: sqm | AE114: 166.55 | AF114: Close timbering in trenches including strutting, shoring and packing cavities (wherever required) complete. (Measurements to be taken of the face area timbered).: Depth exceeding 3 m but not exceeding 4.5 m Details of cost for a trench 30m long and 1.5m deep Area 2x30x1.5=90 sqm- MATERIAL The Material can be used four times on the same work and after use of material credit is given @ 75% of cost Poling boards of | AG114: Sal wood runners, open/close poling boards | AH114: Lowering into trench & positioning | AI114: Strutting with adjustable screw jacks / timber | AJ114: None | AK114: Tight wedge wedging against trench sides | AL114: Excavating post holes 0.1-0.5 cum in hard rock chiseled
A115: Embankment Banking & Dressing | B115: All kinds of soil | C115: Manual labor (depth ≤1.5m) | D115: Banking & rolling only (excavation excluded) | E115: 10 cum | F115: Labour (Operational / Bhishti) | G115: 0101 | H115: Bhisti | I115: 0.4 | J115: day | K115: 617 | L115: 246.8 | M115: 7 | N115: 25 | O115: 1 man × 3.20 h = 3.20 man-hrs ÷ 8 = 0.40 bhisti-day. Compaction watering: 25 cum/8-hr day. | P115: Embankment Banking & Dressing|All kinds of soil|Manual labor (depth ≤1.5m)|Banking & rolling only (excavation excluded)|3 | Q115: 3 | R115: 10 | S115: cum | T115: 470.55 | U115: Earth already excavated (excluded) | V115: Basket Coolie lead 50m / lift 1.5m | W115: Spreading in 20cm layers & breaking clods | X115: Watering to OMC by Bhishti | Y115: 8-10t Power Roller (every 3rd & top layer) | AA115: Embankment Banking & Dressing|All kinds of soil|Manual labor (depth ≤1.5m)|Full cycle: rough excavation + banking + roll | AB115: Embankment Banking & Dressing|All kinds of soil|Manual labor (depth ≤1.5m) | AC115: 10 | AD115: cum | AE115: 746.8 | AF115: Earth work in rough excavation, banking excavated earth in layers not exceeding 20cm in depth, breaking clods, watering, rolling each layer with ½ tonne roller or wooden or steel rammers, and rolling every 3rd and top-most layer with power roller of minimum 8 tonnes and dressing up in embankments for roads, flood banks, marginal banks and guide banks or filling up ground depressions, lead upto 50 m and lift upto 1.5 m :: All kinds of soil Details of cost for 10 cum. LABOUR | AG115: Rough excavation by Beldar | AH115: Basket Coolie (50m lead / 1.5m lift) | AI115: Spreading in 20cm layers & breaking clods | AJ115: Watering to OMC by Bhishti | AK115: 8-10t Power Roller (every 3rd & top layer) | AL115: Excavating post holes 0.1-0.5 cum in ord rock
A116: Embankment Banking & Dressing | B116: All kinds of soil | C116: Manual labor (depth ≤1.5m) | D116: Banking & rolling only (excavation excluded) | E116: 10 cum | F116: Sundries & Allowances | G116: 0113 | H116: Chowkidar | I116: 0.008 | J116: day | K116: 558 | L116: 4.46 | M116: 0.1 | N116: 1250 | O116: 1 machine × 0.064 h ÷ 8 = 0.008 roller-day. 6 passes of 8-10t roller: 1250 cum/8-hr shift. | P116: Embankment Banking & Dressing|All kinds of soil|Manual labor (depth ≤1.5m)|Banking & rolling only (excavation excluded)|4 | Q116: 4 | R116: 10 | S116: cum | T116: 470.55 | U116: Earth already excavated (excluded) | V116: Basket Coolie lead 50m / lift 1.5m | W116: Spreading in 20cm layers & breaking clods | X116: Watering to OMC by Bhishti | Y116: 8-10t Power Roller (every 3rd & top layer) | AA116: Foundation & Pipeline Trenching|All kinds of soil|Manual labor (depth ≤1.5m)|Extra for wet/water position (+20%) | AB116: Foundation & Pipeline Trenching|All kinds of soil|Manual labor (depth ≤1.5m) | AC116: 1 | AD116: m-depth | AE116: 20 | AF116: CPWD DAR Item 2.24.1 - Earth Work | AG116: Excavation under wet / foul conditions | AH116: Mud / slush bailing & haulage | AI116: Disposal | AJ116: Submerged / wet | AK116: None | AL116: Excavating post holes 0.1-0.5 cum in soil
A117: Embankment Banking & Dressing | B117: All kinds of soil | C117: Manual labor (depth ≤1.5m) | D117: Banking & rolling only (excavation excluded) | E117: 10 cum | F117: Plant & Machinery | G117: 0003 | H117: Hire – Diesel Road Roller 8-10t | I117: 0.008 | J117: day | K117: 3000 | L117: 24 | M117: 0.7 | N117: 1250 | P117: Embankment Banking & Dressing|All kinds of soil|Manual labor (depth ≤1.5m)|Banking & rolling only (excavation excluded)|5 | Q117: 5 | R117: 10 | S117: cum | T117: 470.55 | U117: Earth already excavated (excluded) | V117: Basket Coolie lead 50m / lift 1.5m | W117: Spreading in 20cm layers & breaking clods | X117: Watering to OMC by Bhishti | Y117: 8-10t Power Roller (every 3rd & top layer) | AA117: Foundation & Pipeline Trenching|All kinds of soil|Manual labor (depth ≤1.5m)|Extra for foul position (+25%) | AB117: Foundation & Pipeline Trenching|All kinds of soil|Manual labor (depth ≤1.5m) | AC117: 1 | AD117: m-depth | AE117: 25 | AF117: CPWD DAR Item 2.24.2 - Earth Work | AG117: Excavation under wet / foul conditions | AH117: Mud / slush bailing & haulage | AI117: Disposal | AJ117: Submerged / wet | AK117: None | AL117: Extra for foul position (+25%)
A118: Embankment Banking & Dressing | B118: All kinds of soil | C118: Manual labor (depth ≤1.5m) | D118: Banking & rolling only (excavation excluded) | E118: 10 cum | F118: Sundries & Allowances | G118: 9999 | H118: Sundries | I118: 2.73 | J118: L.S. | K118: 2 | L118: 5.46 | M118: 0.2 | P118: Embankment Banking & Dressing|All kinds of soil|Manual labor (depth ≤1.5m)|Banking & rolling only (excavation excluded)|6 | Q118: 6 | R118: 10 | S118: cum | T118: 470.55 | U118: Earth already excavated (excluded) | V118: Basket Coolie lead 50m / lift 1.5m | W118: Spreading in 20cm layers & breaking clods | X118: Watering to OMC by Bhishti | Y118: 8-10t Power Roller (every 3rd & top layer) | AA118: Backfilling & Compaction|All kinds of soil|Manual labor (depth ≤1.5m)|Filling available excavated earth in plinth/trenches | AB118: Backfilling & Compaction|All kinds of soil|Manual labor (depth ≤1.5m) | AC118: 10 | AD118: cum | AE118: 219.65 | AF118: Filling available excavated earth (excluding rock) in trenches, plinth, sides of foundations etc. in layers not exceeding 20cm in depth, consolidating each deposited layer by ramming and watering, lead up to 50 m and lift upto 1.5 m. Details of cost for 10 cum. LABOUR | AG118: Available excavated spoil (no digging) | AH118: Basket Coolie return lead ≤50m | AI118: Spreading in layers ≤20 cm | AJ118: Watering each layer | AK118: Durmat ramming / hand compaction | AL118: Extra for pipe trench depth 1.5m to 3.0m
A119: Embankment Banking & Dressing | B119: All kinds of soil | C119: Manual labor (depth ≤1.5m) | D119: DEDUCT: Omission of 8-10t power rolling | E119: 10 cum | F119: Sundries & Allowances | G119: 0113 | H119: Chowkidar | I119: 0.008 | J119: day | K119: 558 | L119: 4.46 | M119: 13.9 | N119: 1250 | O119: Reverses 8-10t road roller compaction allowance where embankment rolling is omitted: -0.008 roller-day. | P119: Embankment Banking & Dressing|All kinds of soil|Manual labor (depth ≤1.5m)|DEDUCT: Omission of 8-10t power rolling|1 | Q119: 1 | R119: 10 | S119: cum | T119: -4.3 | U119: None | V119: None | W119: None | X119: None | Y119: CREDIT: Deduct 8-10t roller cost | AA119: Foundation & Pipeline Trenching|All kinds of soil|Extra depth >1.5m to 3.0m|Extra lift for every additional 1.5m | AB119: Foundation & Pipeline Trenching|All kinds of soil|Extra depth >1.5m to 3.0m | AC119: 10 | AD119: cum | AE119: 90.4 | AF119: Extra for every additional lift of 1.5 m or part thereof in excavation / banking excavated or stacked materials.: All kinds of soil Details of cost for 10 cum. LABOUR | AG119: Deep excavation lift | AH119: Staged manual lifting per 1.5m | AI119: Disposal | AJ119: None | AK119: None | AL119: Extra for pipe trench depth 3.0m to 4.5m
...
